[{"username":"[14]Last_Try","items_sell":{},"items_buy":{},"price_sell":{},"price_buy":{},"count_sell":{},"count_buy":{},"ostime":1756646475,"LavkaUid":66},{"username":"[04]Vladislav_Hoffman","items_sell":{},"items_buy":{},"price_sell":{},"price_buy":{},"count_sell":{},"count_buy":{},"ostime":1756646475,"LavkaUid":31},{"username":"[15]Aron_McCloud","items_sell":{},"items_buy":{},"price_sell":{},"price_buy":{},"count_sell":{},"count_buy":{},"ostime":1756646476,"LavkaUid":224},{"username":"[25]Visual_Basic","items_sell":{},"items_buy":{},"price_sell":{},"price_buy":{},"count_sell":{},"count_buy":{},"ostime":1756646477,"LavkaUid":268},{"username":"[13]Rampage_Note","items_sell":{},"items_buy":{},"price_sell":{},"price_buy":{},"count_sell":{},"count_buy":{},"ostime":1756646477,"LavkaUid":343},{"username":"[04]Svyatopolk_Knyazev","items_sell":{},"items_buy":{},"price_sell":{},"price_buy":{},"count_sell":{},"count_buy":{},"ostime":1756646475,"LavkaUid":294},{"username":"[07]Vladislav_Lisov","items_sell":{},"items_buy":{},"price_sell":{},"price_buy":{},"count_sell":{},"count_buy":{},"ostime":1756646477,"LavkaUid":154},{"username":"[31]Maki_Ma","items_sell":{},"items_buy":{},"price_sell":{},"price_buy":{},"count_sell":{},"count_buy":{},"ostime":1756646477,"LavkaUid":191},{"username":"[01]Corvus_Bond","items_sell":{},"items_buy":{},"price_sell":{},"price_buy":{},"count_sell":{},"count_buy":{},"ostime":1756646477,"LavkaUid":137},{"username":"[17]Chappa_VneZemnoi","items_sell":{},"items_buy":{},"price_sell":{},"price_buy":{},"count_sell":{},"count_buy":{},"ostime":1756646478,"LavkaUid":117},{"username":"[01]Sebastian_Ford","items_sell":{},"items_buy":{},"price_sell":{},"price_buy":{},"count_sell":{},"count_buy":{},"ostime":1756646478,"LavkaUid":178},{"username":"[07]Suguru_Getou","items_sell":{},"items_buy":{},"price_sell":{},"price_buy":{},"count_sell":{},"count_buy":{},"ostime":1756646478,"LavkaUid":194},{"username":"[13]Sawyer_Smit","items_sell":{},"items_buy":{},"price_sell":{},"price_buy":{},"count_sell":{},"count_buy":{},"ostime":1756646477,"LavkaUid":315},{"username":"[31]Ivy_Craft","items_sell":{},"items_buy":{},"price_sell":{},"price_buy":{},"count_sell":{},"count_buy":{},"ostime":1756646477,"LavkaUid":171},{"username":"[25]Xpuctoc_Bockpec","items_sell":{},"items_buy":{},"price_sell":{},"price_buy":{},"count_sell":{},"count_buy":{},"ostime":1756646476,"LavkaUid":149},{"username":"[31]Youpi_Yee","items_sell":{},"items_buy":{},"price_sell":{},"price_buy":{},"count_sell":{},"count_buy":{},"ostime":1756646477,"LavkaUid":158},{"username":"[28]Stark_Darkside","items_sell":{},"items_buy":{},"price_sell":{},"price_buy":{},"count_sell":{},"count_buy":{},"ostime":1756646476,"LavkaUid":254},{"username":"[06]Lavka_Parker","items_sell":{},"items_buy":{},"price_sell":{},"price_buy":{},"count_sell":{},"count_buy":{},"ostime":1756646477,"LavkaUid":72},{"username":"[01]Katashi_Aoki","items_sell":{},"items_buy":{},"price_sell":{},"price_buy":{},"count_sell":{},"count_buy":{},"ostime":1756646474,"LavkaUid":148},{"username":"[18]Integra_Hellsing","items_sell":{},"items_buy":{},"price_sell":{},"price_buy":{},"count_sell":{},"count_buy":{},"ostime":1756646477,"LavkaUid":198},{"username":"[03]Extra_Brown","items_sell":{},"items_buy":{},"price_sell":{},"price_buy":{},"count_sell":{},"count_buy":{},"ostime":1756646477,"LavkaUid":61},{"username":"[07]Kay_Neal","items_sell":{},"items_buy":{},"price_sell":{},"price_buy":{},"count_sell":{},"count_buy":{},"ostime":1756646477,"LavkaUid":138},{"username":"[21]Crozz_Miretky","items_sell":{},"items_buy":{},"price_sell":{},"price_buy":{},"count_sell":{},"count_buy":{},"ostime":1756646475,"LavkaUid":51},{"username":"[02]Garik_Chester","items_sell":{},"items_buy":{},"price_sell":{},"price_buy":{},"count_sell":{},"count_buy":{},"ostime":1756646475,"LavkaUid":232},{"username":"[02]Doni_Morrison","items_sell":{},"items_buy":{},"price_sell":{},"price_buy":{},"count_sell":{},"count_buy":{},"ostime":1756646477,"LavkaUid":173},{"username":"[07]Suare_Citizen","items_sell":{},"items_buy":{},"price_sell":{},"price_buy":{},"count_sell":{},"count_buy":{},"ostime":1756646478,"LavkaUid":83},{"username":"[07]Frank_Buscemi","items_sell":{},"items_buy":{},"price_sell":{},"price_buy":{},"count_sell":{},"count_buy":{},"ostime":1756646478,"LavkaUid":37},{"username":"[18]Despair_Rampage","items_sell":{},"items_buy":{},"price_sell":{},"price_buy":{},"count_sell":{},"count_buy":{},"ostime":1756646476,"LavkaUid":333},{"username":"[06]Nama_Warden","items_sell":{},"items_buy":{},"price_sell":{},"price_buy":{},"count_sell":{},"count_buy":{},"ostime":1756646477,"LavkaUid":93},{"username":"[14]Alex_Freegamer","items_sell":{},"items_buy":{},"price_sell":{},"price_buy":{},"count_sell":{},"count_buy":{},"ostime":1756646477,"LavkaUid":251},{"username":"[29]Heinz_Weber","items_sell":{},"items_buy":{},"price_sell":{},"price_buy":{},"count_sell":{},"count_buy":{},"ostime":1756646477,"LavkaUid":77},{"username":"[10]Fredy_Schumacher","items_sell":{},"items_buy":{},"price_sell":{},"price_buy":{},"count_sell":{},"count_buy":{},"ostime":1756646475,"LavkaUid":260},{"username":"[18]Anderson_Shaw","items_sell":{},"items_buy":{},"price_sell":{},"price_buy":{},"count_sell":{},"count_buy":{},"ostime":1756646477,"LavkaUid":267},{"username":"[07]Tommy_Vaprosi","items_sell":{},"items_buy":{},"price_sell":{},"price_buy":{},"count_sell":{},"count_buy":{},"ostime":1756646477,"LavkaUid":223},{"username":"[07]Rick_Hunter","items_sell":{},"items_buy":{},"price_sell":{},"price_buy":{},"count_sell":{},"count_buy":{},"ostime":1756646477,"LavkaUid":220},{"username":"[10]Katana_Gold","items_sell":{},"items_buy":{},"price_sell":{},"price_buy":{},"count_sell":{},"count_buy":{},"ostime":1756646477,"LavkaUid":258},{"username":"[16]Duck_Veslep","items_sell":{},"items_buy":{},"price_sell":{},"price_buy":{},"count_sell":{},"count_buy":{},"ostime":1756646508,"LavkaUid":111},{"username":"[31]Ryo_Tov","items_sell":["Альтушка (ID: 1006)(+10)","Генеральский бронежилет(+4)","Энергетический чемодан","Энергетический КУРА шар(+13)","Энергетический махинатор(+13)","Маска-невидимка(+13)","Часы 'Gucci'(+13)","Бейсбольная бита Compton(+13)","Звездный нимб(+13)"],"items_buy":{},"price_sell":[100000000,47000000,26000000,55000000,110000000,80000000,20000000,20000000,120000000],"price_buy":{},"count_sell":[1,1,1,1,1,1,1,1,1],"count_buy":{},"ostime":1756646433,"LavkaUid":168},{"username":"[07]Aineri_Flamel","items_sell":{},"items_buy":{},"price_sell":{},"price_buy":{},"count_sell":{},"count_buy":{},"ostime":1756646477,"LavkaUid":203},{"username":"[14]Young_Seller","items_sell":{},"items_buy":{},"price_sell":{},"price_buy":{},"count_sell":{},"count_buy":{},"ostime":1756646477,"LavkaUid":234},{"username":"[06]Zoe_Milton","items_sell":{},"items_buy":{},"price_sell":{},"price_buy":{},"count_sell":{},"count_buy":{},"ostime":1756646477,"LavkaUid":281},{"username":"[03]Vladimir_Masker","items_sell":{},"items_buy":{},"price_sell":{},"price_buy":{},"count_sell":{},"count_buy":{},"ostime":1756646477,"LavkaUid":255},{"username":"[07]Victor_Satanov","items_sell":{},"items_buy":{},"price_sell":{},"price_buy":{},"count_sell":{},"count_buy":{},"ostime":1756646477,"LavkaUid":229},{"username":"[07]Yota_Nakata","items_sell":{},"items_buy":{},"price_sell":{},"price_buy":{},"count_sell":{},"count_buy":{},"ostime":1756646477,"LavkaUid":159},{"username":"[02]Bounty_Mejer","items_sell":{},"items_buy":{},"price_sell":{},"price_buy":{},"count_sell":{},"count_buy":{},"ostime":1756646477,"LavkaUid":335},{"username":"[07]Gawr_Gura","items_sell":{},"items_buy":["Багажник Таноса","Монета охотника","Заточка для оружия","Нимб 5 звезд","Бейсбольная бита Compton","Цепь СВАГА","Рулетка ужасов","Альтушка (ID: 1006)","Карлик вагос (ID: 1008)","Карлик грув (ID: 1007)","Бойцовский клуб","Обрез (активный аксессуар)","Видеокарта RTX 4090","МайнСкелет","НФТ контейнер (обычный)","НФТ контейнер (средний)","НФТ контейнер (премиум)","Документ для отмывания денег","12 уровень персонажа","Переносной верстак миража","Рюкзак ЯДОСТАВКА","Коса Марси","Лицензия дипломата","Случайный культовый бронежилет","Бронежилет «Атака Титанов»","Бронежилет «Унесенные призраками»","Бронежилет Конь БоДжек»","Бронежилет «Лайт»","Бронежилет «Гравити Фолз»","Бронежилет «Орда»","Бронежилет «Щ.И.Т.»","Бронежилет «Мортал Комбат»","Бронежилет «Игра в кальмара»","Бронежилет «Симпсоны»","Бронежилет «Южный Парк»","Бронежилет «Невермор»","Русский боевой топор","Магмовый топор","Молот Тора","Молот Джейса","Меч ВК","Маска-невидимка","Рука бесконечности","Энергетический двигатель","Сферы инвокера","Перчатка Вай","Руки сэта","Исток","Осколок Истока","AZ-Монеты (Передаваемые)","Танго","Элитная переносная лавка","Складная магическая лавка","Осколок NFT контейнера","Частица космического NFT","Грамота ветерана","Запечатанный сертификат на транспорт","Мидас","Рыбная монета","Дезолятор","Рыбная приманка","Алюминий","Золотой кейс","Желтая инструкция для разбора аксессуара","Инструкция для разбора аксессуара","Инструкция для разбора скинов","Секретный аксессуар","Ящик с секретной машиной","Темная материя","Алмазный камень","Камень","Нашивка на скин (Бег Си Джея)","Нашивка на скин (Бесконечный бег)","Анимированные часы на спину (на спутника)","Анимированный огненный глаз (на спутника)","Маска Муэрты (на спутника)","Шипованный обруч (на спутника)","Золотой Ларец Миража","Осколок Бронежилета Генерала","Админ зарплата","Красное Нитро","Именное поместье","Наёмный фермер","Мешок с мясом","Тайник Собирателя","Осколок Тайника Собирателя","Сертификат бесконечного Дополнения VIP","Сертификат Дополнения VIP","Тайник Vice City","Супер-кирка","Супер-грабли","Ларец лидера","Увеличенный магазин (X3) для Sawnoff","Увеличенный магазин (X3) для Mac-10","Увеличенный магазин (X3) для Desert Eagle","Заточка +13","Осколок предмета Заточка +13","Супер-заточка","Сироп характеристик актера","Twin Turbo (2 уровня)","Увеличенный бак (160 литров)","Ангельское кольцо на голову","Сертификат на безлимитную доставку бочек","Протокол взвешивания","Железная карта нац.банка","Восстановленная карта кладов","Платиновый ящик с секретной машиной","Платиновый осколок ящика секретной машины","Грядка льна","Грядка хлопка","Осколок Молот Тора","Осколок Рука бесконечности","Осколок Щит Капитана Америки","Осколок Русский боевой топор","Осколок Шлем железного человека","Кенгурятник Мародера","Кенгурятник Метельник","Кенгурятник Зомби-Апокалипсиса","Кенгурятник Промышленный","Багажник с Лебедкой","Флешка майнера","Скин: CJ (ID: 74)","Все навыки стрельбы","Вечный индикатор голода","Дополнительная комната","Осколок ящика секретной машины","Заточка для бронежилета","Кусок редкой ткани","Монета Миража","Уголь","Прочная ткань","Шахтерский сплав","Металл","Серебро","Золото","Эхолот для рыбалки","Воздушный шар читера","Грув пончик воздушный шар","Воздушный шар #1","Воздушный шар #2","Воздушный шар #3","Воздушный шар #4","Воздушный шар #5","Воздушный шар #6","Воздушный шар #7","Снегоуборочный бампер [деталь тюнинга]","Рулеточный компас","Талон на 12 x4 PayDay (передаваемый)","Талон снятия предупреждений","Смазка для разгона видеокарты","Охлаждающая жидкость для видеокарты","Платиновая рулетка","Золотая рулетка","Серебряная рулетка","Точильный амулет","Точильный камень","Зловещая монета","Гражданский талон","Подарок","Семейный талон","Ларец инкассатора","Ларец крафтера","Super Car Box","Concept Car Luxury","Ларец Водителя Автобуса","Ларец кастомных аксессуаров","Ларец пилота","Супер авто-ящик","Ларец петуха","Ларец дальнобойщика","Ларец семейных охранников","Ларец рыболова","Ларец Fortnite","Ностальгический ящик","Пасхальный ларец 2024","Ларец с премией","Ларец кладоискателя","Ларец мусорщика","Ларец развозчика продуктов","Одежда из секонд-хенда","Ларец Tidex","Ларец испытателя (Mobile 2.1)","Рандомный Ларец","Супер мото-ящик","Rare Box Yellow","Rare Box Blue","Rare Box Red","Ларец Vice City","Ящик Minecraft","Ящик Marvel","Ларец Mortal Combat","Открыть 6 ячеек инвентаря","Шашка такси (желтая) [деталь тюнинга]","Дифференциал (sport+)","Распредвал (sport+)","КПП (sport+)","Сцепление (sport+)","Турбокомпрессор (sport+)","Подвеска (sport+)","Нагнетатель (sport+)","Полицейская мигалка [деталь тюнинга]","Подиум [деталь тюнинга]","Логотип FBI [деталь тюнинга]","Современная карта кладов","Полицейская мигалка (активная)"],"price_sell":{},"price_buy":[150000,21,120000,200000,200000,200000,3750000,60000000,2500000,2500000,2800000,5000000,12500000,5600000,10000000,11000000,15000000,17500000,1100000,2200000,11000000,8500000,1200000,5500000,5000000,5000000,5000000,5000000,5000000,5000000,5000000,5000000,5000000,5000000,5000000,5000000,3500000,500000,4000000,2500000,1700000,4300000,4500000,12000000,4800000,2200000,700000,500000,1000,550,3500000,9500000,9000000,100000,100000,8250000,2000000,2500000,800,5200000,800000,6000,700000,100000,30000,15000,70000,400000,45000,10000,300,13000000,11000000,4200000,4800000,4500000,2750000,1500000,30000,1000,40000000,21000000,5500000,650000,12000000,450000,9250000,2000000,11500000,3150000,1600000,5000000,7500000,500000,110000,3600000,700000,25000,950000,3200000,3200000,1050000,1500000,1800000,4200000,100000,1900000,170000,2500000,2800000,700000,550000,550000,550000,175000,1250000,1250000,1050000,1050000,950000,1600000,500000,450000,450000,2000000,12000,15000,3300,4500,10000,90000,53000,2000,200,650,450000,2500000,1500000,2200000,2200000,2200000,2200000,2200000,2200000,2200000,700000,700000,1050000,275000,10000,2000,6000,3600,750,2100,110,5100,90,170,225,3900,3000,2950,2700,2700,2500,4000,2500,2650,2400,2500,2300,1600,1550,1250,2100,1600,1200,2000,1100,1000,1000,1000,1050,1000,1000,1000,450,300,300,300,350000,200000,65000,65000,65000,65000,65000,65000,65000,125000,300000,85000,1150000,125000],"count_sell":{},"count_buy":[1,242166,199,1,1,1,5,1,1,1,1,1,1,1,1,1,1,1,1,1,1,1,1,1,1,1,1,1,1,1,1,1,1,1,1,1,1,1,1,1,1,1,1,1,1,1,1,7,1391,2500,1,1,1,42,23,1,5,1,7000,1,1,1490,15,191,408,290,100,1,664,1910,9307,1,1,1,1,1,1,1,655,2000,1,1,1,1,1,29,1,1,1,1,1,1,1,1,1,5,9,99,20,1,1,1,1,1,1,1,5,29,1,1,3,3,3,3,3,1,1,1,1,1,1,1,10,1,1,200,400,751,3300,1964,200,777,3614,1917,4946,1,1,1,1,1,1,1,1,1,1,1,1,10,6,1499,1480,2759,1966,1886,550,2783,965,59515,18586,20299,450,228,629,631,498,385,499,412,184,492,288,449,522,328,138,490,568,497,473,331,397,100,191,774,796,803,726,886,825,723,766,1,1,1,1,1,1,1,1,1,1,1,1,1,1],"ostime":1756646454,"LavkaUid":24},{"username":"[27]Ded_Demorgan","items_sell":{},"items_buy":{},"price_sell":{},"price_buy":{},"count_sell":{},"count_buy":{},"ostime":1756646475,"LavkaUid":151},{"username":"[08]Gospodin_Farma","items_sell":{},"items_buy":{},"price_sell":{},"price_buy":{},"count_sell":{},"count_buy":{},"ostime":1756646477,"LavkaUid":183},{"username":"[19]Luka_Babytape","items_sell":["Прочная ткань","Прочная ткань","Прочная ткань","Прочная ткань","Прочная ткань","Прочная ткань","Прочная ткань","Прочная ткань","Прочная ткань","Прочная ткань","Прочная ткань","Прочная ткань","Нашивка на скин (Огненные пули)","Грамота ветерана","Сертификат Дополнения VIP","Сертификат Дополнения VIP","Сертификат Дополнения VIP","Сертификат Дополнения VIP","Обрез (активный аксессуар)","Обрез (активный аксессуар)","Нашивка на аксессуар(урон)","Нашивка на аксессуар(урон)","Нашивка на аксессуар(урон)","Нашивка на аксессуар(урон)","Нашивка на аксессуар(урон)","Нашивка на аксессуар(урон)","Нашивка на аксессуар(урон)","Нашивка на аксессуар(урон)","Нашивка на аксессуар(урон)","Нашивка на аксессуар(урон)","Нашивка на аксессуар(урон)","Нашивка на аксессуар(урон)","Шахтерский сплав","Темная материя","Темная материя","Темная материя","Багажник","Инструкция для разбора аксессуара","Инструкция для разбора аксессуара","Инструкция для разбора аксессуара","Инструкция для разбора аксессуара","Инструкция для разбора аксессуара","Инструкция для разбора аксессуара","Смазка для разгона видеокарты","Смазка для разгона видеокарты","Смазка для разгона видеокарты","Смазка для разгона видеокарты","Осколок легендарной нашивке монстра","Монета Миража","Анимированные очки Netrunner","Анимированные очки Netrunner","Анимированные очки Netrunner","Анимированные очки Netrunner","Анимированные очки Netrunner","Нашивка на чемодан (Снижение урона противника)","Нашивка на чемодан (Снижение урона противника)","Сертификат на безлимитную доставку бочек","Админ зарплата","Энергетический двигатель","Энергетический двигатель","Энергетический двигатель","Энергетический двигатель","Энергетический двигатель","Энергетический двигатель","Энергетический двигатель","Энергетический двигатель","Энергетический двигатель","Энергетический двигатель","Энергетический двигатель","Энергетический двигатель","Энергетический двигатель","Шкатулка кладоискателя","Шкатулка кладоискателя","Шкатулка кладоискателя","Шкатулка кладоискателя","Шкатулка кладоискателя","Шкатулка кладоискателя","Шкатулка кладоискателя","Шкатулка кладоискателя","Шкатулка кладоискателя","Шкатулка кладоискателя","Шкатулка кладоискателя","Шкатулка кладоискателя","Шкатулка кладоискателя","Шкатулка кладоискателя","Шкатулка кладоискателя","Шкатулка кладоискателя","Шкатулка кладоискателя","Шкатулка кладоискателя","Шкатулка кладоискателя","Шкатулка кладоискателя","Шкатулка кладоискателя","Шкатулка кладоискателя","Шкатулка кладоискателя","Шкатулка кладоискателя","Шкатулка кладоискателя"],"items_buy":["Уголь","Древесина высшего качества","Точильный амулет","Прочная ткань","Темная материя","Алмазный камень","Золото","Осколок Истока","Монета Миража","Осколок Бронежилета Генерала","Осколок легендарной нашивки тьмы","Осколок легендарной нашивке монстра","Осколок легендарной нашивки энергии","Рулетка ужасов","Бизнес реквизит","Осколок предмета Заточка +13","Документ для отмывания денег","Кусок редкой ткани","Объект: Белая сакура","Скин: CJ (ID: 74)","Объект: Розовая сакура","Улучшенный замок","Кенгурятник Промышленный","Осколок объекта Сарай Миража","Эндер куб","Сертификат охранника 'Cлендермена'","Сертификат охранника 'Любимый Робот Морти'","Сертификат охранника 'Петух'","Именное поместье","Осколок BRABUS ROCKET GTS","Энергетический двигатель","Энергетическая накладка","Редкие материалы","Админ зарплата","Рыбная монета","AZ-Монеты (Передаваемые)","Желтая инструкция для разбора аксессуара","Инструкция для разбора скинов","Рюкзак ЯДОСТАВКА","Видеокарта RTX 4090","Элитная переносная лавка","Магический воздушный шар #1","Магический воздушный шар #2","Магический воздушный шар #3","Магический воздушный шар #4","Магический воздушный шар #5","Магический воздушный шар #6","Магический воздушный шар #7","Случайный культовый бронежилет","Бронежилет «Гравити Фолз»","Бронежилет «Атака Титанов»","Бронежилет «Лайт»","Бронежилет «Невермор»","Бронежилет «Учиха»","Бронежилет «Щ.И.Т.»","Бронежилет «Мортал Комбат»","Бронежилет «Орда»","Бронежилет «Унесенные призраками»","Бронежилет «Игра в кальмара»","Бронежилет «Южный Парк»","Бронежилет «Симпсоны»","Бронежилет Конь БоДжек»","Переносной верстак миража","Нашивка на скин (Бег Си Джея)","Нашивка на скин (Бесконечный бег)","Нашивка на бронежилет (Защита от оглушения)","Нашивка на чемодан (Снижение урона противника)","Супер-кирка","Сертификат Дополнения VIP","Дополнительная комната","12 уровень персонажа","Разрешение на улучшение наземной нефтевышки","Сертификат на безлимитную доставку бочек","Железная карта нац.банка","Лицензия дипломата","Маска череп","Маска-невидимка","Бронежилет #3","Бронежилет #7","Складная мусорная лавка","Переносной ларек Рика 1","Обрез (активный аксессуар)","Осколок Портальной пушки","Осколок Audi RS Q8 Mansory","Супер-заточка","Платиновый осколок ящика секретной машины","Увеличенный магазин (X3) для Tec-9","Увеличенный магазин (X3) для M16","Увеличенный магазин (X3) для Sawnoff","Увеличенный магазин (X3) для Mac-10","Грядка льна","Грядка хлопка","Рекламная вывеска","Флешка майнера","Рыбная приманка","Объект: Фиалковое дерево","Объект: Дерево Сакура","Сертификат на Навык плавания","Увеличенный бак (90 литров)","Увеличенный бак (60 литров)","Кенгурятник Метельник","Кенгурятник Мародера","Кенгурятник Зомби-Апокалипсиса","Кенгурятник Ретро","Снегоуборочный бампер [деталь тюнинга]","Багажник","Багажник с Лебедкой","Подиум [деталь тюнинга]","Вечный индикатор голода","Осколок секретного аксессуара","Ящик с секретной машиной","Super Car Box","Талон: +1 EXP (Передаваемые)","Сет: Клоун","Модификация Гринча","Модификация: Тедди в бирюзовой кофте","Модификация: Тедди в красной кофте","Модификация: Тедди в зеленой кофте","Скин: Крик (ID: 641)","Скин: Светлый эльф (ID: 628)","Скин: Гринч (ID: 459)","Скин: Йода (ID: 351)","Заточенная рукоятка","Заточенный приклад","Заточенный прицел","Заточенное цевье","Заточенный магазин","Все навыки стрельбы"],"price_sell":[105690,105690,105690,105690,105690,105690,105690,105690,105690,105690,105690,105690,8899990,9299990,2600000,2600000,2600000,2600000,6199990,6199990,2599990,2599990,2599990,2599990,2599990,2599990,2599990,2599990,2599990,2599990,2599990,2599990,82990,55990,55990,55990,150000,40000,40000,40000,40000,40000,40000,12399,12399,12399,12399,9689990,10000,8199990,8199990,8199990,8199990,8199990,9199990,9199990,2399990,1199,16299290,16299290,16299290,16299290,16299290,16299290,16299290,16299290,16299290,16299290,16299290,16299290,16299290,10989790,10989790,10989790,10989790,10989790,10989790,10989790,10989790,10989790,10989790,10989790,10989790,10989790,10989790,10989790,10989790,10989790,10989790,10989790,10989790,10989790,10989790,10989790,10989790,10989790],"price_buy":[11950,650,6000,94001,48601,10500,1161,1000,7550,30100,5000001,5500001,7500001,4000000,3270001,805000,18200001,4350,2500000,500000,2500000,1000000,1000000,12200000,15000001,30500001,8000000,2000000,24230001,12000001,13000000,12000000,4701,1101,901,601,70001,25001,13000001,13000001,10500000,9500000,9500000,9000000,9500000,9500000,9500000,9500000,6100102,5500000,5500000,5500000,5500000,5500000,5500000,5500000,5500000,5500000,5500000,5500000,5500000,5500000,2500123,13820223,11000002,9000000,7000000,3500000,2000001,4000000,1300001,1500000,1500000,5200001,1200000,4600001,4100001,2000000,2000000,1500000,2500000,5100000,1000000,1300001,35001,100000,200000,200000,1000001,400000,3600001,3500001,1500000,400001,850001,1250000,1000000,500000,850000,800000,1000000,1000000,1000000,500000,500000,10000,1000000,200000,225000,10000,200000,2000,100,2500000,1200000,5000000,3000000,5000000,1500000,3000000,2000000,6000000,5000001,5000001,5000001,5000001,5000002,470000],"count_sell":[46,200,200,200,200,200,93,200,200,200,200,200,1,1,1,1,1,1,1,1,1,1,1,1,1,1,1,1,1,1,1,1,116,10,50,50,1,13,50,50,50,50,50,97,55,100,100,1,34,1,1,1,1,1,1,1,1,301,1,1,1,1,1,1,1,1,1,1,1,1,1,1,1,1,1,1,1,1,1,1,1,1,1,1,1,1,1,1,1,1,1,1,1,1,1,1],"count_buy":[3114,15500,545,200,601,5986,5962,597,1000,1499,1,1,1,2,1,9,1,5480,1,1,1,1,1,1,1,1,1,1,1,1,1,1,492,500,200,100,49,50,1,1,1,1,1,1,1,1,1,1,1,1,1,1,1,1,1,1,1,1,1,1,1,1,1,1,1,1,1,1,1,1,1,1,1,1,1,1,1,1,1,1,1,1,1,1,80,1,1,1,1,1,1,1,1,1,1,1,1,1,1,1,1,1,1,1,1,1,1,1,1,250,1,248,150,1,1,1,1,1,1,1,1,1,1,1,1,1,1,1],"ostime":1756646443,"LavkaUid":302},{"username":"[18]Katana_Marmeladova","items_sell":{},"items_buy":{},"price_sell":{},"price_buy":{},"count_sell":{},"count_buy":{},"ostime":1756646478,"LavkaUid":23},{"username":"[23]Self_Harm","items_sell":{},"items_buy":{},"price_sell":{},"price_buy":{},"count_sell":{},"count_buy":{},"ostime":1756646477,"LavkaUid":296},{"username":"[07]Amiko_Ohayashi","items_sell":{},"items_buy":{},"price_sell":{},"price_buy":{},"count_sell":{},"count_buy":{},"ostime":1756646477,"LavkaUid":153},{"username":"[02]Andrey_Stoyn","items_sell":{},"items_buy":{},"price_sell":{},"price_buy":{},"count_sell":{},"count_buy":{},"ostime":1756646477,"LavkaUid":33},{"username":"[04]Aska_Vialpando","items_sell":["Золотая рулетка тьмы","Сироп характеристик актера","Анимированное солнце(+10)","Кенгурятник для Peterbilt 359","Рулетка тьмы","Аркана ИО","Аркана ИО","Рулетка космоса","Скади","Переносной ларек (1)","Переносной ларек (1)","Переносной ларек (3)","Райден (ID: 1031)","Бомж Космонавт 1 (ID: 1024)","Увеличенный магазин (X3) для Mac-10","Рецепт: Кольцо всевластия","Рецепт: Кольцо всевластия","Рецепт: Коса марси","Рецепт: Коса марси","Темная материя","Темная материя","Темная материя","Темная материя","Космические наушники","Прочная ткань","Прочная ткань","Шахтерский сплав","Алмазный камень","Алмазный камень","Алмазный камень","Осколок Истока","Осколок Бронежилета Генерала","Инструкция для разбора аксессуара","Инструкция для разбора аксессуара","Черная жемчужина","Черная жемчужина","Черная жемчужина","Черная жемчужина","Черная жемчужина","Черная жемчужина","Черная жемчужина","Черная жемчужина","Черная жемчужина","Черная жемчужина","Черная жемчужина","Черная жемчужина","Черная жемчужина","Черная жемчужина","Черная жемчужина","Черная жемчужина","Черная жемчужина","Черная жемчужина","Черная жемчужина","Черная жемчужина","Респиратор(+8)","Монета Миража","Монета Миража","Монета Миража","Монета Миража","Монета Миража","Монета Миража","Монета Миража","Монета Миража","Монета Миража","Зловещая монета","Зловещая монета","Зловещая монета","Подарок","Подарок","Подарок","Подарок","Гражданский талон","Гражданский талон","Гражданский талон","Семейный талон","Семейный талон","Семейный талон","Супер-заточка","Рыбная монета","Бронза","Серебро","Серебро","Серебро","Золотая рулетка","Счастливая травка","Админ зарплата","Заточка для бронежилета","Заточка для бронежилета","Монета Хроники","Монета Хроники","Ларец петуха","Ларец хэллоуина 2022","Ларец Arizona","Ларец Arizona","Ларец семейных охранников","Ларец Fortnite","Пасхальный ларец 2024","Ларец мусорщика","Супер мото-ящик","Ларец Mortal Combat","Ностальгический ящик","Ностальгический ящик","Ностальгический ящик","Ларец кастомных аксессуаров","Ларец организации","Ларец крафтера","Ящик Minecraft","Ящик Minecraft","Ящик Джентельменов","Ящик Джентельменов","Ящик Marvel","Рандомный Ларец","Рандомный Ларец","Ларец Tidex","Concept Car Luxury","Одежда из секонд-хенда","Одежда из секонд-хенда","Super Car Box","Ларец кладоискателя","Ларец кладоискателя","Ларец развозчика продуктов","Ларец рыболова","Ларец Vice City","Rare Box Red","Rare Box Red","Rare Box Red","Rare Box Blue","Rare Box Blue","Rare Box Yellow","Rare Box Yellow","Хлопок","Хлопок","Хлопок","Хлопок","Лён"],"items_buy":{},"price_sell":[700000,1250000,4000000,950000,250000,2000000,2000000,70000,250000,99000,99000,120000,200000,200000,2500000,300000,300000,300000,300000,75000,75000,75000,75000,100000,165000,165000,130000,14500,14500,14500,6000,39000,60000,60000,25000,25000,25000,25000,25000,25000,25000,25000,25000,25000,25000,25000,25000,25000,25000,25000,25000,25000,25000,25000,2000000,13000,13000,13000,13000,13000,13000,13000,13000,13000,9900,9900,9900,440,440,440,440,250,250,250,420,420,420,120000,1500,250,320,320,320,5600,550,5000,40000,40000,1450,1450,5000,7000,12000,12000,6200,3500,6500,12000,3250,2800,5000,5000,5000,3800,1000,7000,2300,2300,2300,2300,2300,3001,3001,3700,8000,3000,3000,6500,3800,3800,6200,5200,4200,2600,2600,2600,2200,2200,3300,3300,100,100,100,100,100],"price_buy":{},"count_sell":[1,1,1,1,1,1,1,58,1,1,1,1,1,1,1,2,10,9,4,50,41,50,50,1,200,10,77,200,59,200,34,142,27,27,20,20,18,20,20,20,20,20,20,20,20,20,16,20,20,20,20,20,20,20,1,200,200,200,200,200,200,200,200,174,50,50,50,4000,4000,428,4000,4000,4000,520,500,500,382,36,1044,903,180,1000,358,11,10,9409,50,43,430,378,27,80,50,200,100,98,41,40,50,96,50,50,50,12,100,100,5,50,50,50,50,8,50,8,7,100,7,66,50,5,9,12,4,50,50,7,50,50,37,50,800,1000,1000,239,300],"count_buy":{},"ostime":1756646468,"LavkaUid":100},{"username":"[30]Sanchez_McCloud","items_sell":{},"items_buy":{},"price_sell":{},"price_buy":{},"count_sell":{},"count_buy":{},"ostime":1756646477,"LavkaUid":304},{"username":"[01]Cameron_Wright","items_sell":{},"items_buy":{},"price_sell":{},"price_buy":{},"count_sell":{},"count_buy":{},"ostime":1756646477,"LavkaUid":147},{"username":"[07]Fransua_Camembert","items_sell":{},"items_buy":{},"price_sell":{},"price_buy":{},"count_sell":{},"count_buy":{},"ostime":1756646477,"LavkaUid":140},{"username":"[28]Mishanya_Freerider","items_sell":{},"items_buy":{},"price_sell":{},"price_buy":{},"count_sell":{},"count_buy":{},"ostime":1756646478,"LavkaUid":103},{"username":"[07]Little_Pony","items_sell":{},"items_buy":{},"price_sell":{},"price_buy":{},"count_sell":{},"count_buy":{},"ostime":1756646478,"LavkaUid":129},{"username":"[07]Sect_Unit","items_sell":{},"items_buy":{},"price_sell":{},"price_buy":{},"count_sell":{},"count_buy":{},"ostime":1756646478,"LavkaUid":57},{"username":"[31]Ajazz_Qonstatez","items_sell":{},"items_buy":{},"price_sell":{},"price_buy":{},"count_sell":{},"count_buy":{},"ostime":1756646477,"LavkaUid":230},{"username":"[22]Lombard_Ghetto","items_sell":{},"items_buy":{},"price_sell":{},"price_buy":{},"count_sell":{},"count_buy":{},"ostime":1756646478,"LavkaUid":262},{"username":"[09]Artyom_Dotow","items_sell":{},"items_buy":{},"price_sell":{},"price_buy":{},"count_sell":{},"count_buy":{},"ostime":1756646477,"LavkaUid":121},{"username":"[01]Westikq_Olloo","items_sell":["Прототип(+10)","Прототип","Осколок Космический ремонт в дом","НФТ контейнер (обычный)","НФТ контейнер (обычный)","НФТ контейнер (обычный)","НФТ контейнер (обычный)","НФТ контейнер (обычный)","Катана Нир","Катана Нир","Рюкзак ЯДОСТАВКА","Рюкзак ЯДОСТАВКА","Рюкзак ЯДОСТАВКА","Элитная переносная лавка","Заточка +13","Энергетическая накладка Маска череп","Энергетическая накладка Маска череп","Нашивка на чемодан (Снижение урона противника)","Нашивка на чемодан (Снижение урона противника)","Энергетический двигатель","Энергетический двигатель","Осколок Энергетический щит","Чертеж характеристик аксессуара","Чертеж характеристик аксессуара","Чертеж характеристик аксессуара","Анимированные очки Netrunner","Цепь «Bitcoin»","Инструкция для разбора аксессуара","Инструкция для разбора аксессуара"],"items_buy":["Секретный аксессуар","Черная жемчужина","Платиновая рулетка","Темная материя","Металл","Золото","Серебро","Эликсир крафтера","Алюминий","Шкатулка кладоискателя","Древесина высшего качества","Уголь"],"price_sell":[9000000,9000000,29999999,12999999,12999999,12999999,12999999,12999999,125000000,125000000,16999999,16999999,16999999,12499999,4999999,43999996,43999996,9289999,9289999,16154556,16154556,14999997,10999999,10999999,10999999,8148432,8999999,111999,111999],"price_buy":[95000,500,4800,47000,2350,1100,250,1000,7350,8455455,670,1952],"count_sell":[1,1,1,1,1,1,1,1,1,1,1,1,1,1,6,1,1,1,1,1,1,1,1,1,1,1,1,50,50],"count_buy":[192,4932,473,487,6042,3666,6090,978,4742,1,6272,3000],"ostime":1756646459,"LavkaUid":312},{"username":"[05]Aron_Stealer","items_sell":["Обрез (активный аксессуар)(+8)","Генеральский бронежилет(+8)","Цепь Иллюмината(+11)","Цепь Иллюмината(+12)","Танго(+13)","НФТ контейнер (обычный)","Энергетический воздушный шар(+9)"],"items_buy":{},"price_sell":[10500000,58000000,19500000,19500000,36000000,13500000,26900000],"price_buy":{},"count_sell":[1,1,1,1,1,1,1],"count_buy":{},"ostime":1756646460,"LavkaUid":240},{"username":"[24]Sfera_Parabelum","items_sell":{},"items_buy":{},"price_sell":{},"price_buy":{},"count_sell":{},"count_buy":{},"ostime":1756646477,"LavkaUid":99},{"username":"[07]Lega_Lydetto","items_sell":{},"items_buy":{},"price_sell":{},"price_buy":{},"count_sell":{},"count_buy":{},"ostime":1756646479,"LavkaUid":266},{"username":"[24]Pasha_Lot","items_sell":{},"items_buy":{},"price_sell":{},"price_buy":{},"count_sell":{},"count_buy":{},"ostime":1756646477,"LavkaUid":209},{"username":"[13]Dima_Pelemenka","items_sell":{},"items_buy":{},"price_sell":{},"price_buy":{},"count_sell":{},"count_buy":{},"ostime":1756646477,"LavkaUid":128},{"username":"[12]Fernando_Esteban","items_sell":{},"items_buy":{},"price_sell":{},"price_buy":{},"count_sell":{},"count_buy":{},"ostime":1756646477,"LavkaUid":347},{"username":"[18]Vinni_Torreto","items_sell":{},"items_buy":{},"price_sell":{},"price_buy":{},"count_sell":{},"count_buy":{},"ostime":1756646477,"LavkaUid":318},{"username":"[07]Sakura_Vandal","items_sell":{},"items_buy":{},"price_sell":{},"price_buy":{},"count_sell":{},"count_buy":{},"ostime":1756646477,"LavkaUid":41},{"username":"[07]Makoto_Shiomi","items_sell":{},"items_buy":{},"price_sell":{},"price_buy":{},"count_sell":{},"count_buy":{},"ostime":1756646477,"LavkaUid":160},{"username":"[15]Makima_Akagi","items_sell":{},"items_buy":{},"price_sell":{},"price_buy":{},"count_sell":{},"count_buy":{},"ostime":1756646477,"LavkaUid":144},{"username":"[12]Maximo_Esteban","items_sell":{},"items_buy":{},"price_sell":{},"price_buy":{},"count_sell":{},"count_buy":{},"ostime":1756646477,"LavkaUid":279},{"username":"[10]Money_Lead","items_sell":{},"items_buy":{},"price_sell":{},"price_buy":{},"count_sell":{},"count_buy":{},"ostime":1756646477,"LavkaUid":55},{"username":"[12]Akakiu_Oreshkin","items_sell":{},"items_buy":{},"price_sell":{},"price_buy":{},"count_sell":{},"count_buy":{},"ostime":1756646477,"LavkaUid":226},{"username":"[23]Haru_Biznes","items_sell":{},"items_buy":{},"price_sell":{},"price_buy":{},"count_sell":{},"count_buy":{},"ostime":1756646477,"LavkaUid":131},{"username":"[31]Salat_Reseller","items_sell":{},"items_buy":{},"price_sell":{},"price_buy":{},"count_sell":{},"count_buy":{},"ostime":1756646475,"LavkaUid":69},{"username":"[07]Arthur_Cooper","items_sell":["Багажник","Багажник","Платиновый осколок ящика секретной машины","Премиум рулетка","Монета Хроники","Бронзовая рулетка","Опыт депозита","Опыт депозита","Опыт депозита","Осколок ящика секретной машины","Эликсир крипатуры","Эликсир Рыбный мастер","Эликсир PUBG Мастер","Эликсир Хороший Человек","Эликсир дальнобойщика","Кусок редкой ткани","Монета Миража","Гражданский талон","Гражданский талон","Платиновая рулетка","Concept Car Luxury","Concept Car Luxury","Ларец пилота","Ларец Tidex","Super Car Box","Super Car Box","Ларец дальнобойщика","Ларец дальнобойщика","Ларец дальнобойщика","Супер авто-ящик","Супер авто-ящик","Супер авто-ящик","Ларец крафтера","Ларец крафтера","Ларец крафтера","Пасхальный ларец 2024","Пасхальный ларец 2024","Ларец петуха","Ларец рыболова","Ларец с премией","Ларец с премией","Ларец с премией","Ларец кладоискателя","Rare Box Yellow","Ностальгический ящик","Ностальгический ящик","Ларец семейных охранников","НФТ контейнер (обычный)"],"items_buy":["Грамота ветерана","Элитная переносная лавка","Рулетка ужасов","Обрез (активный аксессуар)","Бойцовский клуб","Карлик грув (ID: 1007)","12 уровень персонажа","Видеокарта RTX 4090","Цепь СВАГА","Бейсбольная бита Compton","Нимб 5 звезд","Золотая гангстерская цепь","Цепь SWAG","НФТ контейнер (премиум)"],"price_sell":[110000,110000,240000,549000,2000,270,2499,2499,2499,21000,300,1500,1500,1000,4000,5150,10000,179,179,8000,4300,4300,5800,1450,4300,4300,3600,3600,3600,3500,3500,3500,3400,3400,3400,2300,2300,3400,3500,2500,2500,2500,2400,1300,2199,2199,2900,11449000],"price_buy":[8100000,9500000,3500000,5000000,3000000,2500000,1100000,12500000,200000,200000,200000,500000,200000,15000000],"count_sell":[1,1,1,6,9,6,100,84,100,94,1,2,1,1,1,41,22,3178,2201,6,62,78,34,52,100,98,68,100,100,50,50,23,98,98,51,87,98,92,1,67,97,83,45,50,43,46,68,1],"count_buy":[1,1,1,1,1,1,1,1,1,1,1,1,1,1],"ostime":1756646389,"LavkaUid":126},{"username":"[02]Sakata_Wolker","items_sell":{},"items_buy":{},"price_sell":{},"price_buy":{},"count_sell":{},"count_buy":{},"ostime":1756646477,"LavkaUid":127},{"username":"[30]Jonh_Miller","items_sell":{},"items_buy":{},"price_sell":{},"price_buy":{},"count_sell":{},"count_buy":{},"ostime":1756646477,"LavkaUid":242},{"username":"[06]Shery_Anarchy","items_sell":{},"items_buy":{},"price_sell":{},"price_buy":{},"count_sell":{},"count_buy":{},"ostime":1756646478,"LavkaUid":107},{"username":"[02]Gospodin_Light","items_sell":{},"items_buy":{},"price_sell":{},"price_buy":{},"count_sell":{},"count_buy":{},"ostime":1756646477,"LavkaUid":17},{"username":"[06]Rayan_Falcone","items_sell":{},"items_buy":{},"price_sell":{},"price_buy":{},"count_sell":{},"count_buy":{},"ostime":1756646477,"LavkaUid":299},{"username":"[30]Crypto_Chikatilo","items_sell":{},"items_buy":{},"price_sell":{},"price_buy":{},"count_sell":{},"count_buy":{},"ostime":1756646477,"LavkaUid":275},{"username":"[03]One_God","items_sell":{},"items_buy":{},"price_sell":{},"price_buy":{},"count_sell":{},"count_buy":{},"ostime":1756646476,"LavkaUid":85},{"username":"[30]Marmelad_Freeman","items_sell":{},"items_buy":{},"price_sell":{},"price_buy":{},"count_sell":{},"count_buy":{},"ostime":1756646477,"LavkaUid":64},{"username":"[07]Ryan_Yamazaki","items_sell":{},"items_buy":{},"price_sell":{},"price_buy":{},"count_sell":{},"count_buy":{},"ostime":1756646477,"LavkaUid":264},{"username":"[09]Vanek_Armatura","items_sell":{},"items_buy":{},"price_sell":{},"price_buy":{},"count_sell":{},"count_buy":{},"ostime":1756646477,"LavkaUid":162},{"username":"[10]Lorenzo_Bob","items_sell":{},"items_buy":{},"price_sell":{},"price_buy":{},"count_sell":{},"count_buy":{},"ostime":1756646477,"LavkaUid":218},{"username":"[08]Moonling_Soul","items_sell":{},"items_buy":{},"price_sell":{},"price_buy":{},"count_sell":{},"count_buy":{},"ostime":1756646479,"LavkaUid":288},{"username":"[01]Old_Spicex","items_sell":{},"items_buy":{},"price_sell":{},"price_buy":{},"count_sell":{},"count_buy":{},"ostime":1756646477,"LavkaUid":91},{"username":"[17]Denis_Turok","items_sell":{},"items_buy":{},"price_sell":{},"price_buy":{},"count_sell":{},"count_buy":{},"ostime":1756646477,"LavkaUid":305},{"username":"[22]Nikita_Winch","items_sell":{},"items_buy":{},"price_sell":{},"price_buy":{},"count_sell":{},"count_buy":{},"ostime":1756646477,"LavkaUid":193},{"username":"[23]Borth_Deverson","items_sell":{},"items_buy":{},"price_sell":{},"price_buy":{},"count_sell":{},"count_buy":{},"ostime":1756646477,"LavkaUid":221},{"username":"[07]Skill_Smesharic","items_sell":{},"items_buy":{},"price_sell":{},"price_buy":{},"count_sell":{},"count_buy":{},"ostime":1756646479,"LavkaUid":344},{"username":"[23]Ruslan_Akentev","items_sell":{},"items_buy":{},"price_sell":{},"price_buy":{},"count_sell":{},"count_buy":{},"ostime":1756646477,"LavkaUid":238},{"username":"[10]Alex_Belfort","items_sell":{},"items_buy":{},"price_sell":{},"price_buy":{},"count_sell":{},"count_buy":{},"ostime":1756646477,"LavkaUid":259},{"username":"[19]Adrian_KoIiri","items_sell":{},"items_buy":{},"price_sell":{},"price_buy":{},"count_sell":{},"count_buy":{},"ostime":1756646485,"LavkaUid":94},{"username":"[22]Carter_Wilson","items_sell":{},"items_buy":{},"price_sell":{},"price_buy":{},"count_sell":{},"count_buy":{},"ostime":1756646478,"LavkaUid":287},{"username":"[10]Nicholas_Triplicate","items_sell":["Древесина высшего качества","Древесина высшего качества","Древесина высшего качества","Материалы","Материалы","Материалы","Материалы","Материалы","Материалы","Материалы","Материалы","Укроп","Укроп","Укроп","Осколок Бронежилета Генерала","Редкие материалы","Опыт депозита","Монета Хроники","Ларец организации"],"items_buy":{},"price_sell":[1000,1000,1000,10,10,10,10,10,10,10,10,40,40,40,35000,6000,3500,1500,1000],"price_buy":{},"count_sell":[300,300,123,10000,10000,10000,10000,10000,9285,10000,6000,108,33,197,5,8,31,123,69],"count_buy":{},"ostime":1756646417,"LavkaUid":29},{"username":"[29]Piva_Sik","items_sell":{},"items_buy":{},"price_sell":{},"price_buy":{},"count_sell":{},"count_buy":{},"ostime":1756646478,"LavkaUid":20},{"username":"[02]Mirage_Inclusive","items_sell":{},"items_buy":{},"price_sell":{},"price_buy":{},"count_sell":{},"count_buy":{},"ostime":1756646477,"LavkaUid":323},{"username":"[24]Melissa_Visconti","items_sell":{},"items_buy":{},"price_sell":{},"price_buy":{},"count_sell":{},"count_buy":{},"ostime":1756646477,"LavkaUid":133},{"username":"[23]Boom_Shakalaka","items_sell":{},"items_buy":{},"price_sell":{},"price_buy":{},"count_sell":{},"count_buy":{},"ostime":1756646477,"LavkaUid":252},{"username":"[29]Oliver_Saxon","items_sell":{},"items_buy":{},"price_sell":{},"price_buy":{},"count_sell":{},"count_buy":{},"ostime":1756646477,"LavkaUid":228},{"username":"[23]Sky_Yamazaki","items_sell":{},"items_buy":{},"price_sell":{},"price_buy":{},"count_sell":{},"count_buy":{},"ostime":1756646477,"LavkaUid":286},{"username":"[31]Raketka_Tamaeva","items_sell":{},"items_buy":{},"price_sell":{},"price_buy":{},"count_sell":{},"count_buy":{},"ostime":1756646477,"LavkaUid":120},{"username":"[27]Viktor_Paradise","items_sell":{},"items_buy":{},"price_sell":{},"price_buy":{},"count_sell":{},"count_buy":{},"ostime":1756646477,"LavkaUid":337},{"username":"[19]Loli_Popo","items_sell":{},"items_buy":{},"price_sell":{},"price_buy":{},"count_sell":{},"count_buy":{},"ostime":1756646487,"LavkaUid":246},{"username":"[07]Brandon_Inside","items_sell":{},"items_buy":{},"price_sell":{},"price_buy":{},"count_sell":{},"count_buy":{},"ostime":1756646477,"LavkaUid":181},{"username":"[16]Vlad_Didovich","items_sell":{},"items_buy":{},"price_sell":{},"price_buy":{},"count_sell":{},"count_buy":{},"ostime":1756646477,"LavkaUid":106},{"username":"[24]Daimler_Brooks","items_sell":["Куст(Кактус)","Объект: Дерево Бонсай","Объект: Дерево Бонсай","Объект: Дерево Бонсай","Скин: Армейский пончик (ID: 964)","Осколок Истока","Объект: Обелиск","Объект: Обелиск","Осколок Космический ремонт в дом"],"items_buy":{},"price_sell":[50000,800000,800000,800000,500000,10000,120000,120000,26500000],"price_buy":{},"count_sell":[1,1,1,1,1,21,1,1,1],"count_buy":{},"ostime":1756646373,"LavkaUid":186},{"username":"[14]Niveiika_Men","items_sell":{},"items_buy":{},"price_sell":{},"price_buy":{},"count_sell":{},"count_buy":{},"ostime":1756646477,"LavkaUid":122},{"username":"[30]Delta_Freehouse","items_sell":{},"items_buy":{},"price_sell":{},"price_buy":{},"count_sell":{},"count_buy":{},"ostime":1756646477,"LavkaUid":293},{"username":"[18]Andrey_Pudge","items_sell":{},"items_buy":{},"price_sell":{},"price_buy":{},"count_sell":{},"count_buy":{},"ostime":1756646477,"LavkaUid":142},{"username":"[23]Dez_Oxid","items_sell":{},"items_buy":{},"price_sell":{},"price_buy":{},"count_sell":{},"count_buy":{},"ostime":1756646477,"LavkaUid":276},{"username":"[28]Roman_Khovatov","items_sell":{},"items_buy":{},"price_sell":{},"price_buy":{},"count_sell":{},"count_buy":{},"ostime":1756646481,"LavkaUid":133},{"username":"[23]Kkwazza_Waquikkwala","items_sell":{},"items_buy":{},"price_sell":{},"price_buy":{},"count_sell":{},"count_buy":{},"ostime":1756646478,"LavkaUid":201},{"username":"[29]Ek_Makarek","items_sell":{},"items_buy":{},"price_sell":{},"price_buy":{},"count_sell":{},"count_buy":{},"ostime":1756646477,"LavkaUid":332},{"username":"[05]Cano_Castillo","items_sell":{},"items_buy":{},"price_sell":{},"price_buy":{},"count_sell":{},"count_buy":{},"ostime":1756646477,"LavkaUid":271},{"username":"[31]Snow_Mers","items_sell":{},"items_buy":{},"price_sell":{},"price_buy":{},"count_sell":{},"count_buy":{},"ostime":1756646477,"LavkaUid":96},{"username":"[05]Dolores_Renoblade","items_sell":{},"items_buy":{},"price_sell":{},"price_buy":{},"count_sell":{},"count_buy":{},"ostime":1756646476,"LavkaUid":42},{"username":"[08]Alex_Greenfield","items_sell":["Протокол взвешивания"],"items_buy":{},"price_sell":[200000],"price_buy":{},"count_sell":[1],"count_buy":{},"ostime":1756646426,"LavkaUid":26},{"username":"[29]Jett_Max","items_sell":{},"items_buy":{},"price_sell":{},"price_buy":{},"count_sell":{},"count_buy":{},"ostime":1756646477,"LavkaUid":249},{"username":"[02]Goust_Escobar","items_sell":{},"items_buy":{},"price_sell":{},"price_buy":{},"count_sell":{},"count_buy":{},"ostime":1756646477,"LavkaUid":75},{"username":"[31]Bitcoin_Monopoly","items_sell":{},"items_buy":{},"price_sell":{},"price_buy":{},"count_sell":{},"count_buy":{},"ostime":1756646475,"LavkaUid":341},{"username":"[30]Petr_Aoki","items_sell":{},"items_buy":{},"price_sell":{},"price_buy":{},"count_sell":{},"count_buy":{},"ostime":1756646477,"LavkaUid":16},{"username":"[22]Ron_Skorpion","items_sell":{},"items_buy":{},"price_sell":{},"price_buy":{},"count_sell":{},"count_buy":{},"ostime":1756646477,"LavkaUid":350},{"username":"[07]Okiana_Ray","items_sell":{},"items_buy":{},"price_sell":{},"price_buy":{},"count_sell":{},"count_buy":{},"ostime":1756646477,"LavkaUid":207},{"username":"[06]Bob_Li","items_sell":{},"items_buy":{},"price_sell":{},"price_buy":{},"count_sell":{},"count_buy":{},"ostime":1756646477,"LavkaUid":152},{"username":"[04]Leon_Sakai","items_sell":{},"items_buy":{},"price_sell":{},"price_buy":{},"count_sell":{},"count_buy":{},"ostime":1756646484,"LavkaUid":52},{"username":"[16]Thomas_ViceCity","items_sell":{},"items_buy":{},"price_sell":{},"price_buy":{},"count_sell":{},"count_buy":{},"ostime":1756646475,"LavkaUid":247},{"username":"[02]Souteneur_Rakuzan","items_sell":{},"items_buy":{},"price_sell":{},"price_buy":{},"count_sell":{},"count_buy":{},"ostime":1756646477,"LavkaUid":345},{"username":"[01]Plug_Trakov","items_sell":{},"items_buy":{},"price_sell":{},"price_buy":{},"count_sell":{},"count_buy":{},"ostime":1756646477,"LavkaUid":291},{"username":"[30]Rob_Top","items_sell":{},"items_buy":{},"price_sell":{},"price_buy":{},"count_sell":{},"count_buy":{},"ostime":1756646477,"LavkaUid":325},{"username":"[31]Sanek_Matveev","items_sell":{},"items_buy":{},"price_sell":{},"price_buy":{},"count_sell":{},"count_buy":{},"ostime":1756646477,"LavkaUid":340},{"username":"[21]Drakon_Asher","items_sell":{},"items_buy":{},"price_sell":{},"price_buy":{},"count_sell":{},"count_buy":{},"ostime":1756646477,"LavkaUid":222},{"username":"[19]Sleepy_Kitagawa","items_sell":{},"items_buy":{},"price_sell":{},"price_buy":{},"count_sell":{},"count_buy":{},"ostime":1756646477,"LavkaUid":334},{"username":"[30]Satir_Nasatira","items_sell":{},"items_buy":{},"price_sell":{},"price_buy":{},"count_sell":{},"count_buy":{},"ostime":1756646477,"LavkaUid":235},{"username":"[29]Jay_Digger","items_sell":{},"items_buy":{},"price_sell":{},"price_buy":{},"count_sell":{},"count_buy":{},"ostime":1756646478,"LavkaUid":290},{"username":"1211858359","items_sell":{},"items_buy":{},"price_sell":{},"price_buy":{},"count_sell":{},"count_buy":{},"ostime":1756646477,"LavkaUid":236},{"username":"[01]Daydshest_Bayderin","items_sell":{},"items_buy":{},"price_sell":{},"price_buy":{},"count_sell":{},"count_buy":{},"ostime":1756646477,"LavkaUid":156},{"username":"[10]Cristiano_Zoro","items_sell":{},"items_buy":{},"price_sell":{},"price_buy":{},"count_sell":{},"count_buy":{},"ostime":1756646477,"LavkaUid":188},{"username":"[13]Doc_Stone","items_sell":{},"items_buy":{},"price_sell":{},"price_buy":{},"count_sell":{},"count_buy":{},"ostime":1756646477,"LavkaUid":105},{"username":"[06]Lucifer_Knight","items_sell":{},"items_buy":{},"price_sell":{},"price_buy":{},"count_sell":{},"count_buy":{},"ostime":1756646477,"LavkaUid":58},{"username":"[12]Mahmud_Agurcov","items_sell":{},"items_buy":{},"price_sell":{},"price_buy":{},"count_sell":{},"count_buy":{},"ostime":1756646477,"LavkaUid":283},{"username":"[14]Frank_Bestof","items_sell":{},"items_buy":{},"price_sell":{},"price_buy":{},"count_sell":{},"count_buy":{},"ostime":1756646477,"LavkaUid":150},{"username":"[21]Harya_Herrington","items_sell":{},"items_buy":{},"price_sell":{},"price_buy":{},"count_sell":{},"count_buy":{},"ostime":1756646477,"LavkaUid":208},{"username":"[27]Dante_Sacred","items_sell":{},"items_buy":{},"price_sell":{},"price_buy":{},"count_sell":{},"count_buy":{},"ostime":1756646478,"LavkaUid":39},{"username":"[30]Attacms_Tomahawk","items_sell":{},"items_buy":{},"price_sell":{},"price_buy":{},"count_sell":{},"count_buy":{},"ostime":1756646477,"LavkaUid":327},{"username":"[12]Nevermore_Bradley","items_sell":{},"items_buy":{},"price_sell":{},"price_buy":{},"count_sell":{},"count_buy":{},"ostime":1756646477,"LavkaUid":180},{"username":"[29]Zloveshchaya_Monetka","items_sell":{},"items_buy":{},"price_sell":{},"price_buy":{},"count_sell":{},"count_buy":{},"ostime":1756646477,"LavkaUid":241},{"username":"[02]Healing_Proof","items_sell":{},"items_buy":{},"price_sell":{},"price_buy":{},"count_sell":{},"count_buy":{},"ostime":1756646477,"LavkaUid":280},{"username":"[06]Timoha_Parker","items_sell":["Прочная ткань","Шахтерский сплав","Алмазный камень","Осколок шкатулки кладоискателя","Осколок Истока","Алмазные запчасти","Бронза","Бронза","Бронза","Бронза","Бронза","Бронза","Бронза"],"items_buy":{},"price_sell":[109000,70000,11300,2000000,3300,16500000,160,160,160,160,160,160,160],"price_buy":{},"count_sell":[4,3,45,1,116,1,820,1000,1000,34,1000,1000,1000],"count_buy":{},"ostime":1756646436,"LavkaUid":308},{"username":"[27]Altayskiy_Malchik","items_sell":{},"items_buy":{},"price_sell":{},"price_buy":{},"count_sell":{},"count_buy":{},"ostime":1756646475,"LavkaUid":115},{"username":"[22]Marlo_Pajero","items_sell":{},"items_buy":{},"price_sell":{},"price_buy":{},"count_sell":{},"count_buy":{},"ostime":1756646476,"LavkaUid":273},{"username":"[20]Jack_Mantera","items_sell":{},"items_buy":{},"price_sell":{},"price_buy":{},"count_sell":{},"count_buy":{},"ostime":1756646478,"LavkaUid":175},{"username":"[16]Chifuya_Nakamoto","items_sell":{},"items_buy":{},"price_sell":{},"price_buy":{},"count_sell":{},"count_buy":{},"ostime":1756646477,"LavkaUid":284},{"username":"[06]Crisis_Excelsior","items_sell":{},"items_buy":{},"price_sell":{},"price_buy":{},"count_sell":{},"count_buy":{},"ostime":1756646477,"LavkaUid":197},{"username":"[06]Biba_Bobov","items_sell":{},"items_buy":{},"price_sell":{},"price_buy":{},"count_sell":{},"count_buy":{},"ostime":1756646477,"LavkaUid":74},{"username":"[20]Ash_Island","items_sell":{},"items_buy":{},"price_sell":{},"price_buy":{},"count_sell":{},"count_buy":{},"ostime":1756646477,"LavkaUid":248},{"username":"[08]Nevercryx_Guerra","items_sell":{},"items_buy":{},"price_sell":{},"price_buy":{},"count_sell":{},"count_buy":{},"ostime":1756646477,"LavkaUid":239},{"username":"[14]Jozeph_Domowoi","items_sell":{},"items_buy":{},"price_sell":{},"price_buy":{},"count_sell":{},"count_buy":{},"ostime":1756646477,"LavkaUid":244},{"username":"[27]Sasha_Alanov","items_sell":{},"items_buy":{},"price_sell":{},"price_buy":{},"count_sell":{},"count_buy":{},"ostime":1756646475,"LavkaUid":45},{"username":"[26]Thomas_Trupoedov","items_sell":{},"items_buy":{},"price_sell":{},"price_buy":{},"count_sell":{},"count_buy":{},"ostime":1756646475,"LavkaUid":30},{"username":"[05]Sybo_Litvinenko","items_sell":{},"items_buy":{},"price_sell":{},"price_buy":{},"count_sell":{},"count_buy":{},"ostime":1756646477,"LavkaUid":10},{"username":"[06]Irishka_Chikipiki","items_sell":{},"items_buy":{},"price_sell":{},"price_buy":{},"count_sell":{},"count_buy":{},"ostime":1756646477,"LavkaUid":206},{"username":"[02]Neponatnaya_Personka","items_sell":{},"items_buy":{},"price_sell":{},"price_buy":{},"count_sell":{},"count_buy":{},"ostime":1756646478,"LavkaUid":76},{"username":"[31]Papa_Defender","items_sell":{},"items_buy":{},"price_sell":{},"price_buy":{},"count_sell":{},"count_buy":{},"ostime":1756646477,"LavkaUid":174},{"username":"[20]Ghost_McTavish","items_sell":{},"items_buy":{},"price_sell":{},"price_buy":{},"count_sell":{},"count_buy":{},"ostime":1756646477,"LavkaUid":298},{"username":"[18]Kiyoke_Advantage","items_sell":{},"items_buy":{},"price_sell":{},"price_buy":{},"count_sell":{},"count_buy":{},"ostime":1756646477,"LavkaUid":306},{"username":"[25]Wade_Walker","items_sell":{},"items_buy":{},"price_sell":{},"price_buy":{},"count_sell":{},"count_buy":{},"ostime":1756646477,"LavkaUid":346},{"username":"[23]Ressurrection_Based","items_sell":{},"items_buy":{},"price_sell":{},"price_buy":{},"count_sell":{},"count_buy":{},"ostime":1756646477,"LavkaUid":245},{"username":"[15]Jon_Flinger","items_sell":{},"items_buy":{},"price_sell":{},"price_buy":{},"count_sell":{},"count_buy":{},"ostime":1756646478,"LavkaUid":285},{"username":"[22]Owen_Shaw","items_sell":{},"items_buy":{},"price_sell":{},"price_buy":{},"count_sell":{},"count_buy":{},"ostime":1756646477,"LavkaUid":199},{"username":"[29]Oleksandr_Kostylev","items_sell":{},"items_buy":{},"price_sell":{},"price_buy":{},"count_sell":{},"count_buy":{},"ostime":1756646477,"LavkaUid":278},{"username":"[09]Thomas_Hopeless","items_sell":{},"items_buy":{},"price_sell":{},"price_buy":{},"count_sell":{},"count_buy":{},"ostime":1756646475,"LavkaUid":263},{"username":"[28]Biba_Kolovrat","items_sell":{},"items_buy":{},"price_sell":{},"price_buy":{},"count_sell":{},"count_buy":{},"ostime":1756646477,"LavkaUid":97},{"username":"[29]Aqua_Station","items_sell":{},"items_buy":{},"price_sell":{},"price_buy":{},"count_sell":{},"count_buy":{},"ostime":1756646477,"LavkaUid":118},{"username":"[02]Set_Depresed","items_sell":{},"items_buy":{},"price_sell":{},"price_buy":{},"count_sell":{},"count_buy":{},"ostime":1756646479,"LavkaUid":187},{"username":"[29]Psycho_Therapevt","items_sell":{},"items_buy":{},"price_sell":{},"price_buy":{},"count_sell":{},"count_buy":{},"ostime":1756646477,"LavkaUid":339},{"username":"[30]Hamza_Hamza","items_sell":{},"items_buy":{},"price_sell":{},"price_buy":{},"count_sell":{},"count_buy":{},"ostime":1756646477,"LavkaUid":125},{"username":"[27]Chief_Sosa","items_sell":{},"items_buy":{},"price_sell":{},"price_buy":{},"count_sell":{},"count_buy":{},"ostime":1756646477,"LavkaUid":108},{"username":"[14]Molodoi_Kilotravki","items_sell":{},"items_buy":{},"price_sell":{},"price_buy":{},"count_sell":{},"count_buy":{},"ostime":1756646477,"LavkaUid":38},{"username":"[02]Roman_Demiral","items_sell":{},"items_buy":{},"price_sell":{},"price_buy":{},"count_sell":{},"count_buy":{},"ostime":1756646479,"LavkaUid":189},{"username":"[27]Beta_Test","items_sell":{},"items_buy":{},"price_sell":{},"price_buy":{},"count_sell":{},"count_buy":{},"ostime":1756646477,"LavkaUid":114},{"username":"[18]Veld_Bobijon","items_sell":{},"items_buy":{},"price_sell":{},"price_buy":{},"count_sell":{},"count_buy":{},"ostime":1756646477,"LavkaUid":170},{"username":"[03]Pena_Detrov","items_sell":{},"items_buy":{},"price_sell":{},"price_buy":{},"count_sell":{},"count_buy":{},"ostime":1756646477,"LavkaUid":163},{"username":"[01]Danek_Emoxytocin","items_sell":{},"items_buy":{},"price_sell":{},"price_buy":{},"count_sell":{},"count_buy":{},"ostime":1756646477,"LavkaUid":145},{"username":"[07]Saint_Prince","items_sell":{},"items_buy":{},"price_sell":{},"price_buy":{},"count_sell":{},"count_buy":{},"ostime":1756646477,"LavkaUid":40},{"username":"[24]Planka_Blueberry","items_sell":{},"items_buy":{},"price_sell":{},"price_buy":{},"count_sell":{},"count_buy":{},"ostime":1756646477,"LavkaUid":6},{"username":"[27]Eddie_Murphy","items_sell":{},"items_buy":{},"price_sell":{},"price_buy":{},"count_sell":{},"count_buy":{},"ostime":1756646477,"LavkaUid":119},{"username":"[17]Devilish_Wicked","items_sell":{},"items_buy":{},"price_sell":{},"price_buy":{},"count_sell":{},"count_buy":{},"ostime":1756646477,"LavkaUid":123},{"username":"[07]Pavlos_Kavliaris","items_sell":{},"items_buy":{},"price_sell":{},"price_buy":{},"count_sell":{},"count_buy":{},"ostime":1756646477,"LavkaUid":192},{"username":"[31]Desate_Falcone","items_sell":{},"items_buy":{},"price_sell":{},"price_buy":{},"count_sell":{},"count_buy":{},"ostime":1756646477,"LavkaUid":205},{"username":"[31]Atalio_BonBon","items_sell":{},"items_buy":{},"price_sell":{},"price_buy":{},"count_sell":{},"count_buy":{},"ostime":1756646486,"LavkaUid":289},{"username":"[01]Kot_Baly","items_sell":{},"items_buy":{},"price_sell":{},"price_buy":{},"count_sell":{},"count_buy":{},"ostime":1756646477,"LavkaUid":53},{"username":"[31]Donny_Lood","items_sell":{},"items_buy":{},"price_sell":{},"price_buy":{},"count_sell":{},"count_buy":{},"ostime":1756646476,"LavkaUid":303},{"username":"[02]Yura_Kovalevich","items_sell":{},"items_buy":{},"price_sell":{},"price_buy":{},"count_sell":{},"count_buy":{},"ostime":1756646477,"LavkaUid":78},{"username":"[13]Chap_Chap","items_sell":{},"items_buy":{},"price_sell":{},"price_buy":{},"count_sell":{},"count_buy":{},"ostime":1756646477,"LavkaUid":320},{"username":"[02]Naiz_Nephilim","items_sell":{},"items_buy":{},"price_sell":{},"price_buy":{},"count_sell":{},"count_buy":{},"ostime":1756646475,"LavkaUid":309},{"username":"[24]Pafos_Arctic","items_sell":{},"items_buy":{},"price_sell":{},"price_buy":{},"count_sell":{},"count_buy":{},"ostime":1756646475,"LavkaUid":342},{"username":"[27]Yad_Avangard","items_sell":{},"items_buy":{},"price_sell":{},"price_buy":{},"count_sell":{},"count_buy":{},"ostime":1756646477,"LavkaUid":67},{"username":"[06]German_Immortalis","items_sell":{},"items_buy":{},"price_sell":{},"price_buy":{},"count_sell":{},"count_buy":{},"ostime":1756646477,"LavkaUid":141},{"username":"[13]Ragnar_Dereseo","items_sell":{},"items_buy":{},"price_sell":{},"price_buy":{},"count_sell":{},"count_buy":{},"ostime":1756646477,"LavkaUid":49},{"username":"[03]Miguel_Rossetti","items_sell":{},"items_buy":{},"price_sell":{},"price_buy":{},"count_sell":{},"count_buy":{},"ostime":1756646476,"LavkaUid":217},{"username":"[10]Legenda_Kingston","items_sell":{},"items_buy":{},"price_sell":{},"price_buy":{},"count_sell":{},"count_buy":{},"ostime":1756646477,"LavkaUid":295},{"username":"[03]Riccardo_Greco","items_sell":{},"items_buy":{},"price_sell":{},"price_buy":{},"count_sell":{},"count_buy":{},"ostime":1756646477,"LavkaUid":110},{"username":"[02]Liquid_Bounce","items_sell":{},"items_buy":{},"price_sell":{},"price_buy":{},"count_sell":{},"count_buy":{},"ostime":1756646477,"LavkaUid":143},{"username":"[15]Dapo_McCloud","items_sell":{},"items_buy":{},"price_sell":{},"price_buy":{},"count_sell":{},"count_buy":{},"ostime":1756646485,"LavkaUid":313},{"username":"[31]Yukino_Yukinoshita","items_sell":["Рулетка космоса","Ангельское кольцо на голову","Сертификат бесконечного Дополнения VIP","Алмазный камень","Осколок Бронежилета Генерала","Тюнинг-пак для Chevrolet Bel-Air","Темная материя","Лопата(+4)","Лопата(+7)","Ящик рыболова","Платиновая рулетка","Бронза","Инструкция для разбора аксессуара","Флешка майнера","Премиум рулетка","Опыт депозита","Опыт депозита","Опыт депозита","Опыт депозита","Опыт депозита","Черная жемчужина"],"items_buy":["Рулетка космоса"],"price_sell":[60000,1550000,11000000,12000,42000,800000,58000,350000,350000,700000,8000,200,60000,2200000,550000,2700,2700,2700,2700,2700,2000],"price_buy":[35000],"count_sell":[86,1,1,1,7,1,4,1,1,1,1,194,2,1,2,100,100,100,100,12,15],"count_buy":[98],"ostime":1756646438,"LavkaUid":71},{"username":"[02]Lady_Bug","items_sell":{},"items_buy":{},"price_sell":{},"price_buy":{},"count_sell":{},"count_buy":{},"ostime":1756646477,"LavkaUid":301},{"username":"[16]Mosquit_Increase","items_sell":{},"items_buy":{},"price_sell":{},"price_buy":{},"count_sell":{},"count_buy":{},"ostime":1756646478,"LavkaUid":311},{"username":"[28]Buda_Witcha","items_sell":{},"items_buy":{},"price_sell":{},"price_buy":{},"count_sell":{},"count_buy":{},"ostime":1756646477,"LavkaUid":257},{"username":"[05]Lucas_Deluxe","items_sell":{},"items_buy":{},"price_sell":{},"price_buy":{},"count_sell":{},"count_buy":{},"ostime":1756646478,"LavkaUid":314},{"username":"[13]Ambassador_Akcez","items_sell":["Энергетический махинатор","Энергетический воздушный шар(+13)","Энергетический чемодан","Часы 'Casio G-SHOCK'(+13)","Огненная кирка(+13)","Маска распорядителя(+13)"],"items_buy":{},"price_sell":[115000000,33000000,26500000,13000000,35000000,18000000],"price_buy":{},"count_sell":[1,1,1,1,1,1],"count_buy":{},"ostime":1756646358,"LavkaUid":81},{"username":"[07]Papan_Nanashko","items_sell":{},"items_buy":{},"price_sell":{},"price_buy":{},"count_sell":{},"count_buy":{},"ostime":1756646475,"LavkaUid":135},{"username":"[30]Blu_Marin","items_sell":{},"items_buy":{},"price_sell":{},"price_buy":{},"count_sell":{},"count_buy":{},"ostime":1756646478,"LavkaUid":204},{"username":"[01]Candy_Proud","items_sell":{},"items_buy":{},"price_sell":{},"price_buy":{},"count_sell":{},"count_buy":{},"ostime":1756646477,"LavkaUid":112},{"username":"[07]Christopher_Manny","items_sell":{},"items_buy":{},"price_sell":{},"price_buy":{},"count_sell":{},"count_buy":{},"ostime":1756646477,"LavkaUid":331},{"username":"[24]Saiko_Samurai","items_sell":{},"items_buy":{},"price_sell":{},"price_buy":{},"count_sell":{},"count_buy":{},"ostime":1756646478,"LavkaUid":89},{"username":"[01]Rudolf_Naiz","items_sell":{},"items_buy":{},"price_sell":{},"price_buy":{},"count_sell":{},"count_buy":{},"ostime":1756646477,"LavkaUid":165},{"username":"[26]Frank_Kaido","items_sell":{},"items_buy":{},"price_sell":{},"price_buy":{},"count_sell":{},"count_buy":{},"ostime":1756646477,"LavkaUid":167},{"username":"[13]Young_DeLorean","items_sell":{},"items_buy":{},"price_sell":{},"price_buy":{},"count_sell":{},"count_buy":{},"ostime":1756646477,"LavkaUid":95},{"username":"[02]Tim_Really","items_sell":{},"items_buy":{},"price_sell":{},"price_buy":{},"count_sell":{},"count_buy":{},"ostime":1756646477,"LavkaUid":44},{"username":"[02]Ashton_Cooper","items_sell":{},"items_buy":{},"price_sell":{},"price_buy":{},"count_sell":{},"count_buy":{},"ostime":1756646477,"LavkaUid":43},{"username":"[02]Porn_Actor","items_sell":["Оружие Бамбли Би(+9)","Маска 'Wrench'(+12)","Частица космического NFT","Магмовый топор","Нимб Гуррен Лагган","Тюнинг-пак для Dodge Charger Daytona","Тюнинг-пак для Nissan Silvia S14","Русский боевой топор"],"items_buy":{},"price_sell":[6000000,3000000,900000,1600000,800000,200000,200000,7500000],"price_buy":{},"count_sell":[1,1,1,1,1,1,1,1],"count_buy":{},"ostime":1756646431,"LavkaUid":21},{"username":"[26]Gustav_Bismark","items_sell":{},"items_buy":{},"price_sell":{},"price_buy":{},"count_sell":{},"count_buy":{},"ostime":1756646475,"LavkaUid":27},{"username":"[10]Jaxon_Creed","items_sell":{},"items_buy":{},"price_sell":{},"price_buy":{},"count_sell":{},"count_buy":{},"ostime":1756646477,"LavkaUid":26},{"username":"[24]Sky_Deeplace","items_sell":{},"items_buy":{},"price_sell":{},"price_buy":{},"count_sell":{},"count_buy":{},"ostime":1756646477,"LavkaUid":14},{"username":"[06]Ghost_Slayer","items_sell":{},"items_buy":{},"price_sell":{},"price_buy":{},"count_sell":{},"count_buy":{},"ostime":1756646456,"LavkaUid":101},{"username":"[07]Pavel_Bashkatov","items_sell":{},"items_buy":{},"price_sell":{},"price_buy":{},"count_sell":{},"count_buy":{},"ostime":1756646477,"LavkaUid":73},{"username":"[30]Onda_Andar","items_sell":["Танго","Энергетический воздушный шар(+13)","Золотая гангстерская цепь(+13)","Маска череп(+13)","Оружие Бамбли Би(+13)","Огненная кирка(+13)","Дельтаплан на спину(+12)","Маска Терминатор(+13)","Рулетка ужасов","НФТ контейнер (обычный)","НФТ контейнер (обычный)","НФТ контейнер (обычный)","НФТ контейнер (обычный)","Шахтерский сплав","Прочная ткань","Супер-лопата(+11)","Талон на 12 x4 PayDay (передаваемый)","Осколок Lambo Huracan Pirate Edition","Генеральский бронежилет(+7)","Шкатулка кладоискателя"],"items_buy":{},"price_sell":[100000000,38800000,13000000,23500000,18000000,23500000,4500000,4500000,4500000,11950000,11950000,11950000,11950000,67000,106000,1000000,1300000,295000,42500000,10600000],"price_buy":{},"count_sell":[1,1,1,1,1,1,1,1,3,1,1,1,1,33,43,1,1,1,1,1],"count_buy":{},"ostime":1756646463,"LavkaUid":328},{"username":"[29]Countle_Baby","items_sell":{},"items_buy":{},"price_sell":{},"price_buy":{},"count_sell":{},"count_buy":{},"ostime":1756646478,"LavkaUid":68},{"username":"[03]Mafioznik_Mercenari","items_sell":{},"items_buy":{},"price_sell":{},"price_buy":{},"count_sell":{},"count_buy":{},"ostime":1756646477,"LavkaUid":231},{"username":"[09]Dragon_Lond","items_sell":{},"items_buy":{},"price_sell":{},"price_buy":{},"count_sell":{},"count_buy":{},"ostime":1756646477,"LavkaUid":59},{"username":"[18]Robert_Capone","items_sell":{},"items_buy":{},"price_sell":{},"price_buy":{},"count_sell":{},"count_buy":{},"ostime":1756646477,"LavkaUid":196},{"username":"[30]Sever_Bank","items_sell":{},"items_buy":{},"price_sell":{},"price_buy":{},"count_sell":{},"count_buy":{},"ostime":1756646478,"LavkaUid":60},{"username":"[17]Dead_Goose","items_sell":{},"items_buy":{},"price_sell":{},"price_buy":{},"count_sell":{},"count_buy":{},"ostime":1756646485,"LavkaUid":139},{"username":"[13]Max_Wkeed","items_sell":{},"items_buy":{},"price_sell":{},"price_buy":{},"count_sell":{},"count_buy":{},"ostime":1756646478,"LavkaUid":136},{"username":"[07]Randolf_Mayakov","items_sell":{},"items_buy":{},"price_sell":{},"price_buy":{},"count_sell":{},"count_buy":{},"ostime":1756646476,"LavkaUid":215},{"username":"[28]Asumi_Arasaka","items_sell":{},"items_buy":{},"price_sell":{},"price_buy":{},"count_sell":{},"count_buy":{},"ostime":1756646477,"LavkaUid":349},{"username":"[11]Slavchik_Monopoly","items_sell":{},"items_buy":{},"price_sell":{},"price_buy":{},"count_sell":{},"count_buy":{},"ostime":1756646476,"LavkaUid":322},{"username":"[20]Mod_McGrath","items_sell":{},"items_buy":{},"price_sell":{},"price_buy":{},"count_sell":{},"count_buy":{},"ostime":1756646477,"LavkaUid":12},{"username":"[04]Bane_DeCollantes","items_sell":{},"items_buy":{},"price_sell":{},"price_buy":{},"count_sell":{},"count_buy":{},"ostime":1756646477,"LavkaUid":177},{"username":"[08]Templary_Henderson","items_sell":["Видеокарта","Видеокарта","Техническая часть автомобиля","Техническая часть автомобиля","Техническая часть автомобиля","Техническая часть автомобиля","Скин: Рилай (ID: 927)(+8)","Уголь","Осколок Бронежилета Генерала","Осколок Бронежилета Генерала","Инструкция для разбора аксессуара","Инструкция для разбора скинов","Желтая инструкция для разбора аксессуара","Желтая инструкция для разбора аксессуара","Желтая инструкция для разбора аксессуара","Исток","Исток","Исток","Исток","Исток","Ларец кладоискателя","Ларец кладоискателя","Ларец кладоискателя","Ларец кладоискателя","Ларец кастомных аксессуаров","Ларец Олигарха","Ларец Mortal Combat","Супер мото-ящик","Ларец с премией","Ларец с премией","Ларец с премией","Ларец организации"],"items_buy":{},"price_sell":[600000,600000,18500,18500,18500,18500,1500000,14000,43000,43000,70000,65000,350000,350000,350000,2000000,2000000,2000000,2000000,2000000,3100,3100,3100,3100,2850,1850,1500,1900,2900,2900,2900,800],"price_buy":{},"count_sell":[1,1,20,19,20,20,1,14,63,192,28,3,50,32,50,4,4,5,4,4,50,16,50,50,60,50,2,50,100,62,100,69],"count_buy":{},"ostime":1756646416,"LavkaUid":143},{"username":"[25]Salvator_SantaMontte","items_sell":{},"items_buy":{},"price_sell":{},"price_buy":{},"count_sell":{},"count_buy":{},"ostime":1756646477,"LavkaUid":213},{"username":"[26]Santerro_Bounteiro","items_sell":{},"items_buy":{},"price_sell":{},"price_buy":{},"count_sell":{},"count_buy":{},"ostime":1756646477,"LavkaUid":25},{"username":"[26]Yuki_Lester","items_sell":{},"items_buy":{},"price_sell":{},"price_buy":{},"count_sell":{},"count_buy":{},"ostime":1756646475,"LavkaUid":18},{"username":"[22]Yakov_Semenich","items_sell":{},"items_buy":{},"price_sell":{},"price_buy":{},"count_sell":{},"count_buy":{},"ostime":1756646475,"LavkaUid":310},{"username":"[18]Dark_Angelss","items_sell":{},"items_buy":{},"price_sell":{},"price_buy":{},"count_sell":{},"count_buy":{},"ostime":1756646477,"LavkaUid":213},{"username":"[29]Vasya_Bariga","items_sell":{},"items_buy":{},"price_sell":{},"price_buy":{},"count_sell":{},"count_buy":{},"ostime":1756646477,"LavkaUid":157},{"username":"[30]Angel_Skup","items_sell":{},"items_buy":{},"price_sell":{},"price_buy":{},"count_sell":{},"count_buy":{},"ostime":1756646477,"LavkaUid":86},{"username":"[01]Yomato_Opulence","items_sell":{},"items_buy":{},"price_sell":{},"price_buy":{},"count_sell":{},"count_buy":{},"ostime":1756646482,"LavkaUid":184},{"username":"[26]Varlam_Livingston","items_sell":{},"items_buy":{},"price_sell":{},"price_buy":{},"count_sell":{},"count_buy":{},"ostime":1756646480,"LavkaUid":84},{"username":"[09]Artem_Yermolenko","items_sell":{},"items_buy":{},"price_sell":{},"price_buy":{},"count_sell":{},"count_buy":{},"ostime":1756646477,"LavkaUid":216},{"username":"[07]Rento_Okamoto","items_sell":{},"items_buy":{},"price_sell":{},"price_buy":{},"count_sell":{},"count_buy":{},"ostime":1756646477,"LavkaUid":146},{"username":"[12]Nevman_Volkov","items_sell":{},"items_buy":{},"price_sell":{},"price_buy":{},"count_sell":{},"count_buy":{},"ostime":1756646477,"LavkaUid":15},{"username":"[17]Himura_Kensin","items_sell":{},"items_buy":{},"price_sell":{},"price_buy":{},"count_sell":{},"count_buy":{},"ostime":1756646477,"LavkaUid":166},{"username":"[11]Jonis_Davenport","items_sell":{},"items_buy":{},"price_sell":{},"price_buy":{},"count_sell":{},"count_buy":{},"ostime":1756646477,"LavkaUid":113},{"username":"[15]Hisoka_Explorer","items_sell":{},"items_buy":{},"price_sell":{},"price_buy":{},"count_sell":{},"count_buy":{},"ostime":1756646477,"LavkaUid":176},{"username":"[20]Ivan_Ostanin","items_sell":{},"items_buy":{},"price_sell":{},"price_buy":{},"count_sell":{},"count_buy":{},"ostime":1756646477,"LavkaUid":319},{"username":"[26]Rusik_Gaider","items_sell":{},"items_buy":{},"price_sell":{},"price_buy":{},"count_sell":{},"count_buy":{},"ostime":1756646477,"LavkaUid":116},{"username":"[17]Xot_Rock","items_sell":{},"items_buy":{},"price_sell":{},"price_buy":{},"count_sell":{},"count_buy":{},"ostime":1756646477,"LavkaUid":336},{"username":"[02]Maxim_Elite","items_sell":{},"items_buy":{},"price_sell":{},"price_buy":{},"count_sell":{},"count_buy":{},"ostime":1756646478,"LavkaUid":92},{"username":"[06]Mikey_Cannon","items_sell":{},"items_buy":{},"price_sell":{},"price_buy":{},"count_sell":{},"count_buy":{},"ostime":1756646477,"LavkaUid":1},{"username":"[20]Rayder_Wilson","items_sell":{},"items_buy":{},"price_sell":{},"price_buy":{},"count_sell":{},"count_buy":{},"ostime":1756646476,"LavkaUid":13},{"username":"[05]Hesoka_Capone","items_sell":{},"items_buy":{},"price_sell":{},"price_buy":{},"count_sell":{},"count_buy":{},"ostime":1756646480,"LavkaUid":182},{"username":"[25]Robert_Paulson","items_sell":{},"items_buy":{},"price_sell":{},"price_buy":{},"count_sell":{},"count_buy":{},"ostime":1756646477,"LavkaUid":237},{"username":"[19]Dream_Page","items_sell":{},"items_buy":{},"price_sell":{},"price_buy":{},"count_sell":{},"count_buy":{},"ostime":1756646477,"LavkaUid":219},{"username":"[07]Alex_Allonso","items_sell":{},"items_buy":{},"price_sell":{},"price_buy":{},"count_sell":{},"count_buy":{},"ostime":1756646474,"LavkaUid":109},{"username":"[02]Dmitry_Contex","items_sell":{},"items_buy":{},"price_sell":{},"price_buy":{},"count_sell":{},"count_buy":{},"ostime":1756646476,"LavkaUid":47},{"username":"[19]Pavlo_Muracci","items_sell":{},"items_buy":{},"price_sell":{},"price_buy":{},"count_sell":{},"count_buy":{},"ostime":1756646477,"LavkaUid":62},{"username":"[11]Markiian_Monopoly","items_sell":["Энергетический воздушный шар","Энергетический двигатель","Энергетический двигатель","Энергетический двигатель","Энергетический двигатель","Энергетический двигатель","Рулетка космоса","Рулетка космоса","Прочная ткань","Прочная ткань","Алмазный камень","Алмазный камень","Алмазный камень","Алмазный камень","Рулетка гетто","Осколок Истока","Мешок с мясом","Осколок Правый ботинок Таноса","Нашивка на аксессуар(урон)","Нашивка на аксессуар(урон)","Нашивка на аксессуар(урон)","Нашивка на аксессуар(урон)","Смазка для разгона видеокарты","Смазка для разгона видеокарты","Смазка для разгона видеокарты","Смазка для разгона видеокарты","Смазка для разгона видеокарты","Смазка для разгона видеокарты","Смазка для разгона видеокарты","Смазка для разгона видеокарты","Смазка для разгона видеокарты","Смазка для разгона видеокарты","Смазка для разгона видеокарты","Смазка для разгона видеокарты","Смазка для разгона видеокарты","Смазка для разгона видеокарты","Смазка для разгона видеокарты","Смазка для разгона видеокарты","Видеокарта","Видеокарта","Видеокарта","Видеокарта","Видеокарта","Видеокарта","Видеокарта","Видеокарта","Видеокарта","Видеокарта","Видеокарта","Видеокарта","Видеокарта","Видеокарта","Видеокарта","Видеокарта","Видеокарта","Видеокарта","Видеокарта","Видеокарта","Видеокарта","Видеокарта","Видеокарта","Видеокарта","Видеокарта","Видеокарта","Видеокарта","Видеокарта","Видеокарта","Видеокарта","Видеокарта","Видеокарта","Видеокарта","Видеокарта","Видеокарта","Видеокарта","Видеокарта","Видеокарта","Видеокарта","Видеокарта","Видеокарта","Видеокарта","Видеокарта","Видеокарта","Видеокарта","Видеокарта","Видеокарта","Видеокарта","Видеокарта","Видеокарта","Видеокарта","Видеокарта","Видеокарта","Видеокарта","Видеокарта","Видеокарта","Видеокарта","Видеокарта","Видеокарта","Видеокарта","Видеокарта","Видеокарта","Видеокарта","Видеокарта","Видеокарта","Видеокарта"],"items_buy":{},"price_sell":[27000000,16800000,16800000,16800000,16800000,16800000,60000,60000,107000,107000,11400,11400,11400,11400,200000,5000,1000000,2500000,2500000,2500000,2500000,2500000,12500,12500,12500,12500,12500,12500,12500,12500,12500,12500,12500,12500,12500,12500,12500,12500,990000,990000,990000,990000,990000,990000,990000,990000,990000,990000,990000,990000,990000,990000,990000,990000,990000,990000,990000,990000,990000,990000,990000,990000,990000,990000,990000,990000,990000,990000,990000,990000,990000,990000,990000,990000,990000,990000,990000,990000,990000,990000,990000,990000,990000,990000,990000,990000,990000,990000,990000,990000,990000,990000,990000,990000,990000,990000,1300000,1300000,1300000,1300000,1300000,1300000,1300000,1300000],"price_buy":{},"count_sell":[1,1,1,1,1,1,46,31,81,180,149,100,169,200,9,68,1,1,1,1,1,1,81,100,100,100,100,100,100,100,100,90,100,100,100,100,100,25,1,1,1,1,1,1,1,1,1,1,1,1,1,1,1,1,1,1,1,1,1,1,1,1,1,1,1,1,1,1,1,1,1,1,1,1,1,1,1,1,1,1,1,1,1,1,1,1,1,1,1,1,1,1,1,1,1,1,1,1,1,1,1,1,1,1],"count_buy":{},"ostime":1756646431,"LavkaUid":59},{"username":"[20]Qwincy_Martelli","items_sell":{},"items_buy":{},"price_sell":{},"price_buy":{},"count_sell":{},"count_buy":{},"ostime":1756646479,"LavkaUid":211},{"username":"[23]Severe_Romanov","items_sell":{},"items_buy":{},"price_sell":{},"price_buy":{},"count_sell":{},"count_buy":{},"ostime":1756646477,"LavkaUid":212},{"username":"[07]Hermiona_Potter","items_sell":{},"items_buy":{},"price_sell":{},"price_buy":{},"count_sell":{},"count_buy":{},"ostime":1756646478,"LavkaUid":34},{"username":"[29]Hidden_McQueen","items_sell":{},"items_buy":{},"price_sell":{},"price_buy":{},"count_sell":{},"count_buy":{},"ostime":1756646475,"LavkaUid":210},{"username":"[10]Darkfoy_Stockbullet","items_sell":["Метла"],"items_buy":{},"price_sell":[1000123],"price_buy":{},"count_sell":[1],"count_buy":{},"ostime":1756646445,"LavkaUid":161},{"username":"[23]Aleks_Miller","items_sell":{},"items_buy":{},"price_sell":{},"price_buy":{},"count_sell":{},"count_buy":{},"ostime":1756646475,"LavkaUid":90},{"username":"[27]Jimmy_Dismilate","items_sell":{},"items_buy":{},"price_sell":{},"price_buy":{},"count_sell":{},"count_buy":{},"ostime":1756646368,"LavkaUid":317},{"username":"[29]Rika_Mafia","items_sell":{},"items_buy":{},"price_sell":{},"price_buy":{},"count_sell":{},"count_buy":{},"ostime":1756646476,"LavkaUid":102},{"username":"[31]Vyn_Quo","items_sell":{},"items_buy":{},"price_sell":{},"price_buy":{},"count_sell":{},"count_buy":{},"ostime":1756646421,"LavkaUid":126},{"username":"[16]Bushido_Thuggerov","items_sell":{},"items_buy":{},"price_sell":{},"price_buy":{},"count_sell":{},"count_buy":{},"ostime":1756646427,"LavkaUid":316},{"username":"[28]Kunislav_Klitorchuk","items_sell":{},"items_buy":{},"price_sell":{},"price_buy":{},"count_sell":{},"count_buy":{},"ostime":1756646477,"LavkaUid":196},{"username":"[06]Pathetic_Falcone","items_sell":["НФТ контейнер (обычный)","Нашивка на чемодан (Снижение урона противника)","Скин: Анимешная-эмо девочка (ID: 987)","Бейсбольная бита Compton","Сертификат охранника 'Hillbilly'"],"items_buy":{},"price_sell":[11300000,9100000,1100000,750000,150000],"price_buy":{},"count_sell":[1,1,1,1,1],"count_buy":{},"ostime":1756646463,"LavkaUid":300},{"username":"[27]Cheryl_Nuestra","items_sell":{},"items_buy":{},"price_sell":{},"price_buy":{},"count_sell":{},"count_buy":{},"ostime":1756646475,"LavkaUid":36},{"username":"[29]Dean_Glock","items_sell":{},"items_buy":{},"price_sell":{},"price_buy":{},"count_sell":{},"count_buy":{},"ostime":1756646475,"LavkaUid":316},{"username":"[09]Ivan_Arias","items_sell":{},"items_buy":{},"price_sell":{},"price_buy":{},"count_sell":{},"count_buy":{},"ostime":1756646490,"LavkaUid":98}]