[{"username":"[30]Delta_Freehouse","items_sell":["Легендарная мусорка на спину","Торговый ключ","Дифференциал (sport+)"],"items_buy":{},"price_sell":[5000000,5000000,5000000],"price_buy":{},"count_sell":[1,1,1],"count_buy":{},"ostime":1751508766,"LavkaUid":1},{"username":"[23]Fur_Gonchik","items_sell":["Алюминий","Энергетический воздушный шар(+13)","Скин: Ребекка (ID: 634)(+12)","Маска череп","Маска череп","Оружие Бамбли Би","Бронежилет «Орда»(+4)","Ледяной меч(+13)","Наёмный фермер","Нашивка на чемодан (Снижение урона противника)","Нашивка на чемодан (Снижение урона противника)","Нашивка на чемодан (Снижение урона противника)","Нашивка на чемодан (Снижение урона противника)","Нашивка на чемодан (Снижение урона противника)","Нашивка на чемодан (Снижение урона противника)","Нашивка на чемодан (Снижение урона противника)","Нашивка на чемодан (Снижение урона противника)","Нашивка на чемодан (Снижение урона противника)","Нашивка на чемодан (Снижение урона противника)","Заточенный компенсатор","Заточенный компенсатор","Граната Оглушающая","Старая карта кладов","Увеличенный магазин (X3) для Mac-10","Увеличенный магазин (X3) для Mac-10","Монета охотника","Бронза","Бронза","Бронза","Бронза","Бронза","Бронза"],"items_buy":{},"price_sell":[9800,30499000,15000000,6500000,6500000,4900000,7500000,105000000,14999999,9699999,9699999,9699999,9699999,9699999,9699999,9699999,9699999,9699999,9699999,6500000,6500000,500000,200000,1500000,1500000,55,480,480,480,480,480,480],"price_buy":{},"count_sell":[471,1,1,1,1,1,1,1,1,1,1,1,1,1,1,1,1,1,1,1,1,121,1,1,1,15951,1000,836,1000,182,900,1000],"count_buy":{},"ostime":1751508721,"LavkaUid":66},{"username":"[18]Beluga_ViceCity","items_sell":["Скин: Йода (ID: 351)(+10)","Бронежилет «Лайт»(+8)","Маска охранника 2(+13)","Мешок с мясом","Скин: Аквамен (ID: 878)(+12)","Велосипед на спину(+5)","Бронежилет «Гравити Фолз»(+8)","Анимированные часы на спину (на спутника)","Нимб кольца всевластия(+13)","Маска череп(+13)","Оружие Бамбли Би(+13)","Оружие Бамбли Би(+13)","Оружие Бамбли Би","Энергетический чемодан","Энергетический чемодан","Энергетический воздушный шар(+13)","Энергетический воздушный шар(+13)","Энергетический воздушный шар(+13)","Энергетический воздушный шар(+13)","Часы 'Gucci'(+13)","Платиновая рулетка"],"items_buy":{},"price_sell":[54000000,8800000,11500000,1050000,13000000,1100000,7900000,5500000,24500000,20500000,16500000,16500000,5200000,26000000,26000000,30400000,30400000,30400000,30400000,12000000,7000],"price_buy":{},"count_sell":[1,1,1,1,1,1,1,1,1,1,1,1,1,1,1,1,1,1,1,1,51],"count_buy":{},"ostime":1751508728,"LavkaUid":49},{"username":"[28]Barry_Show","items_sell":["Шкатулка кладоискателя","Прочная ткань","Нашивка на скин (Бег Си Джея)","Прототип(+12)","Цепь «Махинатор»(+12)","Элитная переносная лавка(+11)","Элитная переносная лавка","Элитная переносная лавка","Скин: Макима (ID: 904)","Энергетический воздушный шар(+12)","Обрез (активный аксессуар)","Обрез (активный аксессуар)","Обрез (активный аксессуар)","Обрез (активный аксессуар)","Обрез (активный аксессуар)","Обрез (активный аксессуар)"],"items_buy":{},"price_sell":[12950000,121000,16000000,7300000,10500000,11400000,11200000,11200000,23000000,28000000,6250000,6250000,6250000,6250000,6250000,6250000],"price_buy":{},"count_sell":[1,43,1,1,1,1,1,1,1,1,1,1,1,1,1,1],"count_buy":{},"ostime":1751508721,"LavkaUid":52},{"username":"[28]Noah_Husted","items_sell":["Древесина высшего качества","Древесина высшего качества","Древесина высшего качества","Древесина высшего качества","Темная материя","Серебро","Дрова","Гражданский талон","Опыт депозита","Семейный талон","Зловещая монета","Сироп майнера","Алмазный камень","Подарок","Точильный амулет","Камень","Монета охотника","Хлопок","Хлопок","Лён","Лён","Лён","Алюминий","Обрез","Обрез","Обрез","Обрез","Обрез","Обрез","Обрез","Монета Миража"],"items_buy":{},"price_sell":[785,785,785,785,81500,280,15,150,5400,330,4400,1000,11800,280,4400,580,45,79,79,80,80,80,9900,700,700,700,700,700,700,700,9200],"price_buy":{},"count_sell":[300,300,300,146,1,19,2355,39,12,39,2,1,1,17,4,13,2847,600,348,440,297,419,1,500,500,500,500,500,500,94,21],"count_buy":{},"ostime":1751508777,"LavkaUid":25},{"username":"[02]Healing_Proof","items_sell":["Скин: Гоблин 3 (ID: 779)(+12)","Документ для отмывания денег","Документ для отмывания денег","Документ для отмывания денег","Документ для отмывания денег","Документ для отмывания денег","Бизнес реквизит","Магический воздушный шар #2","Генеральский бронежилет","Осколок шкатулки кладоискателя","Сертификат охранника 'Скуби-Ду Хэллоуин'","Переносной верстак миража","Тайник Собирателя","Маска череп","Маска череп","Шкатулка кладоискателя","Элитная переносная лавка","Складная магическая лавка","Сертификат охранника 'Петух'","Сертификат бесконечного Дополнения VIP","Сертификат Дополнения VIP","Сертификат Дополнения VIP","Сертификат Дополнения VIP","Нашивка на бронежилет (Защита от оглушения)","Нашивка на бронежилет (Защита от оглушения)","Нашивка на скин (Огненные пули)","Сироп характеристик актера","Осколок Audi RS Q8 Mansory","Грамота ветерана","Анимированный огненный глаз (на спутника)","Маска Муэрты (на спутника)","Маска Муэрты (на спутника)","Запечатанный сертификат на транспорт","12 уровень персонажа","12 уровень персонажа","Осколок Молот Тора","Золотой кейс","Заточка +13","Осколок предмета Заточка +13","Супер-заточка","Талон на 12 x4 PayDay (передаваемый)","Осколок Тайника Собирателя","Осколок Портальной пушки","Заточка для оружия","Заточка для оружия","Заточка для оружия","Заточка для оружия","Заточка для оружия","Заточка для оружия","Желтая инструкция для разбора аксессуара","Желтая инструкция для разбора аксессуара","Инструкция для разбора аксессуара","Инструкция для разбора аксессуара","Инструкция для разбора аксессуара","Инструкция для разбора аксессуара","Осколок Бронежилета Генерала","Монета Миража","Кусок редкой ткани","Рыбная монета","Бронза","Бронза","Прочная ткань","Прочная ткань","Шахтерский сплав","Шахтерский сплав","Шахтерский сплав","Темная материя","Темная материя","Темная материя","Темная материя","Темная материя","Темная материя","Темная материя","Темная материя","Темная материя","Алмазный камень","Алмазный камень","Алмазный камень","Алмазный камень","Алмазный камень","Алмазный камень","Алмазный камень","Алмазный камень","Алмазный камень","Алмазный камень","Современная карта кладов","Кенгурятник Зомби-Апокалипсиса","Извлекатель нашивки","Монета охотника","Золотая рулетка","Бодрящий сок","Бодрящий сок"],"items_buy":{},"price_sell":[500000000,17000000,17000000,17000000,17000000,17000000,4200000,10500000,41500000,2600000,25000000,3400000,8000000,6000000,6000000,12900000,11000000,10500000,8000000,10500000,2700000,2700000,2700000,9999999,9999999,10000000,1300000,2500000,10500000,6100000,6000000,6000000,3400000,3000000,3000000,1400000,850000,4700000,1000000,90000,1500000,500000,2500000,180000,180000,180000,180000,180000,180000,500000,500000,70000,70000,70000,70000,45000,9500,9900,1500,450,450,124000,124000,95000,95000,95000,95000,95000,95000,95000,95000,95000,95000,95000,95000,12500,12500,12500,12500,12500,12500,12500,12500,12500,12500,4000000,2000000,400000,135,4500,200000,200000],"price_buy":{},"count_sell":[1,1,1,1,1,1,2,1,1,2,1,1,1,1,1,1,1,1,1,1,1,1,1,1,1,1,56,2,1,1,1,1,3,1,1,1,1,6,5,46,2,5,1,50,50,50,50,50,35,50,8,50,50,35,19,70,189,1937,1756,1000,1000,200,198,200,200,137,50,50,50,50,50,50,50,50,46,200,200,200,200,200,200,200,200,200,51,1,1,40,32154,100,50,38],"count_buy":{},"ostime":1751508747,"LavkaUid":62},{"username":"[01]Tif_Cloud","items_sell":["Улучшение Большие карманы"],"items_buy":{},"price_sell":[123123213],"price_buy":{},"count_sell":[1],"count_buy":{},"ostime":1751508728,"LavkaUid":33},{"username":"[18]Lil_Ghoul","items_sell":["Скин: Гринч (ID: 459)(+11)","НФТ контейнер (обычный)","Кровавые крылья(+13)","Магический воздушный шар #2(+6)","Нашивка на бронежилет (Защита от оглушения)","Нашивка на бронежилет (Защита от оглушения)","Нашивка на бронежилет (Защита от оглушения)","Нашивка на бронежилет (Защита от оглушения)","Бронежилет «Невермор»(+12)","Цепь Иллюмината(+12)","Цепь Иллюмината(+10)","Щит Капитана Америки(+13)","Рука бесконечности(+12)","Супер-кирка(+10)","Ангельское кольцо на голову(+13)","Велосипед на спину(+12)","Голова Тыква","Нашивка на аксессуар(защита)","Неоновая маска(+10)","Супер-лопата(+12)","Скин: Мидас (ID: 806)","Скин: BMXer (ID: 23)","Скин: Карась (ID: 804)(+10)","Голова Фредди(+9)","Батлфьюри","Бензопила на спину","Восточный переносной ларек 3","Желтая инструкция для разбора аксессуара","Крылья #5","Кепка 'Supreme'(+10)","Маска Локи","Маска Локи","Маска Локи","Скин: LS Police Officer (ID: 303)","Дельфин бирюзовый","Крылья бабочки","Извлекатель нашивки","Прочная ткань","Шахтерский сплав","Шахтерский сплав"],"items_buy":{},"price_sell":[21000000,15100000,10400000,10250000,10100000,10100000,10100000,10100000,9900000,7850000,7250000,6400000,5800000,4500000,4490000,4000000,3300000,2400000,1100000,1100000,1100000,990000,950000,850000,650000,550000,450000,450000,350000,350000,325000,325000,325000,300000,300000,150000,149000,118000,80000,80000],"price_buy":{},"count_sell":[1,1,1,1,1,1,1,1,1,1,1,1,1,1,1,1,1,1,1,1,1,1,1,1,1,1,1,6,1,1,1,1,1,1,1,1,30,34,54,200],"count_buy":{},"ostime":1751508756,"LavkaUid":73},{"username":"[29]Florian_Florencia","items_sell":["Скин: Тракса аркана (ID: 928)","Генеральский бронежилет","Энергетический воздушный шар(+12)","Энергетический чемодан","Энергетический чемодан","Энергетический двигатель","Энергетический двигатель","Шкатулка кладоискателя","Часы 'Gucci'(+13)","Часы 'Apple Watch'(+13)","Чемодан зомби","Маска-невидимка(+12)","Нимб кольца всевластия","Нимб кольца всевластия","Нимб кольца всевластия","Нимб кольца всевластия","Нимб кольца всевластия","Меч хранителя","Наёмный фермер","Сертификат бесконечного Дополнения VIP","Документ для отмывания денег","Документ для отмывания денег","Документ для отмывания денег","Документ для отмывания денег","Документ для отмывания денег","Документ для отмывания денег","Документ для отмывания денег","Документ для отмывания денег","Цепь Иллюмината(+13)","Магический воздушный шар #1(+12)","Магический воздушный шар #7(+12)","Магический воздушный шар #7(+12)","Магический воздушный шар #6(+12)","Магический воздушный шар #2(+10)","Танго(+13)","Молот «Duff»(+12)","Щит Капитана Америки(+13)","Ангельское кольцо на голову(+12)","Анимированный Пончиковый нимб(+12)","Клинки Аззинота(+13)","Осколок Хоумлендера","Батлфьюри(+13)","НФТ контейнер (обычный)","НФТ контейнер (обычный)","НФТ контейнер (обычный)","НФТ контейнер (обычный)","НФТ контейнер (обычный)","Гоблинский НФТ контейнер","Гоблинский НФТ контейнер","Гоблинский НФТ контейнер","Гоблинский НФТ контейнер","Гоблинский НФТ контейнер","Гоблинский НФТ контейнер","Маска череп(+13)","Маска череп(+13)","Кровавые крылья(+13)","Оружие Бамбли Би(+12)","Оружие Бамбли Би(+12)","Бронежилет «Гравити Фолз»(+5)","Бронежилет «Орда»(+9)","Бронежилет «Симпсоны»(+7)","Бронежилет Конь БоДжек»","Маска Чубаки(+13)","Современная карта кладов","Современная карта кладов","Современная карта кладов","Современная карта кладов","Современная карта кладов","Парящий скейтборд","Золотой кейс","Скин: Правая (ID: 698)(+11)","Скин: Франклин Клинтон (ID: 859)(+12)","Именное поместье","Маска Локи(+13)","Маска 'Wrench'(+13)","Усы (длинные)(+13)","Нашивка на аксессуар(защита)","Энергетический чемодан","Танго","Молот «Duff»"],"items_buy":{},"price_sell":[16500000,41999888,34000000,26000000,26000000,15488888,15488888,13099000,11800000,8999999,6900000,5600000,7999999,7999999,7999999,7999999,7999999,50000000,14400000,10999999,17398000,17398000,17398000,17398000,17398000,17398000,17398000,17398000,23400000,11000000,12200000,12200000,12300000,10700000,13000000,5500000,6500000,2700000,1800000,16500000,14000000,12200000,15150000,15150000,15150000,15150000,15150000,14900000,14900000,14900000,14900000,14900000,14900000,20000000,20000000,12999999,14300000,14300000,7500000,8500000,7250000,6700000,2300000,3600000,3600000,3600000,3600000,3600000,3000000,880000,15000000,12999999,27700000,11300000,11300000,12000000,2100000,16900000,4500000,4500000],"price_buy":{},"count_sell":[1,1,1,1,1,1,1,1,1,1,1,1,1,1,1,1,1,1,1,1,1,1,1,1,1,1,1,1,1,1,1,1,1,1,1,1,1,1,1,1,3,1,1,1,1,1,1,1,1,1,1,1,1,1,1,1,1,1,1,1,1,1,1,1,1,1,1,1,1,6,1,1,1,1,1,1,1,1,1,1],"count_buy":{},"ostime":1751508723,"LavkaUid":58},{"username":"[21]Harya_Herrington","items_sell":["Монета Миража","Монета Миража","Монета Миража","Монета Миража","Монета Миража","Монета Миража","Монета Миража","Монета Миража","Монета Миража"],"items_buy":{},"price_sell":[12998,12998,12998,12998,12998,12998,12998,12998,12998],"price_buy":{},"count_sell":[200,200,200,200,200,200,200,200,200],"count_buy":{},"ostime":1751508739,"LavkaUid":56},{"username":"[02]John_Barrow","items_sell":{},"items_buy":{},"price_sell":{},"price_buy":{},"count_sell":{},"count_buy":{},"ostime":1751508622,"LavkaUid":57},{"username":"[14]Niveiika_Men","items_sell":["Золотой длинный Desert Eagle на бедро(+13)"],"items_buy":{},"price_sell":[10300000],"price_buy":{},"count_sell":[1],"count_buy":{},"ostime":1751508742,"LavkaUid":53},{"username":"[16]Zasa_Diey","items_sell":{},"items_buy":["Обрез"],"price_sell":{},"price_buy":[480],"count_sell":{},"count_buy":[13834],"ostime":1751508728,"LavkaUid":63},{"username":"[15]Kisa_Kunteynir","items_sell":["Жабка рыбак"],"items_buy":{},"price_sell":[350000],"price_buy":{},"count_sell":[1],"count_buy":{},"ostime":1751508763,"LavkaUid":10},{"username":"[10]Alex_Belfort","items_sell":["Увеличенный магазин (X3) для Tec-9","Увеличенный магазин (X3) для Tec-9","Увеличенный магазин (X3) для M16","Увеличенный магазин (X3) для M16","Увеличенный магазин (X3) для Mac-10","Увеличенный магазин (X3) для Mac-10","Инструкция для разбора аксессуара","Инструкция для разбора аксессуара","Инструкция для разбора аксессуара","Инструкция для разбора аксессуара","Super Car Box","Ларец кастомных аксессуаров","Ларец крафтера","Ларец Mortal Combat","Ларец рыболова","Рандомный Ларец","Ларец Tidex","Ларец семейных охранников","Ларец петуха","Ларец Fortnite","Ларец Arizona","Ящик Minecraft","Ящик Marvel","Ящик Джентельменов","Ностальгический ящик","Осколок ящика секретной машины","Талон на смену никнейма","Талон снятия предупреждений","Бронзовая рулетка","Бронзовая рулетка","Бронзовая рулетка","Бронзовая рулетка","Бронзовая рулетка","Бронзовая рулетка","Бронзовая рулетка","Бронзовая рулетка","Бронзовая рулетка","Бронзовая рулетка","Бронзовая рулетка","Бронзовая рулетка","Бронзовая рулетка","Бронзовая рулетка","Бронзовая рулетка","Бронзовая рулетка","Бронзовая рулетка","Бронзовая рулетка","Бронзовая рулетка","Бронзовая рулетка","Бронзовая рулетка","Бронзовая рулетка","Бронзовая рулетка","Бронзовая рулетка","Бронзовая рулетка","Бронзовая рулетка","Бронзовая рулетка","Бронзовая рулетка","Бронзовая рулетка","Бронзовая рулетка","Бронзовая рулетка","Бронзовая рулетка","Бронзовая рулетка","Бронзовая рулетка","Бронзовая рулетка","Бронзовая рулетка","Бронзовая рулетка","Бронзовая рулетка","Бронзовая рулетка","Бронзовая рулетка","Бронзовая рулетка","Бронзовая рулетка","Бронзовая рулетка","Бронзовая рулетка","Бронзовая рулетка","Бронзовая рулетка","Бронзовая рулетка","Бронзовая рулетка","Бронзовая рулетка","Бронзовая рулетка","Бронзовая рулетка","Бронзовая рулетка","Бронзовая рулетка","Бронзовая рулетка","Бронзовая рулетка","Бронзовая рулетка","Платиновая рулетка","Рулеточный компас","Рулеточный компас","Рулеточный компас","Камень","Камень","Дрова","Серебро","Бронза","Золото","Металл","Алюминий","Зловещая монета","Зловещая монета","Зловещая монета","Рыбная монета","Семейная монета","Прочная ткань","Подарок","Охлаждающая жидкость для видеокарты","Охлаждающая жидкость для видеокарты","Охлаждающая жидкость для видеокарты","Восстановленная карта кладов","Современная карта кладов","Вечная рабочая виза","Эхолот для рыбалки","Торговый ключ","Чип-тюнинг (STAGE 3)","Чип-тюнинг (STAGE 3)","Супер-лопата","Супер-лопата","Супер-лопата","Супер-лопата","Жареное мясо оленины","Жареное мясо оленины","Жареное мясо оленины","Мешок с мясом","Опыт депозита","Опыт депозита","Опыт депозита","Опыт депозита","Опыт депозита","Осколок Истока","Лицензия дипломата","Лицензия дипломата","Лицензия дипломата","Исток"],"items_buy":{},"price_sell":[560000,560000,460000,460000,1450000,1450000,65000,65000,65000,65000,5100,3600,3800,1300,3350,2400,2000,4400,4800,2800,8000,1250,1350,1200,2500,24300,39000,475000,252,252,252,252,252,252,252,252,252,252,252,252,252,252,252,252,252,252,252,252,252,252,252,252,252,252,252,252,252,252,252,252,252,252,252,252,252,252,252,252,252,252,252,252,252,252,252,252,252,252,252,252,252,252,252,252,7100,990000,990000,990000,590,590,16,320,475,1250,3100,9950,4000,4000,4000,1300,35,120000,290,3100,3100,3100,875000,4750000,125000,700000,55000,290000,290000,1150000,1150000,1150000,1150000,1900,1900,1900,1100000,6000,6000,6000,6000,6000,20000,1850000,1850000,1850000,2900000],"price_buy":{},"count_sell":[1,1,1,1,1,1,50,41,50,50,1,21,9,6,1,12,31,13,54,67,31,13,3,2,1,7,1,1,100,96,100,96,100,100,100,100,100,100,100,100,100,100,100,100,100,100,100,100,100,100,100,100,100,100,100,100,100,100,100,100,100,100,100,100,100,100,100,100,100,100,100,100,100,100,100,100,100,100,100,100,100,100,100,100,3,1,1,1,837,787,1810,33,1000,18,42,39,50,32,37,616,2768,1,2543,100,100,50,1,1,1,1,1,1,1,1,1,1,1,80,31,80,1,14,100,100,97,100,6,1,1,1,1],"count_buy":{},"ostime":1751508758,"LavkaUid":54},{"username":"[29]Code_Vosemdesyat","items_sell":["Платиновая рулетка"],"items_buy":{},"price_sell":[500000],"price_buy":{},"count_sell":[1],"count_buy":{},"ostime":1751508751,"LavkaUid":2},{"username":"[14]Last_Try","items_sell":["Современная карта кладов","Современная карта кладов","Современная карта кладов","Современная карта кладов","Современная карта кладов","Современная карта кладов","Современная карта кладов","Грамота ветерана","Анимированные очки Netrunner(+12)","Магический воздушный шар #6(+11)","Рука бесконечности(+12)","Шлем железного человека(+12)","Мидас(+8)","Молот Тора(+13)","Шлем «Собачка»(+13)","Супер-лопата","Супер-лопата","Супер-лопата(+10)","Оружие Бамбли Би","Оружие Бамбли Би","Анимированный Пончиковый нимб(+12)","Переносной верстак миража(+10)","Planet Express(+12)","Planet Express(+12)","Маска череп","Паучьи лапы","Паучьи лапы","Анимированная пчела","Анимированная пчела(+12)","Анимированная пчела(+7)","Кровавые крылья(+13)","Кровавые крылья","Кровавые крылья","Пояс боеприпасов","Пояс боеприпасов","Пояс боеприпасов","Пояс боеприпасов","Пояс боеприпасов","Пояс боеприпасов","Пояс боеприпасов","Пояс боеприпасов","Пояс боеприпасов","Складная мусорная лавка(+5)","Аегис(+8)","Дельтаплан на спину(+8)","Дельтаплан на спину","Руки сэта","Обрез (активный аксессуар)(+9)","Переносной ларек Рика 1","Шлем с рогами(+13)","Эффект «Рыбки в пруду»(+13)","Сироп характеристик актера","Скин: Дэдпул (ID: 883)(+8)","Скин: Оксана Чемпионка (ID: 972)(+12)","Скин: Оксана Чемпионка (ID: 972)(+10)","Скин: Джокер (ID: 929)(+7)","Скин: Люцифер (ID: 666)(+12)","Скин: Тоф Бейфонг (ID: 814)","Скин: Алиса Лидделл (ID: 642)","Бронежилет Конь БоДжек»(+12)","Бронежилет «Игра в кальмара»(+11)","Бронежилет «Орда»(+9)","Исток","Анимированные часы на спину (на спутника)","Увеличенный магазин (X3) для Sawnoff","Осколок автомобиля Охотников за привидениями","Нашивка на чемодан (Снижение урона противника)","Флешка майнера","Twin Turbo","Дрова","Дрова","Дрова","Дрова","Дрова","Дрова","Дрова","Дрова","Дрова","Дрова","Дрова","Дрова","Дрова","Дрова","Дрова","Дрова","Чип-тюнинг (STAGE 3)","Чип-тюнинг (STAGE 3)","Чип-тюнинг (STAGE 3)","Дифференциал (sport+)","Дифференциал (sport+)","Подвеска (sport+)","Подвеска (sport+)","Подвеска (sport+)","Подвеска (sport+)","Ларец петуха","Super Car Box","Ларец с премией","Ларец пилота","Ностальгический ящик","Ларец кладоискателя","Ларец Tidex","Ларец семейных охранников","Секретный аксессуар","Осколок ящика секретной машины","Эффект x4 пополнение счёта (24 часа)","Монета основания","Зловещая монета","Зловещая монета","Точильный амулет","Точильный амулет","Точильный амулет","Точильный амулет","Камень","Бронза","Алюминий","Подарок","Бронзовая рулетка","Золотая рулетка","Платиновая рулетка","AZ-Монеты (Передаваемые)","Опыт депозита","Опыт депозита","Гражданский талон"],"items_buy":{},"price_sell":[14350000,14350000,14350000,14350000,14350000,14350000,14350000,11000000,8500000,10400000,6000000,3300000,4000000,8500000,5000000,1200000,1200000,1300000,5500000,5500000,2100000,3100000,4000000,4000000,6500000,1000000,1000000,800000,1000000,850000,13500000,7500000,7500000,300000,300000,300000,300000,300000,300000,300000,300000,300000,3000000,1250000,1150000,1100000,2800000,6400000,4000000,4500000,10000000,1280000,1500000,7500000,7450000,11000000,1400000,1350000,4000000,11500000,10500000,9000000,2600000,5500000,11500000,4000000,9000000,2500000,200000,16,16,16,16,16,16,16,16,16,16,16,16,16,16,16,16,265000,265000,265000,180000,180000,180000,180000,180000,180000,4950,5035,2500,6000,2735,2750,2050,3515,150000,25000,100000,535,4400,4400,4700,4700,4700,4700,585,430,9950,290,235,5000,6950,755,5400,5400,150],"price_buy":{},"count_sell":[1,1,1,1,1,1,1,1,1,1,1,1,1,1,1,1,1,1,1,1,1,1,1,1,1,1,1,1,1,1,1,1,1,1,1,1,1,1,1,1,1,1,1,1,1,1,1,1,1,1,1,1,1,1,1,1,1,1,1,1,1,1,3,1,1,1,1,1,1,30000,30000,30000,30000,30000,30000,30000,30000,30000,30000,30000,30000,30000,30000,30000,28655,1,1,1,1,1,1,1,1,1,26,4,16,4,1,4,3,1,6,56,5,404,50,45,10,10,10,3,19,169,101,751,2,2,11,12,27,100,1],"count_buy":{},"ostime":1751508752,"LavkaUid":55},{"username":"[30]Alex_Tarantino","items_sell":["Передний отбойник Аварийная пружина","Передний отбойник Аварийная пружина","Камень","Нимб из колец Соника(+7)","Часы 'Rolex Submariner'(+12)","Заточка +13","Набор бронежилетов","Семейный талон","Мусорный нимб(+12)","Желтая инструкция для разбора аксессуара","Arizona Video Card"],"items_buy":{},"price_sell":[120000,120000,588,500000,1250000,4925000,70000,328,770000,330000,29000],"price_buy":{},"count_sell":[1,1,72,1,1,1,1,14,1,1,1],"count_buy":{},"ostime":1751508766,"LavkaUid":61},{"username":"[08]Alice_Grimm","items_sell":["Чертеж характеристик скина","Слива","Нашивка на аксессуар(урон)","Нашивка на аксессуар(урон)","Нашивка на аксессуар(урон)","Нашивка на аксессуар(урон)","Скади(+13)","Крылья Инвокера(+13)","Рецепт адреналина","Задний отбойник Спойлер с закисью","Чертеж характеристик скина","Слива","Нашивка на аксессуар(урон)","Нашивка на аксессуар(урон)","Нашивка на аксессуар(урон)","Нашивка на аксессуар(урон)","Скади(+13)","Крылья Инвокера(+13)","Доллар на грудь"],"items_buy":["Инструкция для разбора скинов","Скин: Тоф Бейфонг (ID: 814)","Фургон возрождения","Все навыки стрельбы","Обрез","Редкие материалы"],"price_sell":[9000000,150,2500000,2500000,2500000,2500000,7500000,2500000,500,350000,9000000,150,2500000,2500000,2500000,2500000,7500000,2500000,2000000],"price_buy":[87000,1000000,300000,650000,515,6000],"count_sell":[1,65,1,1,1,1,1,1,1,1,1,65,1,1,1,1,1,1,1],"count_buy":[47,1,4,10,19100,2000],"ostime":1751508742,"LavkaUid":59},{"username":"[30]Ruslyana_Dredd","items_sell":["Скин: Шериф (ID: 898)(+10)","Оружие Бамбли Би(+12)","Секретный аксессуар","Оранжевая магическая шляпа","Оранжевая магическая шляпа","Магическая шляпа Мегумин","Магическая шляпа Мегумин","Магическая шляпа Мегумин","Рецепт: Кольцо всевластия","Рецепт: Коса марси","Ларец пилота","Ларец организации","Ларец Олигарха","Платиновая рулетка","Золотая рулетка","Серебряная рулетка","Бронзовая рулетка","Камень","Серебро","Жареное мясо оленины","Жареное мясо оленины","Жареное мясо оленины","Жареное мясо оленины","Жареное мясо оленины","Жареное мясо оленины","Жареное мясо оленины","Нимб Доры","Нимб Доры","Неоновая подсветка (настраиваемая)","Неоновая подсветка (настраиваемая)","Неоновая подсветка (настраиваемая)","Неоновая подсветка (настраиваемая)","Неоновая подсветка (настраиваемая)","Голова Робосанты","Голова Робосанты","Голова Робосанты","Голова Робосанты","Голова Робосанты","Голова Робосанты","Голова Робосанты","Голова Робосанты","Голова Робосанты","Голова Робосанты","Голова Робосанты","Голова Робосанты","Голова Робосанты","Гражданский талон","Гражданский талон","Гражданский талон","Объект: Мусорка для дома","Объект: Мусорка для дома","Объект: Мусорка для дома","Объект: Мусорка для дома","Объект: Мусорка для дома","Объект: Мусорка для дома","Объект: Мусорка для дома","Объект: Мусорка для дома","Объект: Мусорка для дома","Объект: Мусорка для дома","Объект: Мусорка для дома","Объект: Мусорка для дома","Арбалет Траксы","Арбалет Траксы","Арбалет Траксы","Арбалет Траксы","Арбалет Траксы","Арбалет Траксы","Арбалет Траксы","Арбалет Траксы","Арбалет Траксы","Арбалет Траксы","Арбалет Траксы","Арбалет Траксы","Арбалет Траксы","Арбалет Траксы","Арбалет Траксы","Арбалет Траксы","Арбалет Траксы","Арбалет Траксы","Арбалет Траксы","Арбалет Траксы"],"items_buy":{},"price_sell":[13499900,12999900,159990,289900,289900,169900,169900,169900,39900,39900,6499,849,2099,6949,4799,1149,259,579,369,2499,2499,2499,2499,2499,2499,2499,249900,249900,199900,199900,199900,199900,199900,99900,99900,99900,99900,99900,99900,99900,99900,99900,99900,99900,99900,99900,179,179,179,199900,199900,199900,199900,199900,199900,199900,199900,199900,199900,199900,199900,46999900,46999900,46999900,46999900,46999900,46999900,46999900,46999900,46999900,46999900,46999900,46999900,46999900,46999900,46999900,46999900,46999900,46999900,46999900,46999900],"price_buy":{},"count_sell":[1,1,8,1,1,1,1,1,2,2,20,16,2,3,3,1,3,6,294,70,80,80,80,80,80,70,1,1,1,1,1,1,1,1,1,1,1,1,1,1,1,1,1,1,1,1,2502,4000,195,1,1,1,1,1,1,1,1,1,1,1,1,1,1,1,1,1,1,1,1,1,1,1,1,1,1,1,1,1,1,1,1],"count_buy":{},"ostime":1751508775,"LavkaUid":79},{"username":"[18]Bibon_Covalli","items_sell":["Скин: Уэенсдей Аддамс [2022] (ID: 649)(+8)","НФТ контейнер (средний)","НФТ контейнер (средний)","НФТ контейнер (обычный)","НФТ контейнер (обычный)","НФТ контейнер (обычный)","НФТ контейнер (обычный)","НФТ контейнер (обычный)","НФТ контейнер (обычный)","НФТ контейнер (обычный)","НФТ контейнер (обычный)","Админ зарплата","Меч хранителя","Складная мусорная лавка(+8)","Складная мусорная лавка","Складная мусорная лавка","Элитная переносная лавка(+12)","Меч ВК","Меч ВК","Меч ВК","Сферы инвокера","Сферы инвокера","МайнСкелет","МайнСкелет","Шкатулка кладоискателя","Шкатулка кладоискателя","Шкатулка кладоискателя","Шкатулка кладоискателя","Шкатулка кладоискателя","Шкатулка кладоискателя","Шкатулка кладоискателя","Шкатулка кладоискателя","Шкатулка кладоискателя","Шкатулка кладоискателя","Шкатулка кладоискателя","Шкатулка кладоискателя","Шкатулка кладоискателя","Шкатулка кладоискателя","Шкатулка кладоискателя","Шкатулка кладоискателя","Шкатулка кладоискателя","Шкатулка кладоискателя","Шкатулка кладоискателя","Шкатулка кладоискателя","Шкатулка кладоискателя","Шкатулка кладоискателя","Шкатулка кладоискателя","Шкатулка кладоискателя","Шкатулка кладоискателя","Шкатулка кладоискателя","Шкатулка кладоискателя","Шкатулка кладоискателя","Шкатулка кладоискателя","Шкатулка кладоискателя","Кровавые крылья(+13)","Кровавые крылья(+13)","Генеральский бронежилет","Документ для отмывания денег","Желтая инструкция для разбора аксессуара","Гоблинский НФТ контейнер","Майнер Тёмной материи","Twin Turbo (2 уровня)","Анимированные очки Netrunner(+13)","Элитная переносная лавка","Элитная переносная лавка","Элитная переносная лавка","Элитная переносная лавка","Элитная переносная лавка","Грамота ветерана","Грамота ветерана","Прочная ткань","Прочная ткань","Прочная ткань","Смазка для разгона видеокарты","Смазка для разгона видеокарты","Смазка для разгона видеокарты","Смазка для разгона видеокарты","Смазка для разгона видеокарты","Смазка для разгона видеокарты","Смазка для разгона видеокарты","Смазка для разгона видеокарты","Шахтерский сплав","Шахтерский сплав","Шахтерский сплав","Монета охотника","Монета охотника","Алмазный камень","Алмазный камень","Алмазный камень","Алмазный камень","Нашивка на аксессуар(урон)","Нашивка на аксессуар(урон)","Нашивка на аксессуар(урон)","Нашивка на аксессуар(урон)","Нашивка на аксессуар(урон)","Нашивка на аксессуар(урон)","Нашивка на аксессуар(урон)","Бронзовая рулетка","Серебряная рулетка","Серебряная рулетка","Серебряная рулетка","Мешок с мясом","Руки сэта(+9)","Дрова","Дрова","Дрова","Дрова","Дрова","Дрова","Дрова","Дрова","Дрова","Дрова","Дрова","Дрова","Дрова","Дрова"],"items_buy":{},"price_sell":[1600000,16000000,16000000,15400000,15400000,15400000,15400000,15400000,15400000,15400000,15400000,1600,54000000,3000000,2900000,2900000,11600000,2900000,2900000,2900000,4500000,4500000,7500000,7500000,12950000,12950000,12950000,12950000,12950000,12950000,12950000,12950000,12950000,12950000,12950000,12950000,12950000,12950000,12950000,12950000,12950000,12950000,12950000,12950000,12950000,12950000,12950000,12950000,12950000,12950000,12950000,12950000,12950000,12950000,12700000,12700000,42700000,18000000,400000,15500000,34950000,4400000,10300000,11250000,11250000,11250000,11250000,11250000,11000000,11000000,120000,120000,120000,12500,12500,12500,12500,12500,12500,12500,12500,85000,85000,85000,45,45,12000,12000,12000,12000,2250000,2250000,2250000,2250000,2250000,2250000,2250000,220,1150,1150,1150,1000000,3000000,14,14,14,14,14,14,14,14,14,14,14,14,14,14],"price_buy":{},"count_sell":[1,1,1,1,1,1,1,1,1,1,1,11874,1,1,1,1,1,1,1,1,1,1,1,1,1,1,1,1,1,1,1,1,1,1,1,1,1,1,1,1,1,1,1,1,1,1,1,1,1,1,1,1,1,1,1,1,1,1,5,1,1,1,1,1,1,1,1,1,1,1,200,200,139,100,100,100,100,100,99,100,100,35,200,169,50000,11398,185,138,100,107,1,1,1,1,1,1,1,100,74,100,80,1,1,30000,30000,30000,30000,30000,30000,30000,30000,30000,25186,21599,30000,30000,30000],"count_buy":{},"ostime":1751508756,"LavkaUid":71},{"username":"[16]Lord_Company","items_sell":["Бандитская сумка(2)(+8)"],"items_buy":{},"price_sell":[43534534],"price_buy":{},"count_sell":[1],"count_buy":{},"ostime":1751508776,"LavkaUid":27},{"username":"[21]James_Summers","items_sell":["Шапка Верки Сердючки","Складная магическая лавка","Отражающая нашивка","Респиратор","Увеличенный магазин (X3) для Mac-10","Компенсатор (UZI)","Цевьё (UZI)"],"items_buy":["Частица грохота","Шкатулка кладоискателя","Прочная ткань","Платиновая рулетка","Металл","Осколок Бронежилета Генерала","Кусок редкой ткани","Бандитский респект","Смазка для разгона видеокарты","Рыбная монета","Уголь"],"price_sell":[50000,10300000,250000,200000,1200000,120000,120000],"price_buy":[530000,12300000,105000,5966,2815,38000,4383,40,10176,920,13501],"count_sell":[1,1,1,1,1,1,1],"count_buy":[20,3,80,500,2000,500,1000,80000,500,5000,500],"ostime":1751508740,"LavkaUid":67},{"username":"[07]Daniel_Mayakov","items_sell":["Скин: Дерил Диксон (ID: 907)(+1)","Генеральский бронежилет(+2)","Переносной верстак миража","Супер-кирка(+13)","Мешок с мясом","Мешок с мясом","Мешок с мясом","Мешок с мясом","Неоновая маска(+10)","Складная магическая лавка","Осколок МайнСклет","Тыквенный воздушный шар(+12)","Сертификат охранника Квадратная Курица","Сертификат охранника Квадратная Курица","Сертификат охранника Квадратная Курица","Сертификат охранника Квадратная Курица","Монета охотника","Бронзовая рулетка","Энергетический воздушный шар(+12)"],"items_buy":{},"price_sell":[300000,43500000,3500000,8500000,1000000,1000000,1000000,1000000,2000000,10700000,1500000,1200000,750000,750000,750000,750000,35,300,28000000],"price_buy":{},"count_sell":[1,1,1,1,1,1,1,1,1,1,1,1,1,1,1,1,2095,19,1],"count_buy":{},"ostime":1751508755,"LavkaUid":65},{"username":"[02]Tima_Hala","items_sell":["Охлаждающая жидкость для видеокарты","Охлаждающая жидкость для видеокарты","Охлаждающая жидкость для видеокарты","Охлаждающая жидкость для видеокарты","Охлаждающая жидкость для видеокарты","Охлаждающая жидкость для видеокарты","Охлаждающая жидкость для видеокарты","Охлаждающая жидкость для видеокарты","Охлаждающая жидкость для видеокарты","Охлаждающая жидкость для видеокарты","Охлаждающая жидкость для видеокарты","Охлаждающая жидкость для видеокарты","Охлаждающая жидкость для видеокарты","Охлаждающая жидкость для видеокарты","Охлаждающая жидкость для видеокарты","Охлаждающая жидкость для видеокарты","Охлаждающая жидкость для видеокарты","Охлаждающая жидкость для видеокарты","Охлаждающая жидкость для видеокарты","Охлаждающая жидкость для видеокарты","Охлаждающая жидкость для видеокарты","Охлаждающая жидкость для видеокарты","Охлаждающая жидкость для видеокарты","Охлаждающая жидкость для видеокарты","Охлаждающая жидкость для видеокарты","Охлаждающая жидкость для видеокарты","Охлаждающая жидкость для видеокарты","Охлаждающая жидкость для видеокарты","Охлаждающая жидкость для видеокарты","Охлаждающая жидкость для видеокарты"],"items_buy":["Голова Тыква","Руки сэта","Кусок редкой ткани","Мидас","Танго","Грув пончик воздушный шар","Воздушный шар читера","Смазка для разгона видеокарты","Бензопила на спину","Скин: Грибы 2 (ID: 951)","Скин: Грибы 1 (ID: 950)","Дельтаплан на спину","Скин: Марси (ID: 926)","Чип-тюнинг (STAGE 3)","КПП (sport+)","Сцепление (sport+)","Нагнетатель (sport+)","Сироп фермера","Камень","Супер-грабли","Скин: Рилай (ID: 927)","Велосипед на спину","Лён","Перчатка Вай","Скин: Николай Василенко (ID: 954)","Скин: Ринг мастер (ID: 921)","Супер-кирка","Логотип FBI [деталь тюнинга]","Монета охотника","Полицейская мигалка [деталь тюнинга]","Полицейская мигалка (активная)","Зловещая монета","Меч ВК","Сферы инвокера","Twin Turbo","Тормоза (sport+)","Подвеска (sport+)","Дифференциал (sport+)","Турбокомпрессор (sport+)","Подарок","Снегоуборочный бампер [деталь тюнинга]","Мешок с мясом","Семейный талон","Коленвал (sport+)","Чип-тюнинг (STAGE 2)","Распредвал (sport+)","Тормоза (sport)","Подвеска (sport)","Дифференциал (sport)","КПП (sport)","Сцепление (sport)","Нагнетатель (sport)","Турбокомпрессор (sport)","Распредвал (sport)","Коленвал (sport)"],"price_sell":[3100,3100,3100,3100,3100,3100,3100,3100,3100,3100,3100,3100,3100,3100,3100,3100,3100,3100,3100,3100,3100,3100,3100,3100,3100,3100,3100,3100,3100,3100],"price_buy":[2400000,1800000,3100,1000000,2000000,2700000,2700000,12000,300000,700000,700000,850000,700000,170000,130000,130000,130000,3000,500,2000000,500000,750000,70,1600000,600000,700000,3900000,100000,23,140000,160000,2250,1800000,2300000,95000,130000,130000,130000,130000,230,680000,800000,225,130000,24000,130000,14000,14000,14000,14000,14000,14000,14000,14000,14000],"count_sell":[100,100,100,100,100,100,100,100,100,100,100,100,100,100,60,87,100,100,100,100,100,100,100,100,100,100,90,100,100,90],"count_buy":[1,1,300,1,1,1,1,1700,1,1,1,1,1,1,1,1,1,100,2000,1,1,1,20000,1,1,1,1,1,7000,1,1,100,1,1,1,1,1,1,1,8000,1,1,5000,1,1,1,1,1,1,1,1,1,1,1,1],"ostime":1751508776,"LavkaUid":64},{"username":"[22]Heinz_Fufelschmerz","items_sell":["Скин: VC - Jezz Torrent (ID: 557)","Скин: VC - Jezz Torrent (ID: 557)","Скин: VC - Alex Shrub (ID: 545)","Скин: VC - Alex Shrub (ID: 545)","Скин: VC - Beach Visitor (ID: 553)","Скин: VC - Beach Visitor (ID: 553)","Скин: VC - Beach Visitor (ID: 553)","Скин: VC - Beach Visitor (ID: 553)","Скин: VC - Beach Visitor (ID: 553)","Скин: VC - Worker (ID: 562)","Скин: VC - Worker (ID: 562)","Скин: VC - Worker (ID: 562)","Скин: VC - Worker (ID: 562)","Скин: VC - Diaz (ID: 552)","Скин: VC - Diaz (ID: 552)","Скин: VC - Таксист 1 (ID: 542)","Скин: VC - Таксист 1 (ID: 542)","Скин: VC - Таксист 1 (ID: 542)","Скин: VC - Dick (ID: 556)","Скин: VC - Dick (ID: 556)","Скин: Normal Ped (ID: 55)","Белая сумка «Stone Island»","Белая сумка «Stone Island»","Белая сумка «Stone Island»","Серая сумка «Stone Island»","Серая сумка «Stone Island»","Серая сумка «Stone Island»","Серая сумка «Stone Island»","Серая сумка «Stone Island»","Кислотная сумка «Stone Island»","Кислотная сумка «Stone Island»","Кислотная сумка «Stone Island»","Кислотная сумка «Stone Island»","Кислотная сумка «Stone Island»","Кислотная сумка «Stone Island»","Кислотная сумка «Stone Island»","Кислотная сумка «Stone Island»","Кислотная сумка «Stone Island»","Кислотная сумка «Stone Island»","Сумка «Gucci»","Сумка «Gucci»","Сумка «Gucci»","Сумка «Kenzo»","Сумка «Kenzo»","Сумка «Kenzo»","Сумка «Kenzo»","Сумка «Kenzo»","Сумка «Kenzo»","Сумка «Kenzo»","Сумка «Tommy Hilfiger»","Сумка «Tommy Hilfiger»","Сумка «Tommy Hilfiger»","Сертификат охранника Квадратная Курица","Сертификат охранника Квадратная Курица","Сертификат охранника Квадратная Курица","Сертификат охранника Квадратная Курица","Сертификат охранника Квадратная Курица","Сертификат охранника Квадратная Курица","Сертификат охранника Квадратная Курица","Улучшенный сироп характеристик актера","Улучшенный сироп характеристик актера","Улучшенный сироп характеристик актера","Улучшенный сироп характеристик актера","Улучшенный сироп характеристик актера","Улучшенный сироп характеристик актера","Улучшенный сироп характеристик актера","Улучшенный сироп характеристик актера","Улучшенный сироп характеристик актера","Улучшенный сироп характеристик актера","Улучшенный сироп характеристик актера","Улучшенный сироп характеристик актера","Улучшенный сироп характеристик актера","Улучшенный сироп характеристик актера","Улучшенный сироп характеристик актера","Улучшенный сироп характеристик актера","Улучшенный сироп характеристик актера","Улучшенный сироп характеристик актера","Рецепт: Кольцо всевластия","Рецепт: Коса марси","Семейная монета","Корова","Корова","Корова","Олень","Статуя льва","Статуя льва","Статуя льва","Большой фонтан","Большой фонтан","Большой фонтан","Объект: Мороженное","Объект: Мороженное","Объект: Мороженное","Объект: Надувной круг Пицца","Объект: Надувной круг Пицца","Скин: Priest/Preacher (ID: 68)","Рецепт: Коса марси","Увеличенный магазин (X3) для Mac-10","Мешок с мясом(+7)","Переносной верстак миража","Эксклюзивная шляпа 4","Красный плащ","Скин: Дарт Вейдер (ID: 694)","Скин: Дарт Вейдер (ID: 694)","Скин: Дарт Вейдер (ID: 694)","Скин: Дарт Вейдер (ID: 694)","Скин: Антоха (ID: 877)","Скин: VC - Таксист 2 (ID: 543)","Скин: VC - Lance Vance (ID: 554)","Скин: VC - Lance Vance (ID: 554)","Скин: VC - Ken Rosenberg (ID: 558)","Скин: VC - Ken Rosenberg (ID: 558)","Скин: VC - Biker (ID: 549)","Скин: VC - Biker (ID: 549)","Скин: VC - Stephen Scott (ID: 551)","Скин: VC - Stephen Scott (ID: 551)","Скин: VC - Beach Visitor (ID: 568)","Скин: VC - Beach Visitor (ID: 568)","Скин: VC - Beach Visitor (ID: 568)","Скин: VC - Beach Visitor (ID: 568)","Скин: VC - Beach Visitor (ID: 568)","Скин: VC - Beach Visitor (ID: 568)","Скин: VC - Beach Visitor (ID: 568)","Скин: VC - Pierre La Ponce","Скин: VC - Jezz Torrent (ID: 557)","Скин: VC - Jezz Torrent (ID: 557)","Мешок с мясом(+7)","Переносной верстак миража","Эксклюзивная шляпа 4","Красный плащ","Скин: Дарт Вейдер (ID: 694)","Скин: Дарт Вейдер (ID: 694)","Скин: Дарт Вейдер (ID: 694)","Скин: Дарт Вейдер (ID: 694)","Скин: Антоха (ID: 877)","Скин: VC - Таксист 2 (ID: 543)","Скин: VC - Lance Vance (ID: 554)","Скин: VC - Lance Vance (ID: 554)","Скин: VC - Ken Rosenberg (ID: 558)","Скин: VC - Ken Rosenberg (ID: 558)","Скин: VC - Biker (ID: 549)","Скин: VC - Biker (ID: 549)","Скин: VC - Stephen Scott (ID: 551)","Скин: VC - Stephen Scott (ID: 551)","Скин: VC - Beach Visitor (ID: 568)","Скин: VC - Beach Visitor (ID: 568)","Скин: VC - Beach Visitor (ID: 568)","Скин: VC - Beach Visitor (ID: 568)","Скин: VC - Beach Visitor (ID: 568)","Скин: VC - Beach Visitor (ID: 568)","Скин: VC - Beach Visitor (ID: 568)","Скин: VC - Pierre La Ponce","Скин: VC - Jezz Torrent (ID: 557)","Скин: VC - Jezz Torrent (ID: 557)","Скин: VC - Jezz Torrent (ID: 557)","Скин: VC - Jezz Torrent (ID: 557)","Скин: VC - Alex Shrub (ID: 545)","Скин: VC - Alex Shrub (ID: 545)","Скин: VC - Beach Visitor (ID: 553)","Скин: VC - Beach Visitor (ID: 553)","Скин: VC - Beach Visitor (ID: 553)","Скин: VC - Beach Visitor (ID: 553)","Скин: VC - Beach Visitor (ID: 553)","Скин: VC - Worker (ID: 562)","Скин: VC - Worker (ID: 562)","Скин: VC - Worker (ID: 562)","Скин: VC - Worker (ID: 562)","Скин: VC - Diaz (ID: 552)","Скин: VC - Diaz (ID: 552)","Скин: VC - Таксист 1 (ID: 542)","Скин: VC - Таксист 1 (ID: 542)","Скин: VC - Таксист 1 (ID: 542)","Скин: VC - Dick (ID: 556)","Скин: VC - Dick (ID: 556)","Скин: Normal Ped (ID: 55)","Скин: Priest/Preacher (ID: 68)","Белая сумка «Stone Island»","Белая сумка «Stone Island»","Белая сумка «Stone Island»","Серая сумка «Stone Island»","Серая сумка «Stone Island»","Серая сумка «Stone Island»","Серая сумка «Stone Island»","Серая сумка «Stone Island»","Кислотная сумка «Stone Island»","Кислотная сумка «Stone Island»","Кислотная сумка «Stone Island»","Кислотная сумка «Stone Island»","Кислотная сумка «Stone Island»","Кислотная сумка «Stone Island»","Кислотная сумка «Stone Island»","Кислотная сумка «Stone Island»","Кислотная сумка «Stone Island»","Кислотная сумка «Stone Island»","Сумка «Gucci»","Сумка «Gucci»","Сумка «Gucci»","Сумка «Kenzo»","Сумка «Kenzo»","Сумка «Kenzo»","Сумка «Kenzo»","Сумка «Kenzo»","Сумка «Kenzo»","Сумка «Kenzo»","Сумка «Tommy Hilfiger»","Сумка «Tommy Hilfiger»","Сумка «Tommy Hilfiger»","Сертификат охранника Квадратная Курица","Сертификат охранника Квадратная Курица","Сертификат охранника Квадратная Курица","Сертификат охранника Квадратная Курица","Сертификат охранника Квадратная Курица","Сертификат охранника Квадратная Курица","Сертификат охранника Квадратная Курица","Улучшенный сироп характеристик актера","Улучшенный сироп характеристик актера","Улучшенный сироп характеристик актера","Улучшенный сироп характеристик актера","Улучшенный сироп характеристик актера","Улучшенный сироп характеристик актера","Улучшенный сироп характеристик актера","Улучшенный сироп характеристик актера","Улучшенный сироп характеристик актера","Улучшенный сироп характеристик актера","Улучшенный сироп характеристик актера","Улучшенный сироп характеристик актера","Улучшенный сироп характеристик актера","Улучшенный сироп характеристик актера","Улучшенный сироп характеристик актера","Улучшенный сироп характеристик актера","Улучшенный сироп характеристик актера","Улучшенный сироп характеристик актера","Увеличенный магазин (X3) для Mac-10","Рецепт: Кольцо всевластия","Рецепт: Коса марси","Рецепт: Коса марси","Семейная монета","Корова","Корова","Корова","Олень","Статуя льва","Статуя льва","Статуя льва","Большой фонтан","Большой фонтан","Большой фонтан","Объект: Мороженное","Объект: Мороженное","Объект: Мороженное","Объект: Надувной круг Пицца","Объект: Надувной круг Пицца","Бронзовая рулетка"],"items_buy":{},"price_sell":[700000,700000,700000,700000,700000,700000,700000,700000,700000,700000,700000,700000,700000,700000,700000,700000,700000,700000,700000,700000,200000,190000,190000,190000,190000,190000,190000,190000,190000,190000,190000,190000,190000,190000,190000,190000,190000,190000,190000,190000,190000,190000,190000,190000,190000,190000,190000,190000,190000,190000,190000,190000,700000,700000,700000,700000,700000,700000,700000,4500000,4500000,4500000,4500000,4500000,4500000,4500000,4500000,4500000,4500000,4500000,4500000,4500000,4500000,4500000,4500000,4500000,4500000,50000,50000,50,200000,200000,200000,150000,170000,170000,170000,200000,200000,200000,150000,150000,150000,150000,150000,150000,50000,1400000,1100000,4500000,900000,200000,3000000,3000000,3000000,3000000,1100000,700000,700000,700000,700000,700000,700000,700000,700000,700000,700000,700000,700000,700000,700000,700000,700000,700000,700000,700000,1100000,4500000,900000,200000,3000000,3000000,3000000,3000000,1100000,700000,700000,700000,700000,700000,700000,700000,700000,700000,700000,700000,700000,700000,700000,700000,700000,700000,700000,700000,700000,700000,700000,700000,700000,700000,700000,700000,700000,700000,700000,700000,700000,700000,700000,700000,700000,700000,700000,700000,200000,150000,190000,190000,190000,190000,190000,190000,190000,190000,190000,190000,190000,190000,190000,190000,190000,190000,190000,190000,190000,190000,190000,190000,190000,190000,190000,190000,190000,190000,190000,190000,190000,700000,700000,700000,700000,700000,700000,700000,4500000,4500000,4500000,4500000,4500000,4500000,4500000,4500000,4500000,4500000,4500000,4500000,4500000,4500000,4500000,4500000,4500000,4500000,1400000,50000,50000,50000,50,200000,200000,200000,150000,170000,170000,170000,200000,200000,200000,150000,150000,150000,150000,150000,270],"price_buy":{},"count_sell":[1,1,1,1,1,1,1,1,1,1,1,1,1,1,1,1,1,1,1,1,1,1,1,1,1,1,1,1,1,1,1,1,1,1,1,1,1,1,1,1,1,1,1,1,1,1,1,1,1,1,1,1,1,1,1,1,1,1,1,1,1,1,1,1,1,1,1,1,1,1,1,1,1,1,1,1,1,2,1,534,1,1,1,1,1,1,1,1,1,1,1,1,1,1,1,1,1,1,1,1,1,1,1,1,1,1,1,1,1,1,1,1,1,1,1,1,1,1,1,1,1,1,1,1,1,1,1,1,1,1,1,1,1,1,1,1,1,1,1,1,1,1,1,1,1,1,1,1,1,1,1,1,1,1,1,1,1,1,1,1,1,1,1,1,1,1,1,1,1,1,1,1,1,1,1,1,1,1,1,1,1,1,1,1,1,1,1,1,1,1,1,1,1,1,1,1,1,1,1,1,1,1,1,1,1,1,1,1,1,1,1,1,1,1,1,1,1,1,1,1,1,1,1,1,1,1,1,1,1,1,1,1,1,2,10,1,534,1,1,1,1,1,1,1,1,1,1,1,1,1,1,1,2],"count_buy":{},"ostime":1751508740,"LavkaUid":26},{"username":"[06]Billy_Ramirez","items_sell":["Арбалет Траксы(+13)","Арбалет Траксы(+13)","Осколок Щит Капитана Америки","Бронежилет «Атака Титанов»(+9)","Заточка для оружия","Заточка для оружия","Сертификат охранника 'Bikers Warlock'","Сертификат охранника 'Bikers Warlock'","Заточенный магазин(+5)","Заточенный компенсатор(+5)","Заточенное цевье(+5)","Заточенный прицел(+5)","Меч ВК(+1)","Инструкция для разбора скинов","Инструкция для разбора скинов","Инструкция для разбора аксессуара","Инструкция для разбора аксессуара","Маска череп(+13)","Генеральский бронежилет(+8)","Энергетический воздушный шар(+13)","Нимб кольца всевластия(+13)","Меч ВК(+8)","Осколок предмета Заточка +13","Энергетический чемодан","Цепь «Махинатор»(+13)","Оружие Бамбли Би(+13)","Меч ВК(+12)","Меч ВК(+12)","Меч ВК(+12)","Меч ВК(+12)","Премиум рулетка","Рулетка основания","Прочная ткань","Опыт депозита","Опыт депозита","Опыт депозита","Twin Turbo (2 уровня)","Twin Turbo (2 уровня)","Twin Turbo (2 уровня)","Twin Turbo (2 уровня)","Twin Turbo (2 уровня)","Сертификат охранника 'Night Wolves'","Сертификат охранника 'Night Wolves'","Сертификат охранника 'Night Wolves'","Сертификат охранника 'Night Wolves'","Сертификат охранника 'Night Wolves'","Сертификат охранника 'Night Wolves'","Разрешение на улучшение наземной нефтевышки","Шахтерский сплав","Арбалет Траксы(+13)"],"items_buy":{},"price_sell":[65000000,65000000,600000,9000000,195000,195000,300000,300000,80000000,80000000,80000000,80000000,2400000,185000,185000,50000,50000,20000000,45000000,37000000,21000000,2600000,900000,25000000,12000000,17000000,2800000,2800000,2800000,2800000,200000,50000,117000,5500,5500,5500,4200000,4200000,4200000,4200000,4200000,900000,900000,900000,900000,900000,900000,2600000,80000,70000000],"price_buy":{},"count_sell":[1,1,1,1,50,5,1,1,1,1,1,1,1,46,28,50,28,1,1,1,1,1,1,1,1,1,1,1,1,1,1,1,19,82,100,47,1,1,1,1,1,1,1,1,1,1,1,1,2,1],"count_buy":{},"ostime":1751508767,"LavkaUid":68},{"username":"[07]Fidelio_Paradoxical","items_sell":{},"items_buy":{},"price_sell":{},"price_buy":{},"count_sell":{},"count_buy":{},"ostime":1751508758,"LavkaUid":76},{"username":"[07]Pervoye_Sentyabrya","items_sell":["Супер-лопата(+12)","Маска череп","Маска череп","Кровавые крылья(+13)","Прототип","Шлем железного человека(+12)","Скин: Спецназовец (ID: 880)","Рецепт: Кольцо всевластия"],"items_buy":{},"price_sell":[1400000,6500000,6500000,14000000,6500000,4000000,5000000,60000],"price_buy":{},"count_sell":[1,1,1,1,1,1,1,4],"count_buy":{},"ostime":1751508749,"LavkaUid":43},{"username":"[07]Freid_Rei","items_sell":["Неон - Белый [деталь тюнинга]","Неон - Белый [деталь тюнинга]","Попугай [деталь тюнинга]","Попугай [деталь тюнинга]","Попугай [деталь тюнинга]","Попугай [деталь тюнинга]","Катана [деталь тюнинга]","Катана [деталь тюнинга]","Катана [деталь тюнинга]","Катана [деталь тюнинга]","Кенгурятник Ретро","Кенгурятник Промышленный","Багажник Акустический","Задний отбойник Спойлер с закисью","Задний отбойник Спойлер с закисью","Полицейская мигалка [деталь тюнинга]","Полицейская мигалка [деталь тюнинга]","Неон - Красный [деталь тюнинга]","Неон - Красный [деталь тюнинга]","Задний отбойник Генератор","Багажник Thug Life","Логотип FBI [деталь тюнинга]","Туристический рюкзак (белый) [деталь тюнинга]","Туристический рюкзак (белый) [деталь тюнинга]","Контейнер на крышу [деталь тюнинга]","Контейнер на крышу [деталь тюнинга]","Накладка на бензобак #2 [деталь тюнинга]","Накладка на бензобак #2 [деталь тюнинга]","Накладка на бензобак #2 [деталь тюнинга]"],"items_buy":{},"price_sell":[200000,200000,200000,200000,200000,200000,300000,300000,300000,300000,1500000,2800000,1900000,250000,250000,250000,250000,200000,200000,100000,1900000,250000,20000,20000,100000,100000,20000,20000,20000],"price_buy":{},"count_sell":[1,1,1,1,1,1,1,1,1,1,1,1,1,1,1,1,1,1,1,1,1,1,1,1,1,1,1,1,1],"count_buy":{},"ostime":1751508762,"LavkaUid":75},{"username":"[10]Jonatan_Dauth","items_sell":{},"items_buy":{},"price_sell":{},"price_buy":{},"count_sell":{},"count_buy":{},"ostime":1751508708,"LavkaUid":79},{"username":"[09]Matteo_France","items_sell":["Нимб Ветвь мира","Кислотная сумка «Stone Island»"],"items_buy":["Огненная кирка"],"price_sell":[500000,120000],"price_buy":[14955000],"count_sell":[1,1],"count_buy":[1],"ostime":1751508740,"LavkaUid":3},{"username":"[31]Rick_Wallace","items_sell":["Серебряная рулетка","Уголь","Камень","Камень","Эликсир крафтера","Коленвал (sport)","Распредвал (sport)","Нагнетатель (sport)","Сцепление (sport)","КПП (sport)","Дифференциал (sport)","Тормоза (sport)","Опыт депозита","Эликсир крипатуры","Эликсир Рыбный мастер","Эликсир PUBG Мастер","Эликсир Хороший Человек","Эликсир дальнобойщика","Эликсир инкассатора","Эликсир автобусника","Бронзовая рулетка","Зловещая монета"],"items_buy":{},"price_sell":[942,14500,575,575,4000,40000,40000,40000,40000,40000,40000,40000,5400,1000,3000,6000,300,10000,5000,5000,250,4500],"price_buy":{},"count_sell":[1,22,600,161,2,1,1,1,1,1,1,1,54,13,16,20,2,19,33,3,3,5],"count_buy":{},"ostime":1751508722,"LavkaUid":80},{"username":"[14]Arcane_Explosion","items_sell":["Скин: Гринч (ID: 459)"],"items_buy":{},"price_sell":[22000000],"price_buy":{},"count_sell":[1],"count_buy":{},"ostime":1751508724,"LavkaUid":78},{"username":"[16]Robchik_Platina","items_sell":{},"items_buy":["Платиновая рулетка","Золотая рулетка","Серебряная рулетка","Бронзовая рулетка","Рулеточный компас","Рулеточный бустер","Семейный талон","Гражданский талон","Подарок","Админ зарплата","Монета охотника","Рыбная монета","Монета Миража","Талон на 12 x4 PayDay (передаваемый)","Талон на смену никнейма","Новые документы","Талон: +1 EXP (Передаваемые)","Скидочный талон","AZ-Монеты (Передаваемые)","Опыт депозита","Зловещая монета","Точильный камень","Точильный амулет","Сырое мясо оленины","Жареное мясо оленины","Тушка оленя","Мешок с мясом","Бандитский респект","Заточка для бронежилета","Осколок NFT контейнера","Осколок предмета Заточка +13","Заточка +13","Инструкция для разбора аксессуара","Желтая инструкция для разбора аксессуара","Инструкция для разбора скинов","Редкие материалы","Ящик рыболова","Платиновый ящик с секретной машиной","Ящик с секретной машиной","Осколок ящика секретной машины","Платиновый осколок ящика секретной машины","Осколок Бронежилета Генерала","Осколок секретного аксессуара","Секретный аксессуар","Осколок Истока","Исток","Флешка майнера","Смазка для разгона видеокарты","Охлаждающая жидкость для видеокарты","Супер охлаждающая жидкость для видеокарты","Супер-грабли","Лён","Хлопок","Счастливая травка","Уголь","Кусок редкой ткани","Бензопила на спину","Морской топор","Древесина высшего качества","Дрова","Прочная ткань","Шахтерский сплав","Темная материя","Алмазный камень","Супер-кирка","Алюминий","Металл","Камень","Золото","Серебро","Ларец с премией","Ларец дальнобойщика","Super Car Box","Concept Car Luxury","Ларец Tidex","Ларец Водителя Автобуса","Ларец рыболова","Рандомный Ларец","Одежда из секонд-хенда","Rare Box Yellow","Rare Box Red","Rare Box Blue","Ларец пилота","Ларец развозчика продуктов","Ларец кладоискателя","Ностальгический ящик","Супер авто-ящик","Ларец Vice City","Супер мото-ящик","Ларец кастомных аксессуаров","Ящик Marvel","Ящик Minecraft","Ящик Джентельменов","Ларец Mortal Combat","Ларец организации","Ларец хэллоуина 2022","Ларец семейных охранников","Ларец крафтера","Ларец Олигарха","Ларец Fortnite","Пасхальный ларец 2024","Ларец Arizona","Обнуление пробега для авто","Неоновая подсветка (настраиваемая)","Багажник","Гидравлика (управляемая)","Улучшение для автомобиля","Увеличенный бак (160 литров)","Twin Turbo","Twin Turbo (2 уровня)","Чип-тюнинг (STAGE 3)","Коленвал (sport+)","Распредвал (sport+)","Турбокомпрессор (sport+)","Нагнетатель (sport+)","Сцепление (sport+)","КПП (sport+)","Дифференциал (sport+)","Подвеска (sport+)","Тормоза (sport+)"],"price_sell":{},"price_buy":[6500,4500,1000,140,700000,250000,240,90,200,1150,10,1000,7000,1100000,15000,30000,300,5000,550,3000,2500,400,3300,500,700,1400,750000,45,10000,210000,800000,4000000,15000,150000,30000,3500,600000,2200000,450000,15000,200000,30000,15000,100000,15000,2000000,1200000,10000,2500,3500,1500000,65,65,200,13000,3000,300000,800000,500,10,100000,70000,70000,9000,3500000,8500,2850,450,1000,250,1700,2500,3400,3600,1000,1500,2150,1000,1000,1000,1000,1000,3000,1500,1500,1700,2500,1500,1200,2500,700,700,700,700,650,3400,2150,2500,1500,1650,1600,3400,15000,50000,75000,100000,30000,3450000,135000,3750000,180000,160000,110000,110000,110000,110000,110000,110000,110000,110000],"count_sell":{},"count_buy":[250,250,500,500,1,1,1000,2000,1000,250,5000,500,250,1,1,5,300,10,100,50,250,250,250,50,50,20,1,10000,10,5,1,1,10,5,10,250,1,1,1,25,10,25,50,15,50,1,1,50,100,50,1,2000,2000,250,50,50,1,1,500,15000,10,10,10,25,1,50,250,500,1000,2000,200,200,200,200,200,200,200,200,200,200,200,200,200,200,200,200,200,200,200,200,200,200,200,200,200,200,200,200,200,200,200,200,5,1,1,1,1,1,1,1,1,1,1,1,1,1,1,1,1,1],"ostime":1751508731,"LavkaUid":17},{"username":"[16]Yomi_Yori","items_sell":["Переносной ларек Шрека 1(+12)","Скин: Михаил Круг (ID: 893)(+10)","Голова дьявола","Винил-15","Задний отбойник Попка","Канистра на правое бедро","Торговый ключ","Торговый ключ","Сцепление (sport)","Турбокомпрессор (sport)","Турбокомпрессор (sport)","Дифференциал (sport)","Нагнетатель (sport)","Нагнетатель (sport)","Нагнетатель (sport)","Тормоза (sport)","Тормоза (sport)","Тормоза (sport)","Распредвал (sport)","Распредвал (sport)","Скин: Катсу (ID: 862)(+8)","Коленвал (sport)","Коленвал (sport)","Объект: Барбекю","Зловещая монета","Новогодняя палатка","Амонгус(черный)","Парашют желтый","Объект: Скуби Снэк","Шлем Cyber Cat","Сертификат охранника 'Лис Ник'","Сертификат охранника 'Шито'","Рецепт: Кольцо всевластия","Алмазная кирка","Алмазная кирка","Платиновая рулетка","Голова Робосанты","Бронзовая рулетка","Бронзовая рулетка"],"items_buy":{},"price_sell":[3500000,1000000,47619,38095,95238,190476,95238,95238,47619,47619,47619,47619,47619,47619,47619,47619,47619,47619,47619,47619,1142856,47619,47619,285714,3999,476189,142857,476189,95237,285714,285714,380951,47618,190475,190475,6856,95237,237,237],"price_buy":{},"count_sell":[1,1,1,1,1,1,1,1,1,1,1,1,1,1,1,1,1,1,1,1,1,1,1,1,2,1,1,1,1,1,1,1,1,1,1,1,1,43,2],"count_buy":{},"ostime":1751508733,"LavkaUid":11},{"username":"[02]Magnus_Hardy","items_sell":["Эликсир инкассатора","Эликсир инкассатора","Эликсир инкассатора","Дрова","Камень","Древесина высшего качества","Рыбная монета","Подарок","Ларец дальнобойщика","Ларец Tidex","Одежда из секонд-хенда","Опыт депозита","Rare Box Yellow","Эликсир крипатуры","Эликсир крипатуры","Эликсир автобусника","Эликсир автобусника","Эликсир дальнобойщика","Эликсир Хороший Человек","Эликсир Хороший Человек","Эликсир PUBG Мастер","Эликсир Рыбный мастер","Эликсир Рыбный мастер","Эликсир крафтера","Смазка для разгона видеокарты","Зловещая монета","Шкура оленя","Шкура оленя","Ларец организации","Диски (wheel_vip8)","Диски (wheel_vip3)","Металл","Ностальгический ящик","Эффект x4 пополнение счёта (24 часа)","Бронзовая рулетка"],"items_buy":{},"price_sell":[3000,3000,3000,22,600,800,1500,300,4000,2000,2000,5000,2000,3000,3000,5000,5000,5000,4500,4500,5000,4500,4500,4500,12200,4500,200,200,1000,32000,32000,3205,2800,1602,240],"price_buy":{},"count_sell":[50,50,4,19409,244,63,52,6,1,1,2,12,5,46,23,43,23,1,50,9,29,5,50,28,20,5,80,14,1,1,1,65,1,12,14],"count_buy":{},"ostime":1751508736,"LavkaUid":28},{"username":"[04]Baadur_Jobava","items_sell":{},"items_buy":{},"price_sell":{},"price_buy":{},"count_sell":{},"count_buy":{},"ostime":1751508770,"LavkaUid":82}]