[{"username":"[30]Sanchez_McCloud","items_sell":["Шахтерский сплав","Шахтерский сплав","Шахтерский сплав","Шахтерский сплав","Шахтерский сплав","Шахтерский сплав","Шахтерский сплав","Шахтерский сплав","Шахтерский сплав","Шахтерский сплав","Прочная ткань","Прочная ткань","Прочная ткань","Прочная ткань","Прочная ткань","Прочная ткань","Прочная ткань","Прочная ткань","Прочная ткань","Прочная ткань","Алмазный камень","Осколок Истока","Осколок Бронежилета Генерала","Сироп характеристик актера","Админ зарплата","Нашивка на аксессуар(защита)","Нашивка на аксессуар(защита)","Нашивка на аксессуар(защита)","Нашивка на аксессуар(защита)","Нашивка на аксессуар(защита)","Нашивка на аксессуар(защита)","Нашивка на аксессуар(защита)","Нашивка на аксессуар(урон)","Смазка для разгона видеокарты","Смазка для разгона видеокарты","Смазка для разгона видеокарты","Смазка для разгона видеокарты","Смазка для разгона видеокарты","Смазка для разгона видеокарты","Смазка для разгона видеокарты","Смазка для разгона видеокарты","Смазка для разгона видеокарты","Смазка для разгона видеокарты","Смазка для разгона видеокарты","Смазка для разгона видеокарты","Смазка для разгона видеокарты","Смазка для разгона видеокарты","Смазка для разгона видеокарты","Смазка для разгона видеокарты","Смазка для разгона видеокарты","Смазка для разгона видеокарты","Смазка для разгона видеокарты","Смазка для разгона видеокарты","Смазка для разгона видеокарты","Смазка для разгона видеокарты","Смазка для разгона видеокарты","Смазка для разгона видеокарты","Смазка для разгона видеокарты","Смазка для разгона видеокарты","Смазка для разгона видеокарты","Смазка для разгона видеокарты","Осколок Тайника Собирателя","Деталь двигателя","Деталь двигателя","Деталь двигателя","Деталь автомобиля","Деталь автомобиля","Деталь автомобиля","Деталь автомобиля","Лопата","Лопата","Лопата","Лопата","Лопата","Лопата","Лопата","Лопата","Лопата","Лопата","Лопата","Лопата","Лопата","Лопата","Лопата","Лопата","Лопата","Желтая инструкция для разбора аксессуара","Неоновая подсветка (настраиваемая)","Гибридная установка","Полицейская мигалка [деталь тюнинга]"],"items_buy":["Редкие материалы","Прочная ткань","Шахтерский сплав","Алмазный камень","Темная материя","Уголь","Кусок редкой ткани","Лён","Хлопок","Древесина высшего качества","Дрова","Алюминий","Камень","Металл","Серебро","Бронза","Золото","Осколок Бронежилета Генерала","Талон на 12 x4 PayDay (передаваемый)","Ларец с премией","Ларец рыболова","Ларец кладоискателя","Ларец развозчика продуктов","Точильный амулет","Заточка для бронежилета","Заточка для оружия","Серебряная рулетка","Золотая рулетка","Платиновая рулетка","Сироп характеристик актера"],"price_sell":[85900,85900,85900,85900,85900,85900,85900,85900,85900,85900,122000,122000,122000,122000,122000,122000,122000,122000,122000,122000,12200,25000,47500,1350000,1600,2600000,2600000,2600000,2600000,2600000,2600000,2600000,2600000,12449,12449,12449,12449,12449,12449,12449,12449,12449,12449,12449,12449,12449,12449,12449,12449,12449,12449,12449,12449,12449,12449,12449,12449,12449,12449,12449,12449,500000,17000,17000,17000,17000,17000,17000,17000,800000,800000,800000,800000,800000,800000,800000,800000,800000,800000,800000,800000,800000,800000,800000,800000,800000,225000,120000,50000,180000],"price_buy":[3750,108000,80000,11300,78000,13500,5250,73,55,685,11,9300,550,3100,240,300,950,39000,1200000,1300,1300,1300,1300,3900,13000,140000,900,4000,5500,1000000],"count_sell":[191,178,18,140,200,198,200,158,200,190,144,180,200,200,115,47,200,146,200,140,68,6,1,4,197,1,1,1,1,1,1,1,1,100,100,100,100,100,56,100,100,23,100,100,50,100,100,100,100,100,100,100,100,100,100,100,100,100,100,100,100,1,8,20,20,20,4,20,20,1,1,1,1,1,1,1,1,1,1,1,1,1,1,1,1,1,2,1,1,1],"count_buy":[2000,150,150,500,200,2000,2000,50000,50000,15000,500000,1000,20000,15000,3000,3000,2000,200,2,1000,1000,1000,1000,500,70,40,2000,1000,1000,1],"ostime":1750386182,"LavkaUid":50},{"username":"[18]Xtemple_Tasherka","items_sell":["Перчатка Вай","Сферы инвокера(+10)","Золотой Ларец Миража","Шахтерский сплав","Ангельское кольцо на голову(+12)","Нимб Ветвь мира","Новогодний шарф 2025","Кейс анимированый 3(+1)","Нимб Доры","Руки сэта","Руки сэта","Сертификат охранника 'Зайка Джуди'","Сертификат охранника 'Зайка Джуди'","Воздушный шар Дора","Сцепление (sport)","Монета охотника","Древесина высшего качества","Нимб Пошлой Молли","Скин: Дива (ID: 947)(+7)","Скин: Doggo (ID: 828)(+7)","Сертификат охранника Квадратная Курица","Сертификат охранника Квадратная Курица","Монета основания","Опыт депозита","Бронзовая рулетка","Дельтаплан на спину(+13)"],"items_buy":{},"price_sell":[3000000,4500000,2500000,85000,1900000,700000,100000,100000,100000,2800000,2800000,170000,170000,200000,45000,40,750,100000,178571,200000,500000,500000,535,5803,250,3000000],"price_buy":{},"count_sell":[1,1,1,3,1,1,1,1,1,1,1,1,1,1,1,133,63,1,1,1,1,1,160,12,9,1],"count_buy":{},"ostime":1750386187,"LavkaUid":52},{"username":"[02]Sakata_Wolker","items_sell":["Воздушный шар #2(+10)","Воздушный шар #5(+8)","Воздушный шар #5(+12)","Ангельское кольцо на голову(+9)","Ангельское кольцо на голову(+9)","Мешок с мясом(+2)","Анимированный Пончиковый нимб(+7)","Арбалет Траксы","Арбалет Траксы","Цепь «Махинатор»(+12)","Магический воздушный шар #5(+12)","Скин: Мумия (ID: 613)","Скин: Colonel Fuhrberger (ID: 62)","Мешок с мясом","Мешок с мясом","Мешок с мясом","Мешок с мясом","Мешок с мясом","Мешок с мясом","Обрез (активный аксессуар)","Анимированные часы на спину (на спутника)","Супер-кирка","Супер-кирка","Супер-кирка","Элитная переносная лавка","Элитная переносная лавка","Элитная переносная лавка","Нашивка на аксессуар(защита)","Кровавые крылья(+13)","Скин: Varios Los Aztecas (ID: 116)","Мидас(+9)","Прототип(+12)","Видеокарта","Видеокарта","Видеокарта","Танго(+13)","Micro Tec-9","Micro Tec-9","Обрез","Скин: Мидас (ID: 806)","Скин: Мидас (ID: 806)","Скин: Мидас (ID: 806)"],"items_buy":{},"price_sell":[3500000,3500000,3700000,1800000,1800000,1000000,1900000,45000000,45000000,11000000,13000000,1000000,2000000,1000000,1000000,1000000,1000000,1000000,1000000,6300000,5500000,4400000,4400000,4400000,11300000,11300000,11300000,2350000,13000000,15000000,4400000,7500000,600000,600000,600000,6000000,50,50,700,1800000,1800000,1800000],"price_buy":{},"count_sell":[1,1,1,1,1,1,1,1,1,1,1,1,1,1,1,1,1,1,1,1,1,1,1,1,1,1,1,1,1,1,1,1,1,1,1,1,180,495,140,1,1,1],"count_buy":{},"ostime":1750386188,"LavkaUid":55},{"username":"[18]Bohdan_Sergo","items_sell":["Скин: Люси (ID: 633)(+10)","Камень неуязвимости","Скин: Шериф (ID: 898)(+10)","Скин: Гринч (ID: 459)(+11)","Кровавые крылья(+13)","Кровавые крылья(+13)","Цепь «Bitcoin»(+13)","Энергетический чемодан","Чемодан зомби","Супер-лопата(+12)","Коса Марси","Талон снятия предупреждений","Бронежилет Конь БоДжек»(+7)","Моноколесо SHMEL","Бронежилет Конь БоДжек»","Часы 'Gucci'(+13)","Цепь «Махинатор»(+13)"],"items_buy":{},"price_sell":[17000000,4400000,13500000,23500000,13000000,13000000,13000000,26500000,7000000,1100000,9500000,400000,7200000,14000000,6900000,13500000,13000000],"price_buy":{},"count_sell":[1,11,1,1,1,1,1,1,1,1,1,1,1,1,1,1,1],"count_buy":{},"ostime":1750386135,"LavkaUid":53},{"username":"[04]Ellai_Romanov","items_sell":["Тайник Собирателя","Грамота ветерана","Грамота ветерана","Элитная переносная лавка","Шахтерский сплав","Темная материя","Темная материя","Темная материя","Темная материя","Темная материя","Темная материя","Темная материя","Темная материя","Темная материя","Темная материя","Темная материя","Темная материя","Темная материя","Темная материя","Темная материя","Темная материя","Темная материя","Алмазный камень","Прочная ткань","Прочная ткань","Прочная ткань","Прочная ткань","Кусок редкой ткани","Именное поместье","Дополнительная комната","Дополнительная комната","Дополнительная комната","Переносной верстак миража","Инструкция для разбора аксессуара","Инструкция для разбора аксессуара","Смазка для разгона видеокарты","Смазка для разгона видеокарты","Смазка для разгона видеокарты","Смазка для разгона видеокарты","Смазка для разгона видеокарты","Смазка для разгона видеокарты","Смазка для разгона видеокарты","Смазка для разгона видеокарты","Смазка для разгона видеокарты","Смазка для разгона видеокарты","Смазка для разгона видеокарты","Смазка для разгона видеокарты","Смазка для разгона видеокарты","Смазка для разгона видеокарты","Смазка для разгона видеокарты","Смазка для разгона видеокарты","Смазка для разгона видеокарты","Смазка для разгона видеокарты","Смазка для разгона видеокарты","Смазка для разгона видеокарты","Смазка для разгона видеокарты","Смазка для разгона видеокарты","Смазка для разгона видеокарты","Смазка для разгона видеокарты","Смазка для разгона видеокарты","Документ для отмывания денег","Документ для отмывания денег","Документ для отмывания денег","Документ для отмывания денег","Документ для отмывания денег","Увеличенный магазин (X3) для Sawnoff","Флешка майнера","Мешок с мясом","Мешок с мясом","Ангельское кольцо на голову","Современная карта кладов","Наёмный фермер","Наёмный фермер","Наёмный фермер","Увеличенный магазин (X3) для Mac-10"],"items_buy":{},"price_sell":[8850000,10800000,10800000,11450000,86000,83900,83900,83900,83900,83900,83900,83900,83900,83900,83900,83900,83900,83900,83900,83900,83900,83900,12000,118690,118690,118690,118690,5900,25500000,1700000,1700000,1700000,3500000,58999,58999,12400,12400,12400,12400,12400,12400,12400,12400,12400,12400,12400,12400,12400,12400,12400,12400,12400,12400,12400,12400,12400,12400,12400,12400,12400,19350000,19350000,19350000,19350000,19350000,12000000,2400000,1049000,1049000,1899000,4499000,16700000,16700000,16700000,1500000],"price_buy":{},"count_sell":[1,1,1,1,102,50,50,50,50,50,50,50,50,50,49,50,50,49,50,50,50,50,120,200,200,2,200,570,1,1,1,1,1,28,18,100,100,74,100,100,75,100,100,100,100,100,100,100,100,100,100,100,100,100,100,100,100,100,100,100,1,1,1,1,1,1,1,1,1,1,1,1,1,1,1],"count_buy":{},"ostime":1750386140,"LavkaUid":59},{"username":"[02]Andrey_Stoyn","items_sell":["Опыт депозита","Опыт депозита","Длинный Desert Eagle"],"items_buy":{},"price_sell":[5700,5700,2000000],"price_buy":{},"count_sell":[100,16,1],"count_buy":{},"ostime":1750386157,"LavkaUid":41},{"username":"[30]Ruslyana_Dredd","items_sell":["Эксклюзивная шляпа 3(+13)","Современная карта кладов","Современная карта кладов","Современная карта кладов","Современная карта кладов","Современная карта кладов","Современная карта кладов","Восстановленная карта кладов","Восстановленная карта кладов","Демонический металлоискатель(+12)","Дудец(+12)","Супер-лопата(+12)","Огненная кирка(+13)","Прочная ткань","Маска-невидимка(+13)","Коса Марси(+12)","Цепь «Bitcoin»(+13)","Бронежилет «Унесенные призраками»","Скин: Drug Dealer (ID: 30)","Уголь","Объект: Стелла блогера","Приклад (Sniper Rifle)","Рецепт: Кольцо всевластия","Рецепт: Коса марси"],"items_buy":{},"price_sell":[5999900,15399900,15399900,15399900,15399900,15399900,15399900,799900,799900,31499900,26999900,1199900,27999900,120990,9499900,9499900,12499900,6799900,11999900,14699,149900,99900,49900,49900],"price_buy":{},"count_sell":[1,1,1,1,1,1,1,1,1,1,1,1,1,155,1,1,1,1,1,29,1,1,2,2],"count_buy":{},"ostime":1750386166,"LavkaUid":57},{"username":"[22]Sens_Fix","items_sell":["Голова осла(+5)","Нашивка на аксессуар(защита)","Монета охотника","Семейная монета","Увеличитель пропускной способности","Увеличитель пропускной способности","Увеличитель пропускной способности","Нашивка на аксессуар(защита)","Нашивка на аксессуар(защита)","Нашивка на аксессуар(защита)","Нашивка на аксессуар(урон)"],"items_buy":{},"price_sell":[1500000,2400000,50,35,44000,44000,44000,2800000,2800000,2800000,2800000],"price_buy":{},"count_sell":[1,1,8640,3180,33,100,100,1,1,1,1],"count_buy":{},"ostime":1750386132,"LavkaUid":58},{"username":"[18]Son_Collins","items_sell":["Скин: Пауэр (ID: 906)","Скин: Пауэр (ID: 906)","Осколок Контейнера каменного человека","Нашивка на скин (Бег Си Джея)","Нашивка на скин (Бег Си Джея)","Видеокарта","Скин: Алиса Лидделл (ID: 642)(+10)","Скин: Призрачный гонщик (ID: 965)","Скин: Алекс Мерсер (ID: 730)","Рука бесконечности(+12)","Энергетический махинатор","Магический воздушный шар #4(+12)","Рука бесконечности(+13)","Энергетический двигатель","Энергетический двигатель","Энергетический двигатель","Энергетический двигатель","НФТ Каменного Человека","Осколок Хоумлендера","Скин: Хоумлендер (ID: 841)","Скин: Пауэр (ID: 906)","Скин: Пауэр (ID: 906)","Осколок Контейнера каменного человека","Нашивка на скин (Бег Си Джея)","Нашивка на скин (Бег Си Джея)","Энергетический двигатель","Энергетический двигатель","Энергетический двигатель","Энергетический двигатель","Видеокарта","Энергетический махинатор","Магический воздушный шар #4(+12)","Скин: Алиса Лидделл (ID: 642)(+10)","Скин: Призрачный гонщик (ID: 965)","Скин: Алекс Мерсер (ID: 730)","Рука бесконечности(+12)","Рука бесконечности(+13)","НФТ Каменного Человека","Осколок Хоумлендера","Скин: Хоумлендер (ID: 841)","Скин: Пауэр (ID: 906)","Скин: Пауэр (ID: 906)","Осколок Контейнера каменного человека","Нашивка на скин (Бег Си Джея)","Нашивка на скин (Бег Си Джея)","Энергетический двигатель","Энергетический двигатель","Энергетический двигатель","Энергетический двигатель","Видеокарта","Энергетический махинатор","Магический воздушный шар #4(+12)","Скин: Алиса Лидделл (ID: 642)(+10)","Скин: Призрачный гонщик (ID: 965)","Скин: Алекс Мерсер (ID: 730)","Рука бесконечности(+12)","Рука бесконечности(+13)"],"items_buy":{},"price_sell":[24000000,24000000,4000000,17000000,17000000,600000,4000000,700000,1000000,7500000,105000000,12500000,9000000,15300000,15300000,15300000,15300000,19000000,15000000,90000000,24000000,24000000,4000000,17000000,17000000,15199000,15199000,15199000,15199000,600000,105000000,12500000,4000000,700000,1000000,7500000,9000000,19000000,15000000,90000000,24000000,24000000,4000000,17000000,17000000,15199000,15199000,15199000,15199000,600000,105000000,12500000,4000000,700000,1000000,7500000,9000000],"price_buy":{},"count_sell":[1,1,4,1,1,1,1,1,1,1,1,1,1,1,1,1,1,1,1,1,1,1,1,1,1,1,1,1,1,1,1,1,1,1,1,1,1,1,1,1,1,1,1,1,1,1,1,1,1,1,1,1,1,1,1,1,1],"count_buy":{},"ostime":1750386170,"LavkaUid":56},{"username":"[20]Shatrik_NaFishke","items_sell":["Шкатулка кладоискателя","Документ для отмывания денег","Документ для отмывания денег","Документ для отмывания денег","Документ для отмывания денег","Документ для отмывания денег","Энергетический чемодан","Грамота ветерана","Заточка +13","Осколок предмета Заточка +13","Заточка для оружия","Видеокарта","Видеокарта","Видеокарта","Видеокарта","Видеокарта","Видеокарта","Видеокарта","Видеокарта","Видеокарта","Видеокарта","Видеокарта","Видеокарта","Видеокарта","Видеокарта","Видеокарта","Видеокарта","Видеокарта","Видеокарта","Видеокарта","Видеокарта","Видеокарта"],"items_buy":["Именное поместье","Шкатулка кладоискателя","Документ для отмывания денег","Грамота ветерана","Сертификат бесконечного Дополнения VIP","Тайник Vice City","Заточка +13","Осколок предмета Заточка +13","Энергетический двигатель","Энергетический чемодан","Генеральский бронежилет","Заточка для оружия","Редкие материалы"],"price_sell":[12849000,18999999,18999999,18999999,18999999,18999999,16899999,10800000,4699999,950000,167999,1035000,1035000,1035000,1035000,1035000,1035000,1035000,1035000,1035000,1035000,1035000,1035000,1035000,1035000,1035000,1035000,1035000,1035000,1035000,1035000,1035000],"price_buy":[24000100,12500000,17800000,10300000,10105000,6600500,4400000,870000,14500000,16200000,42500000,163000,3500],"count_sell":[1,1,1,1,1,1,1,1,7,4,40,1,1,1,1,1,1,1,1,1,1,1,1,1,1,1,1,1,1,1,1,1],"count_buy":[1,1,1,1,1,1,5,10,1,1,1,200,500],"ostime":1750386171,"LavkaUid":54},{"username":"[16]Delomaro_Unstoppable","items_sell":["Скин: Пауэр (ID: 906)","МайнСкелет(+13)","Скин: Макима (ID: 904)(+11)","Элитная переносная лавка(+1)","Маска череп","Маска череп","Алмазная кирка(+13)","Молот «Duff»(+13)","Аегис(+10)","Дельтаплан на спину(+3)","Скин: Фенни Лирст (ID: 858)(+7)","Скин: Маршмеллоу (ID: 844)(+5)","Скин: Битлджус (ID: 879)(+12)","Скин: Битлджус (ID: 879)","Скин: Карась (ID: 804)(+10)","Скин: Карась (ID: 804)(+9)","Бронзовая рулетка","Монета основания","Осколок супер-лопаты","Скидочный талон","Скин: Doggo (ID: 828)(+1)","Скин: Дива (ID: 947)","Скин: Дива (ID: 947)","Скин: Дива (ID: 947)","Улучшение Большие карманы"],"items_buy":{},"price_sell":[34000000,33500000,23000000,11400000,8390000,8390000,7000000,6900000,1250000,1240000,1100000,1350000,1300000,1100000,950000,900000,230,10,260000,20000,290000,250000,250000,250000,150000],"price_buy":{},"count_sell":[1,1,1,1,1,1,1,1,1,1,1,1,1,1,1,1,1,39,1,2,1,1,1,1,1],"count_buy":{},"ostime":1750386143,"LavkaUid":61},{"username":"[03]John_Gollandec","items_sell":["Передний отбойник Подушки","Нимб Пошлой Молли","Сертификат охранника 'Зайка Джуди'","Гибридная установка","Объект: Пикачу","Воздушный шар Дора","Багажник","Скин: Бабка матрена (ID: 945)","Скин: Грибы 2 (ID: 951)","Бронежилет Горящий пес","Объект: Дверь с человеком","Крылатая статуя","Объект: Японский фонарь","Объект: Японский фонарь","Объект: Японский фонарь","Объект: Японский фонарь","Объект: Японский фонарь","Объект: Японский фонарь","Объект: Японский фонарь","Объект: Японский фонарь","Объект: Японский фонарь","Пачка с деньгами","Обнуление пробега для авто","Секретный аксессуар","Диски (Турбофан Пицца)","Талон: +1 EXP (Передаваемые)","Сумка","Ларец хэллоуина 2022","Ларец Fortnite","Пасхальный ларец 2024","Ларец семейных охранников","Ларец крафтера","Ларец Vice City","Ларец Arizona","Ларец петуха","Бронзовая рулетка","Крылья Марси","Шар авантюриста","Очки Триггерит","Объект: Покемон 3","Объект: Покемон 4","Точильный камень","Рюкзак Пошлой Молли 2","Шатл на крышу [деталь тюнинга]","Диски (Турбофан Тормоз)","Мигалка под радиатор [деталь тюнинга]","Рюкзак Дратути","Кермит","Рик огурчик на крышу [деталь тюнинга]","Покеболл с покемоном 1","Гора золота на крышу [деталь тюнинга]"],"items_buy":{},"price_sell":[130000,70000,160000,25000,50000,250000,100000,130000,2000000,290000,25000,130000,300000,300000,300000,300000,300000,300000,300000,300000,300000,400000,25000,120000,10000,490,300000,5500,2000,2500,3550,3600,1900,7500,3500,170,25000,150000,100000,50000,20000,400,20000,30000,5000,230000,80000,30000,30000,10000,10000],"price_buy":{},"count_sell":[1,1,1,1,1,1,1,1,1,1,1,1,1,1,1,1,1,1,1,1,1,1,2,1,1,121,1,1,9,1,1,7,2,4,1,9,1,1,1,1,1,1,1,1,1,1,1,1,1,1,1],"count_buy":{},"ostime":1750386178,"LavkaUid":9},{"username":"[28]Barry_Show","items_sell":["Энергетический двигатель","Энергетический двигатель","Энергетический двигатель","Энергетический двигатель","Энергетический двигатель","Кровавые крылья(+12)","Цепь «Махинатор»(+12)","Перчатка Вай(+12)","Энергетический воздушный шар(+13)"],"items_buy":["Талон на 12 x4 PayDay (передаваемый)"],"price_sell":[15000000,15000000,15000000,15000000,15000000,8999999,8999999,5599999,29999999],"price_buy":[1100000],"count_sell":[1,1,1,1,1,1,1,1,1],"count_buy":[15],"ostime":1750386182,"LavkaUid":64},{"username":"[29]Diddy_Glock","items_sell":["Современная карта кладов","Современная карта кладов","Современная карта кладов","Современная карта кладов","Современная карта кладов","Современная карта кладов","Бойцовский клуб","Танго(+13)","Часы 'Apple Watch'(+13)","Скин: Оксана Чемпионка (ID: 972)(+8)","Дезолятор(+13)","Золотой длинный Desert Eagle на бедро(+12)","МайнСкелет(+12)","Элитная переносная лавка","Элитная переносная лавка","Цепь «Махинатор»(+13)","Бронежилет «Орда»(+8)","Бронежилет Конь БоДжек»(+8)","Скин: Витя АК (ID: 736)","Маска череп","Рука бесконечности"],"items_buy":{},"price_sell":[16000000,16000000,16000000,16000000,16000000,16000000,9000000,18000000,10000000,7500000,22500000,8000000,12000000,11350000,11350000,13000000,8500000,8000000,5000000,8000000,8000000],"price_buy":{},"count_sell":[1,1,1,1,1,1,1,1,1,1,1,1,1,1,1,1,1,1,1,1,1],"count_buy":{},"ostime":1750386141,"LavkaUid":73},{"username":"[10]Oleg_Bamper","items_sell":["Объект: Мусорка для дома","Объект: Мусорка для дома","Объект: Мусорка для дома","Бронежилет «Унесенные призраками»(+10)","Респиратор(+13)","Аркана ИО (+13)","Огненная кирка(+13)","Неоновая маска(+13)","Молот «Duff»(+12)","Arizona Video Card","Arizona Video Card","Arizona Video Card","Старая карта кладов","Старая карта кладов","Скидочный талон","Респиратор","Шахтерский сплав","Инструкция для разбора аксессуара","Бронза","Бронза","Серебро","Заточенный компенсатор"],"items_buy":{},"price_sell":[50000,50000,50000,9500000,13000000,10500000,28000000,13000000,5500000,250000,250000,250000,150000,150000,15000,500000,85000,60000,500,500,310,7500000],"price_buy":{},"count_sell":[1,1,1,1,1,1,1,1,1,1,1,1,1,1,26,1,10,1,594,117,51,1],"count_buy":{},"ostime":1750386139,"LavkaUid":80},{"username":"[14]Bennie_Baker","items_sell":["Скин: Ребекка (ID: 634)"],"items_buy":{},"price_sell":[15000000],"price_buy":{},"count_sell":[1],"count_buy":{},"ostime":1750386171,"LavkaUid":62},{"username":"[02]Healing_Proof","items_sell":["Сертификат охранника 'Петух'"],"items_buy":{},"price_sell":[12000123],"price_buy":{},"count_sell":[1],"count_buy":{},"ostime":1750386172,"LavkaUid":65},{"username":"[14]Niveiika_Men","items_sell":["Моноколесо SHMEL"],"items_buy":{},"price_sell":[20000000],"price_buy":{},"count_sell":[1],"count_buy":{},"ostime":1750386173,"LavkaUid":67},{"username":"[10]Ayaxo_ChyVanal","items_sell":["Платиновая рулетка"],"items_buy":{},"price_sell":[10000000],"price_buy":{},"count_sell":[1],"count_buy":{},"ostime":1750386161,"LavkaUid":82},{"username":"[04]Leon_Sakai","items_sell":{},"items_buy":{},"price_sell":{},"price_buy":{},"count_sell":{},"count_buy":{},"ostime":1750386002,"LavkaUid":63},{"username":"[21]Ethiopia_Market","items_sell":["Маска-невидимка","Документ для отмывания денег","Ангельское кольцо на голову(+12)","Сфера над головой(+12)","Бронежилет «Щ.И.Т.»(+9)","Скин: Инвокер (ID: 922)(+8)","Часы 'Rolex Submariner'(+8)","Танго(+12)","Паучьи лапы(+13)","Кровавые крылья(+13)","Скин: Джокер (ID: 929)(+12)","Голова Тыква(+13)","Сертификат охранника 'Осёл'","Мешок с мясом","Скин: Маршмеллоу (ID: 844)","Рука бесконечности(+13)","Парящий скейтборд","Обрез (активный аксессуар)(+10)"],"items_buy":{},"price_sell":[5000000,19700000,1900000,7500000,8300000,4000000,800000,8300000,7500000,11000000,22500000,4500000,3900000,1050000,1300000,8300000,3000000,6300000],"price_buy":{},"count_sell":[1,1,1,1,1,1,1,1,1,1,1,1,1,1,1,1,1,1],"count_buy":{},"ostime":1750386139,"LavkaUid":72},{"username":"[15]Kendo_Risson","items_sell":["Мидас","Элитная переносная лавка(+7)","Велосипед на спину(+12)","Ангельское кольцо на голову(+9)","Щит Капитана Америки(+12)","Автомат AK47(+8)","Мешок с мясом(+10)","Наушники 'beats by Dre'(+13)","Кровавые крылья(+13)","Нимб из Покеболлов(+6)","Скин: CRZ-8 (ID: 827)(+12)","Магический воздушный шар #3(+12)","Инструкция для разбора аксессуара","Шлем штурмовика(+12)","Нимб кольца всевластия(+12)","Скин: Люси (ID: 848)(+8)","Скин: Normal Ped (ID: 22)","Магический топор(+13)","Кенгурятник Мародера","Эксклюзивная шляпа 1(+12)","Воздушный шар Хасбик","Ангельское кольцо на голову(+12)","Сертификат охранника 'Rifa'","Парящий скейтборд","Скин: Рилай (ID: 927)(+8)","Анимированный Пончиковый нимб(+12)","Маски Хищника","Нимб Ветвь мира","Нимб Ветвь мира","Нимб Ветвь мира","Эксклюзивная шляпа 2","Кепка 'Ralph Lauren'","Бронежилет «Южный Парк»(+12)","Скин: Девушка в хиджабе (ID: 853)(+10)","Бензопила на спину(+4)","Бронежилет «Южный Парк»(+8)","Скин: Призрачный гонщик (ID: 965)(+8)","Скин: Мидас (ID: 806)(+10)","Магический воздушный шар #4(+10)","Сертификат охранника 'Дмитрий Гордон'","Сертификат охранника 'Хэнсер'","Сертификат охранника 'Varrios Los Aztecas'","Скин: Призрачный гонщик (ID: 965)","Энергетический скейтборд","Монета основания","Респиратор","Старая карта кладов","Старая карта кладов","Старая карта кладов","Старая карта кладов"],"items_buy":{},"price_sell":[4500000,11600000,1500000,2000000,4000000,500000,1500000,3500000,12000000,1500000,5000000,11000000,80000,1000000,17000000,2500000,14000000,7000000,2900000,4000000,600000,3500000,1500000,3500000,2150000,3500000,300000,1000000,1000000,1000000,500000,200000,11500000,8000000,800000,8700000,1000000,2500000,12000000,4100000,4100000,3000000,1500000,3700000,346,990000,200000,200000,200000,200000],"price_buy":{},"count_sell":[1,1,1,1,1,1,1,1,1,1,1,1,23,1,1,1,1,1,1,1,1,1,1,1,1,1,1,1,1,1,1,1,1,1,1,1,1,1,1,1,1,1,1,1,71,1,1,1,1,1],"count_buy":{},"ostime":1750386133,"LavkaUid":26},{"username":"[04]Baadur_Jobava","items_sell":["Зловещая монета","Ларец пилота","Семейная монета","Монета охотника","Подарок","Сертификат охранника 'Лис Ник'","Рецепт: Кольцо всевластия","Бронежилет Versus","Секретный аксессуар","Ларец Arizona","Пасхальный ларец 2024","Ларец Fortnite","Ларец хэллоуина 2022","Ларец кастомных аксессуаров","Супер авто-ящик","Серебряная рулетка","Монета основания","Опыт депозита","Опыт депозита","Золотая рулетка","Бронзовая рулетка","Хлопок","Хлопок","Хлопок","Хлопок"],"items_buy":{},"price_sell":[4000,5800,41,55,300,150000,45000,150000,140000,8800,2800,2500,6500,3300,4300,1130,500,5800,5800,4900,220,90,90,90,90],"price_buy":{},"count_sell":[25,3,90,390,479,1,1,1,1,20,5,5,1,1,1,1,194,100,84,1,5,600,309,600,600],"count_buy":{},"ostime":1750386171,"LavkaUid":69},{"username":"[30]Delta_Freehouse","items_sell":{},"items_buy":["Монета Миража","Осколок секретного аксессуара","Секретный аксессуар","Осколок NFT контейнера","Серебряная рулетка","Золотая рулетка","Платиновая рулетка","Гражданский талон","Семейный талон","AZ-Монеты (Передаваемые)","Подарок","Супер охлаждающая жидкость для видеокарты","Охлаждающая жидкость для видеокарты","Смазка для разгона видеокарты","Осколок Бронежилета Генерала","Темная материя","Алмазный камень","Шахтерский сплав","Прочная ткань","Воздушный шар #1","Осколок Тайника Собирателя","Супер-грабли","Супер-кирка","Заточка +13","Осколок предмета Заточка +13","Ангельское кольцо на голову","Платиновый ящик с секретной машиной","Ящик рыболова","Осколок ящика секретной машины","Платиновый осколок ящика секретной машины","Ящик с секретной машиной","Сертификат Дополнения VIP","Сертификат на безлимитную доставку бочек","Талон на 12 x4 PayDay (передаваемый)","Мешок с мясом","Сироп характеристик актера","Старая карта кладов","Восстановленная карта кладов","Флешка майнера","Рулеточный компас","Скидочный талон","Заточка для бронежилета","Рыбная монета","Рыбная приманка","Талон снятия предупреждений","Алюминий","Вечный индикатор голода","Эхолот для рыбалки","Зловещая монета","Точильный амулет","Super Car Box","Concept Car Luxury","Ларец рыболова","Ларец с премией","Супер авто-ящик","Супер мото-ящик","Ларец крафтера","Ларец семейных охранников","Ларец Водителя Автобуса","Ларец инкассатора","Ларец дальнобойщика","Ларец хэллоуина 2022","Ларец Arizona","Рандомный Ларец","Rare Box Blue","Rare Box Red","Rare Box Yellow","Ларец Vice City","Ларец Tidex","Ларец петуха","Ларец развозчика продуктов","Ларец кладоискателя","Ларец Mortal Combat","Ящик Marvel","Ящик Minecraft","Ящик Джентельменов","Все навыки стрельбы","Улучшение Большие карманы","Супер-заточка","Талон: +1 EXP (Передаваемые)","Снегоуборочный бампер [деталь тюнинга]","Чип-тюнинг (STAGE 3)","Турбокомпрессор (sport+)","Тормоза (sport+)","Подвеска (sport+)","Распредвал (sport+)","Сцепление (sport+)","Нагнетатель (sport+)","КПП (sport+)","Дифференциал (sport+)","Коленвал (sport+)","Осколок Летающий BMW X5","Осколок Летающий Mercedes ML350","Осколок Летающий Range Rover","Осколок объекта Сарай Миража","Осколок супер-лопаты","Камень","Монета охотника","Багажник","Древесина высшего качества","Обнуление пробега для авто","Лён","Хлопок","Точильный камень","Неоновая подсветка (настраиваемая)","Подиум [деталь тюнинга]","Полицейская мигалка [деталь тюнинга]","Улучшение для автомобиля","Twin Turbo","Twin Turbo (2 уровня)","Велосипед на спину","Дельтаплан на спину","Маска-невидимка","Жареное мясо оленины","Коса Марси","Тайник Vice City","Осколок Истока","Металл","Современная карта кладов","Ларец мусорщика","Редкие материалы","Админ зарплата","Золото","Серебро","Логотип FBI [деталь тюнинга]","Серебряный кейс"],"price_sell":{},"price_buy":[4200,11000,55000,230000,850,4300,5100,96,220,530,170,3500,1850,11000,30000,60000,8000,55000,65000,3200000,250000,1500000,3800000,4000000,640000,1600000,2000000,500000,10000,175000,300000,2000000,2050000,1050000,750000,800000,75000,450000,1000000,625000,1000,9500,750,650000,270000,8000,220000,450000,2000,2000,3000,3000,2200,1600,2300,1000,2800,2300,2900,3700,2300,3200,5500,1000,890,890,890,1000,1000,2000,1750,1700,500,600,600,600,400000,25000,40000,100,750000,180000,105000,105000,105000,105000,105000,105000,105000,105000,105000,1350000,1350000,1500000,6500000,150000,450,30,50000,450,8000,45,45,300,50000,300000,125000,25000,75000,3100000,700000,800000,4000000,700,7500000,5500000,1500,2300,3900000,1200,3500,1100,950,220,120000,150000],"count_sell":{},"count_buy":[140,30,10,4,5000,1300,400,10000,1000,380,2000,100,100,100,400,40,100,10,10,1,4,1,1,1,1,1,1,1,100,8,1,1,1,1,1,1,1,1,1,1,10,30,1000,1,1,200,1,1,500,500,500,500,500,500,500,500,500,500,500,500,500,500,500,500,500,500,500,500,500,500,500,500,500,500,500,500,1,1,30,1000,1,1,1,1,1,1,1,1,1,1,1,1,1,1,1,5,3000,20000,1,300,1,5000,5000,500,1,1,1,1,1,1,1,1,1,400,1,1,100,500,1,250,1500,1000,3500,5000,1,1],"ostime":1750386145,"LavkaUid":1},{"username":"[07]Amiko_Ohayashi","items_sell":["Монета основания","Древесина высшего качества","Древесина высшего качества","Древесина высшего качества","Древесина высшего качества","Древесина высшего качества","Древесина высшего качества","Древесина высшего качества","Древесина высшего качества","Древесина высшего качества","Древесина высшего качества","Древесина высшего качества","Древесина высшего качества","Древесина высшего качества","Древесина высшего качества","Древесина высшего качества","Древесина высшего качества","Древесина высшего качества","Древесина высшего качества","Древесина высшего качества","Древесина высшего качества","Древесина высшего качества","Древесина высшего качества","Древесина высшего качества","Древесина высшего качества","Древесина высшего качества","Древесина высшего качества","Древесина высшего качества","Древесина высшего качества","Древесина высшего качества","Древесина высшего качества","Древесина высшего качества","Древесина высшего качества","Древесина высшего качества","Древесина высшего качества","Древесина высшего качества","Древесина высшего качества","Древесина высшего качества","Древесина высшего качества","Древесина высшего качества","Древесина высшего качества","Древесина высшего качества","Древесина высшего качества","Древесина высшего качества","Древесина высшего качества","Древесина высшего качества","Древесина высшего качества","Древесина высшего качества","Древесина высшего качества","Древесина высшего качества","Древесина высшего качества","Древесина высшего качества","Древесина высшего качества","Древесина высшего качества","Древесина высшего качества","Древесина высшего качества","Древесина высшего качества","Древесина высшего качества","Древесина высшего качества","Древесина высшего качества","Древесина высшего качества","Древесина высшего качества","Древесина высшего качества","Древесина высшего качества","Древесина высшего качества","Древесина высшего качества","Древесина высшего качества","Древесина высшего качества","Древесина высшего качества","Древесина высшего качества","Древесина высшего качества","Древесина высшего качества","Древесина высшего качества","Древесина высшего качества","Древесина высшего качества","Древесина высшего качества","Древесина высшего качества","Древесина высшего качества","Древесина высшего качества","Древесина высшего качества","Древесина высшего качества","Древесина высшего качества","Древесина высшего качества","Древесина высшего качества","Древесина высшего качества","Древесина высшего качества","Древесина высшего качества"],"items_buy":{},"price_sell":[555,1425,1425,1425,1425,1425,1425,1425,1425,1425,1425,1425,1425,1425,1425,1425,1425,1425,1425,1425,1425,1425,1425,1425,1425,1425,1425,1425,1425,1425,1425,1425,1425,1425,1425,1425,1425,1425,1425,1425,1425,1425,1425,1425,1425,1425,1425,1425,1425,1425,1425,1425,1425,1425,1425,1425,1425,1425,1425,1425,1425,1425,1425,1425,1425,1425,1425,1425,1425,1425,1425,1425,1425,1425,1425,1425,1425,1425,1425,1425,1425,1425,1425,1425,1425,1425,1425],"price_buy":{},"count_sell":[498,300,300,300,300,300,300,300,300,300,300,300,300,300,300,300,300,300,300,300,300,300,300,300,300,300,300,300,300,300,300,300,300,300,300,300,300,300,300,300,300,300,300,300,300,300,300,300,300,300,300,300,300,300,300,300,300,300,300,300,300,300,300,300,300,300,300,300,300,300,300,300,300,300,300,300,300,300,300,300,300,300,300,300,300,300,54],"count_buy":{},"ostime":1750386165,"LavkaUid":74},{"username":"[15]Kisa_Kunteynir","items_sell":["Голова дьявола"],"items_buy":{},"price_sell":[230000],"price_buy":{},"count_sell":[1],"count_buy":{},"ostime":1750386138,"LavkaUid":33},{"username":"[02]Katrin_Haf","items_sell":["Заточка для оружия","Заточка для оружия","Заточка для оружия","Заточка для оружия"],"items_buy":{},"price_sell":[175000,175000,175000,175000],"price_buy":{},"count_sell":[50,50,50,28],"count_buy":{},"ostime":1750386172,"LavkaUid":66},{"username":"[10]Majorka_Immortal","items_sell":["Шар авантюриста","Охлаждающая жидкость для видеокарты","Охлаждающая жидкость для видеокарты","Охлаждающая жидкость для видеокарты","Охлаждающая жидкость для видеокарты","Охлаждающая жидкость для видеокарты","Охлаждающая жидкость для видеокарты","Охлаждающая жидкость для видеокарты","Охлаждающая жидкость для видеокарты","Скин: Аанг (ID: 815)(+10)","Танго(+8)","Алмазная кирка(+13)","Танго(+12)","Маска череп(+8)","Ларец Arizona","Ларец мусорщика","Бандитский респект","Ларец испытателя (Mobile 2.1)","Секретный аксессуар","Шар авантюриста","Ларец Олигарха","Ностальгический ящик","Ларец Mortal Combat","Точильный амулет","Супер авто-ящик","Уголь","Rare Box Yellow","Рандомный Ларец","Ларец Fortnite","Переносной ларек (3)","Ларец хэллоуина 2022","Ларец петуха","Ларец Водителя Автобуса","Талон: +1 EXP (Передаваемые)","Пасхальный ларец 2024","Rare Box Red","Ящик Джентельменов","Ларец инкассатора","Ящик Marvel","Ларец семейных охранников","Зловещая монета","Rare Box Blue","Скидочный талон","Опыт депозита","Полицейская мигалка [деталь тюнинга]","Ларец крафтера","Ларец Vice City","Ларец организации","Переносной ларек (2)","Видеокарта","Серебро","Бронза","Камень","Камень","Темная материя","Серебряная рулетка","Хлопок","Хлопок","Хлопок","Хлопок","Хлопок","Хлопок","Хлопок","Хлопок","Хлопок","Хлопок","Хлопок"],"items_buy":{},"price_sell":[150000,3100,3100,3100,3100,3100,3100,3100,3100,15000000,3500000,5200000,4500000,8000000,8500,4000,90,3000,150000,150000,2500,2900,1400,4500,4700,14000,2000,2200,2700,110000,6700,5000,3900,600,3000,1900,1250,5500,1500,4000,4500,1600,10000,6200,180000,4000,2000,1000,80000,1100000,275,385,550,550,85000,1056,75,75,75,75,75,75,75,75,75,75,75],"price_buy":{},"count_sell":[1,100,100,100,100,100,100,23,100,1,1,1,1,1,99,21,500,10,1,1,7,11,5,10,18,11,17,19,14,1,3,15,25,3,21,7,9,6,5,6,9,6,2,54,1,15,10,6,1,1,48,120,320,456,5,1,160,600,600,600,246,2,476,600,511,600,152],"count_buy":{},"ostime":1750386160,"LavkaUid":71},{"username":"[21]Harya_Herrington","items_sell":["Нимб из Покеболлов","Нимб из Покеболлов","Мешок с мясом","Мешок с мясом","Энергетический махинатор"],"items_buy":{},"price_sell":[1250000,1250000,1100000,1100000,104000000],"price_buy":{},"count_sell":[1,1,1,1,1],"count_buy":{},"ostime":1750386180,"LavkaUid":81},{"username":"[07]Zloy_Goose","items_sell":["Парашют желтый","Дрова","Горящий щит","Горящий щит","Зверушка","Зверушка","Скин: Энит (ID: 902)","Инструкция для разбора аксессуара","Хлопок","Золото","Серебряная рулетка","Мантия из тентаклей","Хедкраб","Серебро","Точильный амулет","Наклейка череп [деталь тюнинга]","Наклейка череп [деталь тюнинга]","Задний отбойник Попка","Материалы","Объект: Объект Ничоси","Осколок секретного аксессуара","Подарок","Талон для охранника: +1 EXP","Сертификат охранника 'Bikers Warlock'","Пляжный лежак","Пикачу","Кошелёк (Бумажник)","Кошелёк (Бумажник)","Кошелёк (Бумажник)","Кошелёк (Бумажник)","Бронзовая рулетка","Счастливая травка","Лезвия ниндзи","Осколок Голова Робокоп","Декоративная арка","Декоративная арка","Объект: Геймпад","Объект: Геймпад","Туристический рюкзак (белый) [деталь тюнинга]","Карта VIP рекламщика","Лён","Танго(+8)","Пасхальный бронежилет (3)(+5)","Крылья Золотого ангела","Новогодний компаньон(+8)","Объект: Пасхальные домики","Бронежилет Горящий пес","Рюкзак 'Louis Vuitton'","Скин: Майнкрафт (ID: 365)","Скин: Майнкрафт (ID: 370)","Скин: Майнкрафт (ID: 373)","Скин: Майнкрафт (ID: 367)","Скин: Майнкрафт (ID: 369)","Скин: Майнкрафт (ID: 366)","Скин: Майнкрафт (ID: 374)","Задний отбойник Генератор","Задний отбойник Генератор","Скин: Кратос (ID: 728)(+8)","Скин: Кратос (ID: 728)(+7)","Объект: Бамбуковые заросли","Объект: Бамбуковые заросли","Зловещая монета","Редкие материалы","Киберпанковские VR-очки(+12)","Бронежилет Горящий пес(+2)","Увеличенный магазин (X3) для Colt 45","Рецепт: Коса марси","Монета охотника","Семейный талон","Задний отбойник Спойлер с закисью","Бандитская сумка(1)","Объект: Змея (символ 2025)"],"items_buy":{},"price_sell":[90000,14,55000,55000,100000,100000,1000000,70000,83,1099,1075,250000,350000,269,4444,20000,20000,95000,10,65000,19900,300,300,850000,65000,150000,850000,850000,850000,850000,230,250,550000,80000,130000,130000,75000,75000,20000,350000,75,3300000,250000,250000,600000,450000,320000,300000,50000,50000,50000,50000,50000,50000,50000,70000,70000,175000,170000,500000,500000,4000,5000,7700000,300000,25000,40000,50,320,175000,350000,65000],"price_buy":{},"count_sell":[1,490,1,1,1,1,1,2,3,2,19,1,1,19,4,1,1,1,1693,1,63,8,17,1,1,1,1,1,1,1,39,252,1,1,1,1,1,1,1,1,20,1,1,1,1,1,1,1,1,1,1,1,1,1,1,1,1,1,1,1,1,5,7,1,1,1,1,320,13,1,1,1],"count_buy":{},"ostime":1750386146,"LavkaUid":2},{"username":"[02]Leonid_Shmid","items_sell":["Огненная кирка(+13)","Маска 'Wrench'","Часы 'Rolex Submariner'(+13)"],"items_buy":{},"price_sell":[20500000,10500000,9500000],"price_buy":{},"count_sell":[1,1,1],"count_buy":{},"ostime":1750386172,"LavkaUid":78},{"username":"[17]Dante_Zogratis","items_sell":["Скин: Пауэр (ID: 906)","Энергетический воздушный шар(+13)","Бронежилет «Невермор»(+12)","Нимб кольца всевластия(+12)","Улучшенный сироп характеристик актера","Ангельское кольцо на голову"],"items_buy":{},"price_sell":[24500000,31000000,18000000,13000000,9000000,3500000],"price_buy":{},"count_sell":[1,1,1,1,1,1],"count_buy":{},"ostime":1750386187,"LavkaUid":79},{"username":"[12]Mentol_Monopoly","items_sell":{},"items_buy":["Опыт депозита","Темная материя","Алмазный камень","Прочная ткань","Шахтерский сплав","Осколок Тайника Собирателя","Осколок ящика секретной машины","Осколок секретного аксессуара","Осколок Истока","Осколок Бронежилета Генерала","Талон на смену никнейма","Уголь","Зловещая монета","Монета Миража","AZ-Монеты (Передаваемые)","Кусок редкой ткани","Лён","Хлопок","Сырое мясо оленины","Жареное мясо оленины","Тушка оленя","Заточка для бронежилета","Подарок","Гражданский талон","Семейный талон","Скидочный талон","Бронзовая рулетка","Серебряная рулетка","Золотая рулетка","Платиновая рулетка","Древесина высшего качества","Счастливая травка","Точильный камень","Точильный амулет","Алюминий","Камень","Металл","Серебро","Золото","Бронза","Чип-тюнинг (STAGE 2)","Коленвал (sport)","Распредвал (sport)","Турбокомпрессор (sport)","Нагнетатель (sport)","Сцепление (sport)","КПП (sport)","Дифференциал (sport)","Подвеска (sport)","Тормоза (sport)","Чип-тюнинг (STAGE 3)","Коленвал (sport+)","Турбокомпрессор (sport+)","Нагнетатель (sport+)","Сцепление (sport+)","КПП (sport+)","Дифференциал (sport+)","Подвеска (sport+)","Распредвал (sport+)","Тормоза (sport+)","Ларец Mortal Combat","Ящик Marvel","Ящик Джентельменов","Ящик Minecraft","Ларец петуха","Супер мото-ящик","Супер авто-ящик","Ностальгический ящик","Ларец Олигарха","Ларец организации","Ларец кастомных аксессуаров","Ларец Arizona","Ларец Fortnite","Ларец крафтера","Ларец с премией","Rare Box Yellow","Rare Box Blue","Rare Box Red","Одежда из секонд-хенда","Ларец дальнобойщика","Ларец Водителя Автобуса","Concept Car Luxury","Super Car Box","Ларец инкассатора","Ларец рыболова","Ларец Tidex","Рандомный Ларец","Ларец кладоискателя","Ларец пилота","Ларец развозчика продуктов","Ларец Vice City","Охлаждающая жидкость для видеокарты","Смазка для разгона видеокарты","Талон: +1 EXP (Передаваемые)","Неон - Красный [деталь тюнинга]","Неон - Синий [деталь тюнинга]","Неон - Желтый [деталь тюнинга]","Неон - Розовый [деталь тюнинга]","Неон - Белый [деталь тюнинга]","Неон - Зеленый [деталь тюнинга]","Неоновая подсветка (настраиваемая)","Гидравлика (управляемая)","Улучшение для автомобиля","Twin Turbo","Снегоуборочный бампер [деталь тюнинга]","Черепаха [деталь тюнинга]","Шипы [деталь тюнинга]","Попугай [деталь тюнинга]","Катана [деталь тюнинга]","Логотип FBI [деталь тюнинга]","Сердце [деталь тюнинга]","Рога [деталь тюнинга]","Кальян [деталь тюнинга]","Доска для сёрфинга [деталь тюнинга]","Полицейская мигалка [деталь тюнинга]","Полицейская мигалка (активная)","Ящик с секретной машиной","Сироп характеристик актера","Бензопила на спину","Супер-кирка","Супер-грабли","Супер-лопата","Модификация Соник","Скин: CJ (ID: 74)","Продажа фишек без комиссии","Осколок супер-лопаты","Улучшение Большие карманы","Заточка +13","Золотой кейс","Кейс 'Diamond'","Лицензия дипломата","Разрешение на улучшение наземной нефтевышки","Сертификат на безлимитную доставку бочек","Дополнительная комната","Платиновый осколок ящика секретной машины","Рулеточный компас","Все навыки стрельбы","Ящик рыболова","Сертификат Дополнения VIP","Талон снятия предупреждений","Осколок предмета Заточка +13","Осколок Рука бесконечности","Осколок Молот Тора","Осколок Шлем железного человека","Осколок Русский боевой топор","Осколок Щит Капитана Америки","Осколок NFT контейнера","Восстановленная карта кладов","Вечный индикатор голода","Дельтаплан на спину","Велосипед на спину"],"price_sell":{},"price_buy":[3850,60000,8000,80000,65000,150000,11000,10000,8500,25000,15000,8000,1500,4500,550,3250,40,40,250,250,500,10000,160,75,200,5500,120,650,3000,4900,500,50,200,2100,8000,450,2300,170,600,400,30000,20000,20000,20000,20000,20000,20000,20000,20000,20000,150000,100000,90000,90000,90000,90000,90000,90000,90000,90000,600,600,600,600,2300,850,2500,1400,1300,400,2300,3500,1800,2500,1400,800,800,800,1000,2400,2300,2600,2900,2000,2000,800,800,1200,2800,1100,500,2250,10500,200,60000,60000,60000,60000,60000,60000,50000,160000,32000,120000,550000,60000,50000,50000,50000,70000,50000,50000,50000,40000,120000,130000,400000,900000,50000,3800000,1550000,700000,65000,550000,50000,125000,30000,3900000,500000,550000,1200000,1900000,1900000,1100000,150000,600000,400000,550000,2100000,250000,650000,500000,700000,200000,550000,500000,170000,500000,350000,700000,700000],"count_sell":{},"count_buy":[200,10,15,15,20,3,10,10,10,20,1,50,100,50,300,50,5000,5000,100,200,100,15,2000,5000,1000,3,1000,350,150,100,200,1000,300,100,50,1000,100,2000,300,500,1,1,1,1,1,1,1,1,1,1,1,1,1,1,1,1,1,1,1,1,300,300,300,300,100,100,100,100,100,300,100,100,100,100,100,100,100,100,200,100,100,100,100,10,150,100,200,200,100,100,100,100,30,1000,1,1,1,1,1,1,1,1,1,1,1,1,1,1,1,1,1,1,1,1,1,1,1,1,1,1,1,1,1,1,1,1,1,1,1,1,1,1,1,1,5,1,1,1,1,1,1,1,1,1,1,1,1,1,1,1,1],"ostime":1750386164,"LavkaUid":68},{"username":"[04]Aska_Vialpando","items_sell":{},"items_buy":{},"price_sell":{},"price_buy":{},"count_sell":{},"count_buy":{},"ostime":1750386191,"LavkaUid":77},{"username":"[30]Lim_Cuirass","items_sell":["Нашивка на аксессуар(защита)","Нашивка на аксессуар(защита)","Нашивка на аксессуар(защита)","Нашивка на аксессуар(защита)","Нашивка на аксессуар(защита)","Нашивка на аксессуар(защита)","Нашивка на аксессуар(защита)","Нашивка на аксессуар(защита)","Нашивка на аксессуар(защита)","Прочная ткань","Прочная ткань","Прочная ткань","Прочная ткань","Прочная ткань","Прочная ткань","Прочная ткань","Прочная ткань","Прочная ткань","Прочная ткань","Шахтерский сплав","Шахтерский сплав","Шахтерский сплав","Шахтерский сплав","Шахтерский сплав","Шахтерский сплав","Шахтерский сплав","Шахтерский сплав","Шахтерский сплав","Шахтерский сплав","Шахтерский сплав","Шахтерский сплав","Шахтерский сплав","Шахтерский сплав","Шахтерский сплав","Скин: Маскхалат(М) (ID: 444)(+12)","Темная материя","Темная материя","Темная материя","Темная материя","Темная материя","Темная материя","Темная материя","Темная материя","Темная материя","Ларец с премией","Смазка для разгона видеокарты","Смазка для разгона видеокарты","Смазка для разгона видеокарты","Смазка для разгона видеокарты","Смазка для разгона видеокарты","Смазка для разгона видеокарты","Смазка для разгона видеокарты","Смазка для разгона видеокарты","Смазка для разгона видеокарты","Смазка для разгона видеокарты","Смазка для разгона видеокарты","Смазка для разгона видеокарты","Смазка для разгона видеокарты","Смазка для разгона видеокарты","Смазка для разгона видеокарты","Смазка для разгона видеокарты","Смазка для разгона видеокарты","Смазка для разгона видеокарты","Смазка для разгона видеокарты","Смазка для разгона видеокарты","Смазка для разгона видеокарты","Смазка для разгона видеокарты","Смазка для разгона видеокарты","Смазка для разгона видеокарты","Смазка для разгона видеокарты","Смазка для разгона видеокарты","Смазка для разгона видеокарты","Смазка для разгона видеокарты","Смазка для разгона видеокарты","Смазка для разгона видеокарты","Смазка для разгона видеокарты","Смазка для разгона видеокарты","Смазка для разгона видеокарты","Смазка для разгона видеокарты","Смазка для разгона видеокарты","Смазка для разгона видеокарты","Смазка для разгона видеокарты","Смазка для разгона видеокарты","Смазка для разгона видеокарты","Смазка для разгона видеокарты","Смазка для разгона видеокарты","Смазка для разгона видеокарты","Смазка для разгона видеокарты","Смазка для разгона видеокарты","Смазка для разгона видеокарты","Смазка для разгона видеокарты","Смазка для разгона видеокарты","Смазка для разгона видеокарты","Смазка для разгона видеокарты","Смазка для разгона видеокарты","Смазка для разгона видеокарты","Смазка для разгона видеокарты","Смазка для разгона видеокарты","Смазка для разгона видеокарты","Смазка для разгона видеокарты","Смазка для разгона видеокарты","Смазка для разгона видеокарты","Смазка для разгона видеокарты","Смазка для разгона видеокарты","Смазка для разгона видеокарты","Смазка для разгона видеокарты","Смазка для разгона видеокарты","Смазка для разгона видеокарты","Смазка для разгона видеокарты","Смазка для разгона видеокарты","Смазка для разгона видеокарты","Смазка для разгона видеокарты","Смазка для разгона видеокарты","Смазка для разгона видеокарты","Смазка для разгона видеокарты","Смазка для разгона видеокарты","Смазка для разгона видеокарты"],"items_buy":{},"price_sell":[2349000,2349000,2349000,2349000,2349000,2349000,2349000,2349000,2349000,121990,121990,121990,121990,121990,121990,121990,121990,121990,121990,85480,85480,85480,85480,85480,85480,85480,85480,85480,85480,85480,85480,85480,85480,85480,2199000,86990,86990,86990,86990,86990,86990,86990,86990,86990,2999,12490,12490,12490,12490,12490,12490,12490,12490,12490,12490,12490,12490,12490,12490,12490,12490,12490,12490,12490,12490,12490,12490,12490,12490,12490,12490,12490,12490,12490,12490,12490,12490,12490,12490,12490,12490,12490,12490,12490,12490,12490,12490,12490,12490,12490,12490,12490,12490,12490,12490,12490,12490,12490,12490,12490,12490,12490,12490,12490,12490,12490,12490,12490,12490,12490,12490,12490,12490,12490,12490,12490,12490],"price_buy":{},"count_sell":[1,1,1,1,1,1,1,1,1,150,160,160,155,200,115,195,200,172,200,152,189,200,50,200,180,200,200,200,200,200,200,200,199,198,1,40,28,10,18,50,50,46,50,50,4,2,100,100,100,100,100,100,100,100,100,100,100,100,100,100,100,100,100,100,100,100,100,100,100,100,100,100,100,100,100,100,100,100,100,100,100,100,100,100,100,100,100,100,100,78,100,100,100,100,100,100,100,100,100,100,100,100,100,100,100,100,100,100,100,100,100,100,100,100,100,100,100],"count_buy":{},"ostime":1750386177,"LavkaUid":75},{"username":"[07]Santiago_Escobar","items_sell":["Золотая рулетка","Осколок Бронежилета Генерала","Серебряная рулетка","Редкие материалы","Камень пространства","Камень бесконечности","Ларец с премией","Ларец кладоискателя","Сет: Охранник из Игры в Кальмара","Бронзовая рулетка","Ларец Arizona","Micro Tec-9","Micro Tec-9","Micro Tec-9","Micro Tec-9","Micro Tec-9","Micro Tec-9","Micro Tec-9","Micro Tec-9","Micro Tec-9","Micro Tec-9","Micro Tec-9","Micro Tec-9","Micro Tec-9","Micro Tec-9","Micro Tec-9","Ларец крафтера","Инструкция для разбора скинов","Семейный талон","Гражданский талон","Одежда из секонд-хенда"],"items_buy":{},"price_sell":[4300,42000,1100,4000,2000000,2000000,2500,3000,20000000,220,8500,37,37,37,37,37,37,37,37,37,37,37,37,37,37,37,4000,150000,300,140,1800],"price_buy":{},"count_sell":[3,7,7,5,1,5,24,35,1,29,50,500,500,500,491,500,500,500,383,500,500,500,500,500,500,500,12,19,11,80,2],"count_buy":{},"ostime":1750386144,"LavkaUid":70},{"username":"[09]Hell_Reey","items_sell":["Танго(+13)","Амулеты анкх(+13)","Оранжевая магическая шляпа","Увеличенный магазин (X3) для Sawnoff","Twin Turbo"],"items_buy":{},"price_sell":[18000000,30000000,2000000,15000000,200000],"price_buy":{},"count_sell":[1,1,1,1,1],"count_buy":{},"ostime":1750386142,"LavkaUid":18},{"username":"[06]Vitek_Balenciaga","items_sell":["Магический воздушный шар #1(+12)","Магический воздушный шар #2(+7)","Магический воздушный шар #2(+12)"],"items_buy":{},"price_sell":[11350000,10800000,11350000],"price_buy":{},"count_sell":[1,1,1],"count_buy":{},"ostime":1750386165,"LavkaUid":84},{"username":"[01]Tif_Cloud","items_sell":["Тормоза (sport+)","Скин: Джек рождественский (ID: 912)(+10)","Скин: Дива (ID: 947)","Скин: Дива (ID: 947)","Маска для пугания","Маска для пугания","Скин: Леорик (ID: 923)(+9)","Скин: Леорик (ID: 923)","Скин: Леорик (ID: 923)","Скин: Леорик (ID: 923)","Личная визитка","Бронежилет","Хлопок","Хлопок","Лён","Лён","Крылья Марси","Темная материя","Талон снятия предупреждений","Охлаждающая жидкость для видеокарты","Охлаждающая жидкость для видеокарты","Охлаждающая жидкость для видеокарты","Охлаждающая жидкость для видеокарты","Гибридная установка","Гибридная установка","Гибридная установка","Гибридная установка","Улучшение Большие карманы","Улучшение Большие карманы","Улучшение Большие карманы","Улучшение Большие карманы","Кокос","Кокос","Кокос","Кокос","Кокос","Кокос","Кокос","Кокос","Кокос","Улучшение для автомобиля","Улучшение для автомобиля","Инструкция для разбора аксессуара","Рыбная монета","Бронза","Бронза","Бронза","Бронза","Бронза","Бронза","Бронза","Бронза","Осколок Истока","Ларец Fortnite","Древесина высшего качества","Скидочный талон","Super Car Box","Подарок","Ларец Олигарха","Ларец с премией","Камень","Гражданский талон","Платиновая рулетка","Twin Turbo","Серебряная рулетка","Золотая рулетка","Бронзовая рулетка"],"items_buy":{},"price_sell":[170000,3950000,250000,250000,150000,150000,410000,390000,390000,390000,75000,500,85,85,85,85,500000,82000,430000,3400,3400,3400,3400,50000,50000,50000,50000,100000,100000,100000,100000,150,150,150,150,150,150,150,150,150,99000,99000,75000,1200,500,500,500,500,500,500,500,500,21000,2560,800,9950,4000,300,1950,2700,600,144,6800,205000,1300,4500,229],"price_buy":{},"count_sell":[1,1,1,1,1,1,1,1,1,1,1,1,600,40,600,546,1,3,1,11,100,100,69,1,1,1,1,1,1,1,1,100,100,100,100,100,100,100,100,80,1,1,2,92,600,600,600,600,103,600,600,600,28,34,54,14,3,908,3,8,484,16,6,1,7,2,5],"count_buy":{},"ostime":1750386161,"LavkaUid":86},{"username":"[02]John_Barrow","items_sell":{},"items_buy":["Дельтаплан на спину","Велосипед на спину","Rare Box Yellow","Rare Box Blue","Rare Box Red","Одежда из секонд-хенда","Concept Car Luxury","Super Car Box","Ларец с премией","Ларец Олигарха","Ларец кастомных аксессуаров","Ларец организации","Ларец крафтера","Ларец дальнобойщика","Ларец Mortal Combat","Ларец Водителя Автобуса","Ларец рыболова","Рандомный Ларец","Ларец пилота","Ларец развозчика продуктов","Ларец кладоискателя","Ларец Vice City","Ларец Tidex","Ларец хэллоуина 2022","Ларец семейных охранников","Ларец петуха","Ларец испытателя (Mobile 2.1)","Ларец инкассатора","Ларец Fortnite","Пасхальный ларец 2024","Ларец Arizona","Супер авто-ящик","Супер мото-ящик","Ящик Minecraft","Ящик Marvel","Ящик Джентельменов","Ностальгический ящик","Ящик рыболова","Платиновый осколок ящика секретной машины","Осколок ящика секретной машины","Ящик с секретной машиной","Семейный талон","Гражданский талон","Талон: +1 EXP (Передаваемые)","Талон для охранника: +1 EXP","Талон на 12 x4 PayDay (передаваемый)","Скидочный талон","Талон на смену никнейма","Талон снятия предупреждений","Бронзовая рулетка","Серебряная рулетка","Рулеточный компас","Секретный аксессуар","Бронза","Зловещая монета","Монета Миража","Семейная монета","Алмазный камень","Темная материя","Шахтерский сплав","Прочная ткань","Кусок редкой ткани","Древесина высшего качества","Подарок","Осколок Бронежилета Генерала","Осколок Тайника Собирателя","Осколок предмета Заточка +13","Осколок секретного аксессуара","Осколок супер-лопаты","Осколок NFT контейнера","Флешка майнера","Охлаждающая жидкость для видеокарты","Супер охлаждающая жидкость для видеокарты","Смазка для разгона видеокарты","Точильный амулет","Точильный камень","Заточка для бронежилета","Заточка +13","Увеличенный магазин (X3) для Tec-9","Увеличенный магазин (X3) для M16","Увеличенный магазин (X3) для Sawnoff","Золотой кейс","AZ-Монеты (Передаваемые)","Восстановленная карта кладов","Вечная рабочая виза","Вечный индикатор голода","Извлекатель нашивки","Эхолот для рыбалки","Торговый ключ","Разрешение на улучшение наземной нефтевышки","Сертификат на безлимитную доставку бочек","Рыбная приманка","Логотип FBI [деталь тюнинга]","Снегоуборочный бампер [деталь тюнинга]","Полицейская мигалка [деталь тюнинга]","Шашка такси (желтая) [деталь тюнинга]","Чип-тюнинг (STAGE 3)","Twin Turbo","Twin Turbo (2 уровня)","Коленвал (sport+)","Распредвал (sport+)","Турбокомпрессор (sport+)","Нагнетатель (sport+)","Сцепление (sport+)","КПП (sport+)","Дифференциал (sport+)","Подвеска (sport+)","Тормоза (sport+)","Багажник","Неоновая подсветка (настраиваемая)","Гидравлика (управляемая)","Супер-грабли","Супер-лопата","Жареное мясо оленины","Тушка оленя","Счастливая травка","Мешок с мясом","Все навыки стрельбы","Улучшение Большие карманы","Сертификат Дополнения VIP","Опыт депозита","Осколок Истока","Желтая инструкция для разбора аксессуара","Инструкция для разбора скинов","Инструкция для разбора аксессуара","Протокол взвешивания"],"price_sell":{},"price_buy":[801000,801000,1000,1000,1000,1200,3250,3250,1500,1400,2250,450,3000,2500,600,2800,2250,1250,3750,1250,1250,1100,1100,3750,2700,2500,1100,3750,1750,1900,6000,3000,1100,600,600,600,1750,600000,150000,15000,450000,225,90,375,75,1150000,5000,17500,275000,175,800,700000,9000,325,3100,6000,15,9500,75000,75000,107500,3250,450,175,30000,250000,700000,10000,100000,175000,1250000,2250,3750,10500,3250,350,12500,4100000,250000,250000,8500000,550000,600,550000,20000,300000,10000,500000,25000,2100000,2100000,950000,100000,700000,100000,275000,150000,125000,3500000,90000,90000,90000,90000,90000,90000,90000,90000,90000,50000,55000,125000,1500000,900000,1000,1000,125,800000,400000,35000,2100000,3500,12500,150000,30000,40000,2201000],"count_sell":{},"count_buy":[1,1,75,75,75,150,250,125,250,75,75,250,100,75,50,50,125,75,75,75,75,15,15,15,15,15,15,15,15,15,35,125,125,75,75,75,125,1,1,15,1,1500,2500,250,250,1,2,1,1,2000,750,1,5,2000,250,125,1500,250,25,25,25,350,500,3000,50,1,1,35,1,1,1,400,125,150,125,250,50,1,1,1,1,1,125,1,1,1,3,1,1,1,1,1,1,1,1,1,1,1,1,1,1,1,1,1,1,1,1,1,1,1,1,1,1,750,750,3000,1,1,1,1,100,100,10,15,15,1],"ostime":1750386153,"LavkaUid":51},{"username":"[12]Mercedes_Brabus","items_sell":["Огненная кирка(+13)","Воздушный шар #3(+11)","Ледяной щит(+8)","Чемодан Bomj Gang","Магмовый топор","Увеличенный магазин (X3) для M16","Дрова","Ларец Fortnite","Монета основания","Монета охотника","Ларец Vice City","Сырое мясо оленины","Ларец крафтера","Рандомный Ларец","Древесина высшего качества","Рога [деталь тюнинга]","Ларец Tidex","Темная материя","Коленвал (sport)","Ларец Arizona","Ларец Arizona","Опыт депозита","Опыт депозита","Опыт депозита","Тормоза (sport)","Объект: Кубическое дерево"],"items_buy":{},"price_sell":[21000000,3700000,900000,3000000,1500000,450000,16,2500,540,45,2000,1440,3800,2021,750,145000,2000,85000,50000,8300,8300,5900,5900,5900,43200,1300000],"price_buy":{},"count_sell":[1,1,1,1,1,1,7930,29,167,9528,6,35,9,12,48,1,6,14,1,28,176,24,99,89,1,1],"count_buy":{},"ostime":1750386166,"LavkaUid":76},{"username":"[09]Mercury_Brazzers","items_sell":["Танго(+13)","Кровавые крылья(+12)"],"items_buy":{},"price_sell":[17500000,10700000],"price_buy":{},"count_sell":[1,1],"count_buy":{},"ostime":1750386167,"LavkaUid":63},{"username":"[09]Romashka_Mirror","items_sell":{},"items_buy":{},"price_sell":{},"price_buy":{},"count_sell":{},"count_buy":{},"ostime":1750386143,"LavkaUid":79},{"username":"[07]Mary_Salvatrucha","items_sell":{},"items_buy":["Админ зарплата","Ящик рыболова","Платиновый осколок ящика секретной машины","Осколок ящика секретной машины","Ящик с секретной машиной","Семейный талон","Гражданский талон","Талон: +1 EXP (Передаваемые)","Талон для охранника: +1 EXP","Талон на 12 x4 PayDay (передаваемый)","Скидочный талон","Талон на смену никнейма","Талон снятия предупреждений","Бронзовая рулетка","Серебряная рулетка","Золотая рулетка","Платиновая рулетка","Рулеточный компас","Секретный аксессуар","Камень","Серебро","Бронза","Золото","Металл","Алюминий","Зловещая монета","Монета Миража","Рыбная монета","Семейная монета","Алмазный камень","Темная материя","Шахтерский сплав","Прочная ткань","Уголь","Кусок редкой ткани","Древесина высшего качества","Подарок","Осколок Бронежилета Генерала","Осколок Тайника Собирателя","Осколок предмета Заточка +13","Осколок секретного аксессуара","Осколок супер-лопаты","Осколок Портальной пушки","Осколок NFT контейнера","Флешка майнера","Охлаждающая жидкость для видеокарты","Супер охлаждающая жидкость для видеокарты","Смазка для разгона видеокарты","Точильный амулет","Точильный камень","Заточка для бронежилета","Сироп характеристик актера","Увеличенный магазин (X3) для Tec-9","Увеличенный магазин (X3) для M16","Золотой кейс","Кейс 'Diamond'","AZ-Монеты (Передаваемые)","Восстановленная карта кладов","Вечная рабочая виза","Вечный индикатор голода","Извлекатель нашивки","Эхолот для рыбалки","Личная визитка","Торговый ключ","Рыбная приманка","Логотип FBI [деталь тюнинга]","Снегоуборочный бампер [деталь тюнинга]","Полицейская мигалка [деталь тюнинга]","Шашка такси (желтая) [деталь тюнинга]","Чип-тюнинг (STAGE 3)","Twin Turbo","Коленвал (sport+)","Распредвал (sport+)","Турбокомпрессор (sport+)","Нагнетатель (sport+)","Сцепление (sport+)","КПП (sport+)","Дифференциал (sport+)","Подвеска (sport+)","Тормоза (sport+)","Багажник","Неоновая подсветка (настраиваемая)","Гидравлика (управляемая)","Гибридная установка","Жареное мясо оленины","Тушка оленя","Счастливая травка","Мешок с мясом","Улучшение Большие карманы","Желтая инструкция для разбора аксессуара","Инструкция для разбора скинов","Инструкция для разбора аксессуара"],"price_sell":{},"price_buy":[1200,600000,150000,15000,450000,225,90,375,75,1150000,5000,17500,275000,175,800,4000,5500,700000,9000,425,200,325,900,2750,7250,3100,6000,750,15,9500,75000,75000,107500,10250,3250,450,175,30000,250000,700000,10000,100000,300000,175000,1250000,2250,3750,10500,3250,350,12500,1050000,250000,250000,550000,700000,600,550000,20000,300000,10000,500000,25000,25000,950000,100000,700000,100000,275000,150000,125000,90000,90000,90000,90000,90000,90000,90000,90000,90000,50000,55000,125000,15000,1000,1000,125,800000,35000,150000,30000,40000],"count_sell":{},"count_buy":[1250,1,1,15,1,1500,2500,250,250,1,2,1,1,2000,750,750,500,1,5,1500,1500,1000,1000,1000,200,200,75,250,1500,125,20,20,5,100,150,2000,3000,15,1,1,50,1,1,1,1,400,125,150,125,250,50,1,1,1,1,1,125,1,1,1,3,1,1,1,1,1,1,1,1,1,1,1,1,1,1,1,1,1,1,1,1,1,1,1,500,500,1000,1,1,10,15,25],"ostime":1750386175,"LavkaUid":85},{"username":"[31]Sber_Shakur","items_sell":["Новогодний шарф 2025","Скин: Бабка матрена (ID: 945)","Twin Turbo","Полицейская мигалка (активная)","Скин: Бабка матрена (ID: 945)"],"items_buy":{},"price_sell":[250000,200000,200000,200000,200000],"price_buy":{},"count_sell":[1,1,1,1,1],"count_buy":{},"ostime":1750386190,"LavkaUid":10}]